<?xml version="1.0" encoding="UTF-8"?>
<AssetDeclaration
	xmlns="uri:ea.com:eala:asset"
	xmlns:xsi="http://www.w3.org/2001/XMLSchema-instance">
	<Tags/>
	<Includes>
		<Include
			source="DATA:static.xml"
			type="reference"/>
		<Include
			source="DATA:global.xml"
			type="reference"/>
		<Include
			source="ART:EVDefault.xml"
			type="instance"/>
		<Include
			source="ART:TSCloudMed.xml"
			type="instance"/>
		<Include
			source="ART:TSNoiseUrb.xml"
			type="instance"/>
		<Include
			source="DATA:GlobalData/roads.xml"
			type="instance"/>
		<Include
			source="DATA:civilian/australia_as/trees/astdead01.xml"
			type="instance"/>
		<Include
			source="DATA:civilian/australia_as/trees/astdead02.xml"
			type="instance"/>
		<Include
			source="DATA:civilian/australia_as/trees/astdead03.xml"
			type="instance"/>
		<Include
			source="DATA:civilian/australia_as/trees/astdead06.xml"
			type="instance"/>
		<Include
			source="DATA:civilian/brazil_br/buildings/brboil01.xml"
			type="instance"/>
		<Include
			source="DATA:civilian/brazil_br/buildings/brboil02.xml"
			type="instance"/>
		<Include
			source="DATA:civilian/egypt_eg/buildings/cbegyruin03.xml"
			type="instance"/>
		<Include
			source="DATA:civilian/egypt_eg/buildings/cbegyruin04.xml"
			type="instance"/>
		<Include
			source="DATA:civilian/egypt_eg/buildings/cbegytent01.xml"
			type="instance"/>
		<Include
			source="DATA:civilian/egypt_eg/buildings/cbegytent02.xml"
			type="instance"/>
		<Include
			source="DATA:civilian/egypt_eg/buildings/egbmkt01_a.xml"
			type="instance"/>
		<Include
			source="DATA:civilian/egypt_eg/buildings/egbmkt01_d.xml"
			type="instance"/>
		<Include
			source="DATA:civilian/italy_it/rocks/itrocks07.xml"
			type="instance"/>
		<Include
			source="DATA:civilian/italy_it/rocks/itrocks08.xml"
			type="instance"/>
		<Include
			source="DATA:civilian/italy_it/rocks/itrocks09.xml"
			type="instance"/>
		<Include
			source="DATA:civilian/italy_it/rocks/itrocks10.xml"
			type="instance"/>
		<Include
			source="DATA:civilian/italy_it/rocks/itrocks11.xml"
			type="instance"/>
		<Include
			source="DATA:civilian/italy_it/rocks/itrocks12.xml"
			type="instance"/>
		<Include
			source="DATA:civilian/italy_it/rocks/itrocks13.xml"
			type="instance"/>
		<Include
			source="DATA:civilian/italy_it/rocks/itrocks14.xml"
			type="instance"/>
		<Include
			source="DATA:neutral/crates/moneycrate.xml"
			type="instance"/>
		<Include
			source="DATA:neutral/crates/salvagecrate.xml"
			type="instance"/>
		<Include
			source="DATA:neutral/crates/veterancycrate.xml"
			type="instance"/>
		<Include
			source="DATA:neutral/props/audioambients.xml"
			type="instance"/>
		<Include
			source="DATA:neutral/structures/civbunker.xml"
			type="instance"/>
		<Include
			source="DATA:neutral/structures/defensivetower.xml"
			type="instance"/>
		<Include
			source="DATA:neutral/structures/electromagneticpulsecontrolcenter.xml"
			type="instance"/>
		<Include
			source="DATA:neutral/structures/mutanthovel.xml"
			type="instance"/>
		<Include
			source="DATA:neutral/structures/tiberiumsilo.xml"
			type="instance"/>
		<Include
			source="DATA:neutral/structures/tiberiumspike.xml"
			type="instance"/>
		<Include
			source="DATA:sounds/musicscript_bluezone.xml"
			type="instance"/>
		<Include
			source="overrides.xml"
			type="all"/>
	</Includes>
	<GameMap
		id="erl115intothesea">
		<Waypoint
			id="Player_8_Start">
			<Position
				x="1638.99"
				y="433.658"
				z="0"/>
		</Waypoint>
		<Waypoint
			id="Player_7_Start">
			<Position
				x="2523.59"
				y="514.173"
				z="0"/>
		</Waypoint>
		<Waypoint
			id="Player_6_Start">
			<Position
				x="2551.83"
				y="1659.92"
				z="0"/>
		</Waypoint>
		<Waypoint
			id="Player_5_Start">
			<Position
				x="2404.71"
				y="2732.54"
				z="0"/>
		</Waypoint>
		<Waypoint
			id="Player_4_Start">
			<Position
				x="1270.89"
				y="2545.14"
				z="0"/>
		</Waypoint>
		<Waypoint
			id="Player_3_Start">
			<Position
				x="528.423"
				y="2707.02"
				z="0"/>
		</Waypoint>
		<Waypoint
			id="Player_2_Start">
			<Position
				x="461.263"
				y="1595.5"
				z="0"/>
		</Waypoint>
		<Waypoint
			id="Player_1_Start">
			<Position
				x="493.723"
				y="347.047"
				z="0"/>
		</Waypoint>
		<Structure
			Angle="0"
			EventList=""
			Faction="SkirmishNeutral/teamSkirmishNeutral"
			Health="500"
			Team="SkirmishNeutral"
			ThingTemplate="TiberiumSpike"
			id="TiberiumSpike">
			<Position
				x="1926.44"
				y="1683.96"
				z="0"/>
		</Structure>
		<Structure
			Angle="-1.97757"
			EventList=""
			Faction="PlyrCivilian/teamPlyrCivilian"
			Health="500"
			Team="PlyrCivilian"
			ThingTemplate="CBEgyTent02"
			id="CBEGYTENT02">
			<Position
				x="1908.14"
				y="1290.05"
				z="0"/>
		</Structure>
		<Structure
			Angle="0"
			EventList=""
			Faction="PlyrCivilian/teamPlyrCivilian"
			Health="500"
			Team="PlyrCivilian"
			ThingTemplate="CBEgyTent01"
			id="CBEGYTENT01">
			<Position
				x="1563.27"
				y="1001.04"
				z="0"/>
		</Structure>
		<Structure
			Angle="0"
			EventList=""
			Faction="PlyrCivilian/teamPlyrCivilian"
			Health="100"
			Team="PlyrCivilian"
			ThingTemplate="CBEgyTent01"
			id="CBEGYTENT01">
			<Position
				x="1063.83"
				y="1701.92"
				z="0"/>
		</Structure>
		<Structure
			Angle="0"
			EventList=""
			Faction="PlyrCivilian/teamPlyrCivilian"
			Health="100"
			Team="PlyrCivilian"
			ThingTemplate="CBEgyRuin04"
			id="CBEGYRUIN04">
			<Position
				x="1691.58"
				y="1898.84"
				z="0"/>
		</Structure>
		<Structure
			Angle="0"
			EventList=""
			Faction="PlyrCivilian/teamPlyrCivilian"
			Health="100"
			Team="PlyrCivilian"
			ThingTemplate="CBEgyRuin03"
			id="CBEGYRUIN03">
			<Position
				x="1611.02"
				y="1936.83"
				z="0"/>
		</Structure>
		<Structure
			Angle="0"
			EventList=""
			Faction="PlyrCivilian/teamPlyrCivilian"
			Health="100"
			Team="PlyrCivilian"
			ThingTemplate="Brazilian_Oil_Platform_01"
			id="Brazilian_Oil_Platform_01">
			<Position
				x="507.482"
				y="946.58"
				z="19"/>
		</Structure>
		<Structure
			Angle="0"
			EventList=""
			Faction="PlyrCivilian/teamPlyrCivilian"
			Health="100"
			Team="PlyrCivilian"
			ThingTemplate="Brazilian_Oil_Platform_01"
			id="Brazilian_Oil_Platform_01">
			<Position
				x="2532.21"
				y="2047.73"
				z="19"/>
		</Structure>
		<Structure
			Angle="0"
			EventList=""
			Faction="PlyrCivilian/teamPlyrCivilian"
			Health="100"
			Team="PlyrCivilian"
			ThingTemplate="Brazilian_Oil_Platform_02"
			id="Brazilian_Oil_Platform_02">
			<Position
				x="946.691"
				y="2434.31"
				z="43"/>
		</Structure>
		<Structure
			Angle="0"
			EventList=""
			Faction="PlyrCivilian/teamPlyrCivilian"
			Health="100"
			Team="PlyrCivilian"
			ThingTemplate="Brazilian_Oil_Platform_02"
			id="Brazilian_Oil_Platform_02">
			<Position
				x="2214.32"
				y="1136.25"
				z="43"/>
		</Structure>
		<Structure
			Angle="-0.076028"
			EventList=""
			Faction="SkirmishNeutral/teamSkirmishNeutral"
			Health="100"
			Team="SkirmishNeutral"
			ThingTemplate="TiberiumSilo"
			id="TiberiumSilo">
			<Position
				x="1460.3"
				y="1523.17"
				z="0"/>
		</Structure>
		<Structure
			Angle="1.95518"
			EventList=""
			Faction="SkirmishNeutral/teamSkirmishNeutral"
			Health="2500"
			Team="SkirmishNeutral"
			ThingTemplate="MutantHovel"
			id="MutantHovel">
			<Position
				x="1089.42"
				y="1340.53"
				z="0"/>
		</Structure>
		<Structure
			Angle="-1.05872"
			EventList=""
			Faction="SkirmishNeutral/teamSkirmishNeutral"
			Health="2500"
			Team="SkirmishNeutral"
			ThingTemplate="ElectroMagneticPulseControlCenter"
			id="ElectroMagneticPulseControlCenter">
			<Position
				x="1296.08"
				y="1897.77"
				z="0"/>
		</Structure>
		<Structure
			Angle="1.96895"
			EventList=""
			Faction="SkirmishNeutral/teamSkirmishNeutral"
			Health="500"
			Team="SkirmishNeutral"
			ThingTemplate="DefensiveTower"
			id="DefensiveTower">
			<Position
				x="1657.47"
				y="1040.02"
				z="0"/>
		</Structure>
		<Structure
			Angle="0"
			EventList=""
			Faction="SkirmishNeutral/teamSkirmishNeutral"
			Health="100"
			Team="SkirmishNeutral"
			ThingTemplate="CivBunker"
			id="CivBunker">
			<Position
				x="474.193"
				y="629.86"
				z="0"/>
		</Structure>
		<Structure
			Angle="0"
			EventList=""
			Faction="SkirmishNeutral/teamSkirmishNeutral"
			Health="100"
			Team="SkirmishNeutral"
			ThingTemplate="CivBunker"
			id="CivBunker">
			<Position
				x="645.473"
				y="481.995"
				z="0"/>
		</Structure>
		<Structure
			Angle="0"
			EventList=""
			Faction="SkirmishNeutral/teamSkirmishNeutral"
			Health="100"
			Team="SkirmishNeutral"
			ThingTemplate="CivBunker"
			id="CivBunker">
			<Position
				x="1351.49"
				y="645.465"
				z="0"/>
		</Structure>
		<Structure
			Angle="0"
			EventList=""
			Faction="SkirmishNeutral/teamSkirmishNeutral"
			Health="100"
			Team="SkirmishNeutral"
			ThingTemplate="CivBunker"
			id="CivBunker">
			<Position
				x="1571.18"
				y="651.534"
				z="0"/>
		</Structure>
		<Structure
			Angle="0"
			EventList=""
			Faction="SkirmishNeutral/teamSkirmishNeutral"
			Health="100"
			Team="SkirmishNeutral"
			ThingTemplate="CivBunker"
			id="CivBunker">
			<Position
				x="2328.34"
				y="494.51"
				z="0"/>
		</Structure>
		<Structure
			Angle="0"
			EventList=""
			Faction="SkirmishNeutral/teamSkirmishNeutral"
			Health="100"
			Team="SkirmishNeutral"
			ThingTemplate="CivBunker"
			id="CivBunker">
			<Position
				x="2452.66"
				y="630.47"
				z="0"/>
		</Structure>
		<Structure
			Angle="0"
			EventList=""
			Faction="SkirmishNeutral/teamSkirmishNeutral"
			Health="100"
			Team="SkirmishNeutral"
			ThingTemplate="CivBunker"
			id="CivBunker">
			<Position
				x="2323.1"
				y="1602.74"
				z="0"/>
		</Structure>
		<Structure
			Angle="0"
			EventList=""
			Faction="SkirmishNeutral/teamSkirmishNeutral"
			Health="100"
			Team="SkirmishNeutral"
			ThingTemplate="CivBunker"
			id="CivBunker">
			<Position
				x="2319.84"
				y="1361.85"
				z="0"/>
		</Structure>
		<Structure
			Angle="0"
			EventList=""
			Faction="SkirmishNeutral/teamSkirmishNeutral"
			Health="100"
			Team="SkirmishNeutral"
			ThingTemplate="CivBunker"
			id="CivBunker">
			<Position
				x="2502.28"
				y="2335.19"
				z="0"/>
		</Structure>
		<Structure
			Angle="0"
			EventList=""
			Faction="SkirmishNeutral/teamSkirmishNeutral"
			Health="100"
			Team="SkirmishNeutral"
			ThingTemplate="CivBunker"
			id="CivBunker">
			<Position
				x="2337.58"
				y="2473.8"
				z="0"/>
		</Structure>
		<Structure
			Angle="0"
			EventList=""
			Faction="SkirmishNeutral/teamSkirmishNeutral"
			Health="100"
			Team="SkirmishNeutral"
			ThingTemplate="CivBunker"
			id="CivBunker">
			<Position
				x="1565.84"
				y="2347.56"
				z="0"/>
		</Structure>
		<Structure
			Angle="0"
			EventList=""
			Faction="SkirmishNeutral/teamSkirmishNeutral"
			Health="100"
			Team="SkirmishNeutral"
			ThingTemplate="CivBunker"
			id="CivBunker">
			<Position
				x="1321.68"
				y="2345"
				z="0"/>
		</Structure>
		<Structure
			Angle="0"
			EventList=""
			Faction="SkirmishNeutral/teamSkirmishNeutral"
			Health="100"
			Team="SkirmishNeutral"
			ThingTemplate="CivBunker"
			id="CivBunker">
			<Position
				x="601.211"
				y="2433.26"
				z="0"/>
		</Structure>
		<Structure
			Angle="0"
			EventList=""
			Faction="SkirmishNeutral/teamSkirmishNeutral"
			Health="100"
			Team="SkirmishNeutral"
			ThingTemplate="CivBunker"
			id="CivBunker">
			<Position
				x="637.52"
				y="1585.17"
				z="0"/>
		</Structure>
		<Structure
			Angle="0"
			EventList=""
			Faction="SkirmishNeutral/teamSkirmishNeutral"
			Health="100"
			Team="SkirmishNeutral"
			ThingTemplate="CivBunker"
			id="CivBunker">
			<Position
				x="450.157"
				y="2342.41"
				z="0"/>
		</Structure>
		<Structure
			Angle="0"
			EventList=""
			Faction="SkirmishNeutral/teamSkirmishNeutral"
			Health="100"
			Team="SkirmishNeutral"
			ThingTemplate="CivBunker"
			id="CivBunker">
			<Position
				x="647.403"
				y="1352.27"
				z="0"/>
		</Structure>
		<Structure
			Angle="0"
			EventList=""
			Faction="SkirmishNeutral/teamSkirmishNeutral"
			Health="100"
			Team="SkirmishNeutral"
			ThingTemplate="TiberiumSpike"
			id="TiberiumSpike">
			<Position
				x="1880.53"
				y="44.546"
				z="0"/>
		</Structure>
		<Structure
			Angle="1.13359"
			EventList=""
			Faction="SkirmishNeutral/teamSkirmishNeutral"
			Health="100"
			Team="SkirmishNeutral"
			ThingTemplate="TiberiumSpike"
			id="TiberiumSpike">
			<Position
				x="2945.24"
				y="817.824"
				z="0"/>
		</Structure>
		<Structure
			Angle="0"
			EventList=""
			Faction="SkirmishNeutral/teamSkirmishNeutral"
			Health="100"
			Team="SkirmishNeutral"
			ThingTemplate="TiberiumSpike"
			id="TiberiumSpike">
			<Position
				x="2945.85"
				y="1949.96"
				z="0"/>
		</Structure>
		<Structure
			Angle="0"
			EventList=""
			Faction="SkirmishNeutral/teamSkirmishNeutral"
			Health="100"
			Team="SkirmishNeutral"
			ThingTemplate="TiberiumSpike"
			id="TiberiumSpike">
			<Position
				x="2180.43"
				y="2952.68"
				z="0"/>
		</Structure>
		<Structure
			Angle="0"
			EventList=""
			Faction="SkirmishNeutral/teamSkirmishNeutral"
			Health="100"
			Team="SkirmishNeutral"
			ThingTemplate="TiberiumSpike"
			id="TiberiumSpike">
			<Position
				x="1084.97"
				y="2950.99"
				z="0"/>
		</Structure>
		<Structure
			Angle="0"
			EventList=""
			Faction="SkirmishNeutral/teamSkirmishNeutral"
			Health="100"
			Team="SkirmishNeutral"
			ThingTemplate="TiberiumSpike"
			id="TiberiumSpike">
			<Position
				x="44.5518"
				y="2157.24"
				z="0"/>
		</Structure>
		<Structure
			Angle="0"
			EventList=""
			Faction="SkirmishNeutral/teamSkirmishNeutral"
			Health="100"
			Team="SkirmishNeutral"
			ThingTemplate="TiberiumSpike"
			id="TiberiumSpike">
			<Position
				x="43.3165"
				y="1084.09"
				z="0"/>
		</Structure>
		<Structure
			Angle="0"
			EventList=""
			Faction="SkirmishNeutral/teamSkirmishNeutral"
			Health="100"
			Team="SkirmishNeutral"
			ThingTemplate="TiberiumSpike"
			id="TiberiumSpike">
			<Position
				x="843.539"
				y="40.7188"
				z="0"/>
		</Structure>
		<Unit
			Angle="0"
			EventList=""
			Faction="PlyrCreeps/teamPlyrCreeps"
			Health="100"
			Team="PlyrCreeps"
			ThingTemplate="Viceroid"
			id="Viceroid">
			<Position
				x="1599.28"
				y="1646.4"
				z="0"/>
		</Unit>
		<Unit
			Angle="0"
			EventList=""
			Faction="PlyrCreeps/teamPlyrCreeps"
			Health="100"
			Team="PlyrCreeps"
			ThingTemplate="Viceroid"
			id="Viceroid">
			<Position
				x="1772.19"
				y="1733.45"
				z="0"/>
		</Unit>
		<Unit
			Angle="0"
			EventList=""
			Faction="PlyrCreeps/teamPlyrCreeps"
			Health="100"
			Team="PlyrCreeps"
			ThingTemplate="Viceroid"
			id="Viceroid">
			<Position
				x="1841.09"
				y="1499.61"
				z="0"/>
		</Unit>
		<Unit
			Angle="0"
			EventList=""
			Faction="PlyrCreeps/teamPlyrCreeps"
			Health="100"
			Team="PlyrCreeps"
			ThingTemplate="Viceroid"
			id="Viceroid">
			<Position
				x="1814.65"
				y="1352.3"
				z="0"/>
		</Unit>
		<Unit
			Angle="0"
			EventList=""
			Faction="PlyrCreeps/teamPlyrCreeps"
			Health="100"
			Team="PlyrCreeps"
			ThingTemplate="Viceroid"
			id="Viceroid">
			<Position
				x="1748.01"
				y="1158.58"
				z="0"/>
		</Unit>
		<Unit
			Angle="0"
			EventList=""
			Faction="PlyrCreeps/teamPlyrCreeps"
			Health="100"
			Team="PlyrCreeps"
			ThingTemplate="Viceroid"
			id="Viceroid">
			<Position
				x="1477.71"
				y="1074.13"
				z="0"/>
		</Unit>
		<Unit
			Angle="0"
			EventList=""
			Faction="PlyrCreeps/teamPlyrCreeps"
			Health="100"
			Team="PlyrCreeps"
			ThingTemplate="Viceroid"
			id="Viceroid">
			<Position
				x="1230.96"
				y="1128.2"
				z="0"/>
		</Unit>
		<Unit
			Angle="0"
			EventList=""
			Faction="PlyrCreeps/teamPlyrCreeps"
			Health="100"
			Team="PlyrCreeps"
			ThingTemplate="Viceroid"
			id="Viceroid">
			<Position
				x="1572.7"
				y="1309.88"
				z="0"/>
		</Unit>
		<Unit
			Angle="0"
			EventList=""
			Faction="PlyrCreeps/teamPlyrCreeps"
			Health="100"
			Team="PlyrCreeps"
			ThingTemplate="Viceroid"
			id="Viceroid">
			<Position
				x="1357.34"
				y="1345.26"
				z="0"/>
		</Unit>
		<Unit
			Angle="0"
			EventList=""
			Faction="PlyrCreeps/teamPlyrCreeps"
			Health="100"
			Team="PlyrCreeps"
			ThingTemplate="Viceroid"
			id="Viceroid">
			<Position
				x="1286.42"
				y="1539.22"
				z="0"/>
		</Unit>
		<Unit
			Angle="0"
			EventList=""
			Faction="PlyrCreeps/teamPlyrCreeps"
			Health="100"
			Team="PlyrCreeps"
			ThingTemplate="Viceroid"
			id="Viceroid">
			<Position
				x="1662.07"
				y="1723.15"
				z="0"/>
		</Unit>
		<Unit
			Angle="0"
			EventList=""
			Faction="PlyrCreeps/teamPlyrCreeps"
			Health="100"
			Team="PlyrCreeps"
			ThingTemplate="Viceroid"
			id="Viceroid">
			<Position
				x="1464.41"
				y="1880.57"
				z="0"/>
		</Unit>
		<Unit
			Angle="0"
			EventList=""
			Faction="PlyrCreeps/teamPlyrCreeps"
			Health="100"
			Team="PlyrCreeps"
			ThingTemplate="Viceroid"
			id="Viceroid">
			<Position
				x="1186.13"
				y="1705.84"
				z="0"/>
		</Unit>
		<Unit
			Angle="0"
			EventList=""
			Faction="PlyrCreeps/teamPlyrCreeps"
			Health="100"
			Team="PlyrCreeps"
			ThingTemplate="Viceroid"
			id="Viceroid">
			<Position
				x="1076.78"
				y="1534.82"
				z="0"/>
		</Unit>
		<Prop
			Angle="0"
			EventList=""
			Faction="SkirmishNeutral/teamSkirmishNeutral"
			Health="100"
			Team="SkirmishNeutral"
			ThingTemplate="TiberiumFieldSeeded"
			id="TiberiumFieldSeeded">
			<Position
				x="1459.7"
				y="1529.42"
				z="0"/>
		</Prop>
		<Prop
			Angle="0"
			EventList=""
			Faction="SkirmishNeutral/teamSkirmishNeutral"
			Health="100"
			Team="SkirmishNeutral"
			ThingTemplate="TiberiumCrystal"
			id="TiberiumCrystal">
			<Position
				x="1462.34"
				y="1596.83"
				z="0"/>
		</Prop>
		<Prop
			Angle="3.02479"
			EventList=""
			Faction="SkirmishNeutral/teamSkirmishNeutral"
			Health="100"
			Team="SkirmishNeutral"
			ThingTemplate="TiberiumCrystal"
			id="TiberiumCrystal">
			<Position
				x="1470.88"
				y="1595.83"
				z="0"/>
		</Prop>
		<Prop
			Angle="2.22639"
			EventList=""
			Faction="SkirmishNeutral/teamSkirmishNeutral"
			Health="100"
			Team="SkirmishNeutral"
			ThingTemplate="TiberiumCrystal"
			id="TiberiumCrystal">
			<Position
				x="1519.09"
				y="1572.04"
				z="0"/>
		</Prop>
		<Prop
			Angle="1.37456"
			EventList=""
			Faction="SkirmishNeutral/teamSkirmishNeutral"
			Health="100"
			Team="SkirmishNeutral"
			ThingTemplate="TiberiumCrystal"
			id="TiberiumCrystal">
			<Position
				x="1525.65"
				y="1514.28"
				z="0"/>
		</Prop>
		<Prop
			Angle="0.952661"
			EventList=""
			Faction="SkirmishNeutral/teamSkirmishNeutral"
			Health="100"
			Team="SkirmishNeutral"
			ThingTemplate="TiberiumCrystal"
			id="TiberiumCrystal">
			<Position
				x="1493.09"
				y="1474.79"
				z="0"/>
		</Prop>
		<Prop
			Angle="-0.116738"
			EventList=""
			Faction="SkirmishNeutral/teamSkirmishNeutral"
			Health="100"
			Team="SkirmishNeutral"
			ThingTemplate="TiberiumCrystal"
			id="TiberiumCrystal">
			<Position
				x="1465.65"
				y="1449.62"
				z="0"/>
		</Prop>
		<Prop
			Angle="0"
			EventList=""
			Faction="SkirmishNeutral/teamSkirmishNeutral"
			Health="100"
			Team="SkirmishNeutral"
			ThingTemplate="TiberiumCrystal"
			id="TiberiumCrystal">
			<Position
				x="1407.06"
				y="1479.42"
				z="0"/>
		</Prop>
		<Prop
			Angle="0"
			EventList=""
			Faction="SkirmishNeutral/teamSkirmishNeutral"
			Health="100"
			Team="SkirmishNeutral"
			ThingTemplate="TiberiumCrystal"
			id="TiberiumCrystal">
			<Position
				x="1385.29"
				y="1537.9"
				z="0"/>
		</Prop>
		<Prop
			Angle="0"
			EventList=""
			Faction="SkirmishNeutral/teamSkirmishNeutral"
			Health="100"
			Team="SkirmishNeutral"
			ThingTemplate="TiberiumCrystal"
			id="TiberiumCrystal">
			<Position
				x="1425.97"
				y="1585.97"
				z="0"/>
		</Prop>
		<Prop
			Angle="0"
			EventList=""
			Faction="SkirmishNeutral/teamSkirmishNeutral"
			Health="100"
			Team="SkirmishNeutral"
			ThingTemplate="TiberiumCrystal"
			id="TiberiumCrystal">
			<Position
				x="1780.18"
				y="1430.2"
				z="0"/>
		</Prop>
		<Prop
			Angle="0"
			EventList=""
			Faction="SkirmishNeutral/teamSkirmishNeutral"
			Health="100"
			Team="SkirmishNeutral"
			ThingTemplate="TiberiumCrystal"
			id="TiberiumCrystal">
			<Position
				x="1459.08"
				y="1799.26"
				z="0"/>
		</Prop>
		<Prop
			Angle="0"
			EventList=""
			Faction="SkirmishNeutral/teamSkirmishNeutral"
			Health="100"
			Team="SkirmishNeutral"
			ThingTemplate="TiberiumCrystal"
			id="TiberiumCrystal">
			<Position
				x="1139.4"
				y="1520.58"
				z="0"/>
		</Prop>
		<Prop
			Angle="0"
			EventList=""
			Faction="SkirmishNeutral/teamSkirmishNeutral"
			Health="100"
			Team="SkirmishNeutral"
			ThingTemplate="TiberiumCrystal"
			id="TiberiumCrystal">
			<Position
				x="1545.82"
				y="1080.4"
				z="0"/>
		</Prop>
		<Prop
			Angle="-0.0297722"
			EventList=""
			Faction="SkirmishNeutral/teamSkirmishNeutral"
			Health="100"
			Team="SkirmishNeutral"
			ThingTemplate="TiberiumCrystal"
			id="TiberiumCrystal">
			<Position
				x="1303.59"
				y="1232.18"
				z="0"/>
		</Prop>
		<Prop
			Angle="-0.116849"
			EventList=""
			Faction="SkirmishNeutral/teamSkirmishNeutral"
			Health="100"
			Team="SkirmishNeutral"
			ThingTemplate="TiberiumCrystal"
			id="TiberiumCrystal">
			<Position
				x="1265.47"
				y="1229.27"
				z="0"/>
		</Prop>
		<Prop
			Angle="0"
			EventList=""
			Faction="SkirmishNeutral/teamSkirmishNeutral"
			Health="100"
			Team="SkirmishNeutral"
			ThingTemplate="TiberiumCrystal"
			id="TiberiumCrystal">
			<Position
				x="1292.77"
				y="1192.04"
				z="0"/>
		</Prop>
		<Prop
			Angle="0"
			EventList=""
			Faction="SkirmishNeutral/teamSkirmishNeutral"
			Health="100"
			Team="SkirmishNeutral"
			ThingTemplate="TiberiumCrystal"
			id="TiberiumCrystal">
			<Position
				x="1267.87"
				y="1190.96"
				z="0"/>
		</Prop>
		<Prop
			Angle="0"
			EventList=""
			Faction="SkirmishNeutral/teamSkirmishNeutral"
			Health="100"
			Team="SkirmishNeutral"
			ThingTemplate="TiberiumCrystal"
			id="TiberiumCrystal">
			<Position
				x="1334.54"
				y="1426.79"
				z="0"/>
		</Prop>
		<Prop
			Angle="0"
			EventList=""
			Faction="SkirmishNeutral/teamSkirmishNeutral"
			Health="100"
			Team="SkirmishNeutral"
			ThingTemplate="TiberiumCrystal"
			id="TiberiumCrystal">
			<Position
				x="1360.58"
				y="1285.87"
				z="0"/>
		</Prop>
		<Prop
			Angle="0"
			EventList=""
			Faction="SkirmishNeutral/teamSkirmishNeutral"
			Health="100"
			Team="SkirmishNeutral"
			ThingTemplate="TiberiumCrystal"
			id="TiberiumCrystal">
			<Position
				x="1483.37"
				y="1186.59"
				z="0"/>
		</Prop>
		<Prop
			Angle="0"
			EventList=""
			Faction="SkirmishNeutral/teamSkirmishNeutral"
			Health="100"
			Team="SkirmishNeutral"
			ThingTemplate="TiberiumCrystal"
			id="TiberiumCrystal">
			<Position
				x="1673.46"
				y="1192.54"
				z="0"/>
		</Prop>
		<Prop
			Angle="0"
			EventList=""
			Faction="SkirmishNeutral/teamSkirmishNeutral"
			Health="100"
			Team="SkirmishNeutral"
			ThingTemplate="TiberiumCrystal"
			id="TiberiumCrystal">
			<Position
				x="1737.06"
				y="1261.39"
				z="0"/>
		</Prop>
		<Prop
			Angle="0"
			EventList=""
			Faction="SkirmishNeutral/teamSkirmishNeutral"
			Health="100"
			Team="SkirmishNeutral"
			ThingTemplate="TiberiumCrystal"
			id="TiberiumCrystal">
			<Position
				x="1830.66"
				y="1378.3"
				z="0"/>
		</Prop>
		<Prop
			Angle="0"
			EventList=""
			Faction="SkirmishNeutral/teamSkirmishNeutral"
			Health="100"
			Team="SkirmishNeutral"
			ThingTemplate="TiberiumCrystal"
			id="TiberiumCrystal">
			<Position
				x="1796.19"
				y="1569.31"
				z="0"/>
		</Prop>
		<Prop
			Angle="0"
			EventList=""
			Faction="SkirmishNeutral/teamSkirmishNeutral"
			Health="100"
			Team="SkirmishNeutral"
			ThingTemplate="TiberiumCrystal"
			id="TiberiumCrystal">
			<Position
				x="1696.03"
				y="1718.63"
				z="0"/>
		</Prop>
		<Prop
			Angle="0"
			EventList=""
			Faction="SkirmishNeutral/teamSkirmishNeutral"
			Health="100"
			Team="SkirmishNeutral"
			ThingTemplate="TiberiumCrystal"
			id="TiberiumCrystal">
			<Position
				x="1592.64"
				y="1704.45"
				z="0"/>
		</Prop>
		<Prop
			Angle="0"
			EventList=""
			Faction="SkirmishNeutral/teamSkirmishNeutral"
			Health="100"
			Team="SkirmishNeutral"
			ThingTemplate="TiberiumCrystal"
			id="TiberiumCrystal">
			<Position
				x="1670.29"
				y="1553.21"
				z="0"/>
		</Prop>
		<Prop
			Angle="0"
			EventList=""
			Faction="SkirmishNeutral/teamSkirmishNeutral"
			Health="100"
			Team="SkirmishNeutral"
			ThingTemplate="TiberiumCrystal"
			id="TiberiumCrystal">
			<Position
				x="1651.56"
				y="1376.76"
				z="0"/>
		</Prop>
		<Prop
			Angle="0"
			EventList=""
			Faction="SkirmishNeutral/teamSkirmishNeutral"
			Health="100"
			Team="SkirmishNeutral"
			ThingTemplate="TiberiumCrystal"
			id="TiberiumCrystal">
			<Position
				x="1451.04"
				y="1351.67"
				z="0"/>
		</Prop>
		<Prop
			Angle="0"
			EventList=""
			Faction="SkirmishNeutral/teamSkirmishNeutral"
			Health="100"
			Team="SkirmishNeutral"
			ThingTemplate="TiberiumCrystal"
			id="TiberiumCrystal">
			<Position
				x="1274.07"
				y="1590.87"
				z="0"/>
		</Prop>
		<Prop
			Angle="0"
			EventList=""
			Faction="SkirmishNeutral/teamSkirmishNeutral"
			Health="100"
			Team="SkirmishNeutral"
			ThingTemplate="TiberiumCrystal"
			id="TiberiumCrystal">
			<Position
				x="1447.06"
				y="1722.98"
				z="0"/>
		</Prop>
		<Prop
			Angle="-0.116823"
			EventList=""
			Faction="SkirmishNeutral/teamSkirmishNeutral"
			Health="100"
			Team="SkirmishNeutral"
			ThingTemplate="TiberiumCrystal"
			id="TiberiumCrystal">
			<Position
				x="1157.39"
				y="1664.04"
				z="0"/>
		</Prop>
		<Prop
			Angle="-0.250407"
			EventList=""
			Faction="/team"
			Health="100"
			Team=""
			ThingTemplate="ASTdead06"
			id="ASTDEAD06">
			<Position
				x="1759.39"
				y="1140.62"
				z="0"/>
		</Prop>
		<Prop
			Angle="-1.37716"
			EventList=""
			Faction="/team"
			Health="100"
			Team=""
			ThingTemplate="ASTdead03"
			id="ASTdead03">
			<Position
				x="1740.63"
				y="1178.23"
				z="0"/>
		</Prop>
		<Prop
			Angle="-0.767376"
			EventList=""
			Faction="/team"
			Health="100"
			Team=""
			ThingTemplate="ASTdead03"
			id="ASTdead03">
			<Position
				x="1784.18"
				y="1145.63"
				z="0"/>
		</Prop>
		<Prop
			Angle="1.59434"
			EventList=""
			Faction="/team"
			Health="100"
			Team=""
			ThingTemplate="ASTdead06"
			id="ASTDEAD06">
			<Position
				x="1779.61"
				y="1151.66"
				z="0"/>
		</Prop>
		<Prop
			Angle="1.75174"
			EventList=""
			Faction="/team"
			Health="100"
			Team=""
			ThingTemplate="ASTdead06"
			id="ASTDEAD06">
			<Position
				x="1743.79"
				y="1176.87"
				z="0"/>
		</Prop>
		<Prop
			Angle="1.27477"
			EventList=""
			Faction="/team"
			Health="100"
			Team=""
			ThingTemplate="ASTdead02"
			id="ASTDEAD02">
			<Position
				x="1785.36"
				y="1112.1"
				z="0"/>
		</Prop>
		<Prop
			Angle="-2.09212"
			EventList=""
			Faction="/team"
			Health="100"
			Team=""
			ThingTemplate="ASTdead03"
			id="ASTdead03">
			<Position
				x="1778.63"
				y="1113.16"
				z="0"/>
		</Prop>
		<Prop
			Angle="1.35106"
			EventList=""
			Faction="/team"
			Health="100"
			Team=""
			ThingTemplate="ASTdead01"
			id="ASTdead01">
			<Position
				x="1764.06"
				y="1165.25"
				z="0"/>
		</Prop>
		<Prop
			Angle="-1.22458"
			EventList=""
			Faction="/team"
			Health="100"
			Team=""
			ThingTemplate="ASTdead02"
			id="ASTDEAD02">
			<Position
				x="1767.41"
				y="1121.59"
				z="0"/>
		</Prop>
		<Prop
			Angle="2.02019"
			EventList=""
			Faction="/team"
			Health="100"
			Team=""
			ThingTemplate="ASTdead06"
			id="ASTDEAD06">
			<Position
				x="1764.31"
				y="1137.16"
				z="0"/>
		</Prop>
		<Prop
			Angle="0.541939"
			EventList=""
			Faction="/team"
			Health="100"
			Team=""
			ThingTemplate="ASTdead01"
			id="ASTdead01">
			<Position
				x="1822.86"
				y="1463.43"
				z="0"/>
		</Prop>
		<Prop
			Angle="2.32834"
			EventList=""
			Faction="/team"
			Health="100"
			Team=""
			ThingTemplate="ASTdead03"
			id="ASTdead03">
			<Position
				x="1921.86"
				y="1504.95"
				z="0"/>
		</Prop>
		<Prop
			Angle="-0.586156"
			EventList=""
			Faction="/team"
			Health="100"
			Team=""
			ThingTemplate="ASTdead06"
			id="ASTDEAD06">
			<Position
				x="1826.69"
				y="1464.78"
				z="0"/>
		</Prop>
		<Prop
			Angle="2.51025"
			EventList=""
			Faction="/team"
			Health="100"
			Team=""
			ThingTemplate="ASTdead01"
			id="ASTdead01">
			<Position
				x="1887.58"
				y="1501.39"
				z="0"/>
		</Prop>
		<Prop
			Angle="0.239175"
			EventList=""
			Faction="/team"
			Health="100"
			Team=""
			ThingTemplate="ASTdead06"
			id="ASTDEAD06">
			<Position
				x="1911.72"
				y="1526.38"
				z="0"/>
		</Prop>
		<Prop
			Angle="0.0458795"
			EventList=""
			Faction="/team"
			Health="100"
			Team=""
			ThingTemplate="ASTdead06"
			id="ASTDEAD06">
			<Position
				x="1945.53"
				y="1416.03"
				z="0"/>
		</Prop>
		<Prop
			Angle="-0.00192928"
			EventList=""
			Faction="/team"
			Health="100"
			Team=""
			ThingTemplate="ASTdead06"
			id="ASTDEAD06">
			<Position
				x="1843.17"
				y="1504.42"
				z="0"/>
		</Prop>
		<Prop
			Angle="-1.71617"
			EventList=""
			Faction="/team"
			Health="100"
			Team=""
			ThingTemplate="ASTdead01"
			id="ASTdead01">
			<Position
				x="1875.41"
				y="1521.11"
				z="0"/>
		</Prop>
		<Prop
			Angle="2.70954"
			EventList=""
			Faction="/team"
			Health="100"
			Team=""
			ThingTemplate="ASTdead03"
			id="ASTdead03">
			<Position
				x="1951.45"
				y="1508.5"
				z="0"/>
		</Prop>
		<Prop
			Angle="2.49872"
			EventList=""
			Faction="/team"
			Health="100"
			Team=""
			ThingTemplate="ASTdead02"
			id="ASTDEAD02">
			<Position
				x="1881.01"
				y="1466.68"
				z="0"/>
		</Prop>
		<Prop
			Angle="2.92269"
			EventList=""
			Faction="/team"
			Health="100"
			Team=""
			ThingTemplate="ASTdead01"
			id="ASTdead01">
			<Position
				x="1849.82"
				y="1771.73"
				z="0"/>
		</Prop>
		<Prop
			Angle="-2.90058"
			EventList=""
			Faction="/team"
			Health="100"
			Team=""
			ThingTemplate="ASTdead02"
			id="ASTDEAD02">
			<Position
				x="1835.23"
				y="1858.54"
				z="0"/>
		</Prop>
		<Prop
			Angle="0.62424"
			EventList=""
			Faction="/team"
			Health="100"
			Team=""
			ThingTemplate="ASTdead02"
			id="ASTDEAD02">
			<Position
				x="1766.83"
				y="1770.51"
				z="0"/>
		</Prop>
		<Prop
			Angle="-1.76408"
			EventList=""
			Faction="/team"
			Health="100"
			Team=""
			ThingTemplate="ASTdead02"
			id="ASTDEAD02">
			<Position
				x="1844.55"
				y="1775.6"
				z="0"/>
		</Prop>
		<Prop
			Angle="-2.70306"
			EventList=""
			Faction="/team"
			Health="100"
			Team=""
			ThingTemplate="ASTdead02"
			id="ASTDEAD02">
			<Position
				x="1802.53"
				y="1847.39"
				z="0"/>
		</Prop>
		<Prop
			Angle="-0.407639"
			EventList=""
			Faction="/team"
			Health="100"
			Team=""
			ThingTemplate="ASTdead02"
			id="ASTDEAD02">
			<Position
				x="1780.44"
				y="1743.91"
				z="0"/>
		</Prop>
		<Prop
			Angle="-1.73856"
			EventList=""
			Faction="/team"
			Health="100"
			Team=""
			ThingTemplate="ASTdead02"
			id="ASTDEAD02">
			<Position
				x="1802.86"
				y="1874.38"
				z="0"/>
		</Prop>
		<Prop
			Angle="-0.138056"
			EventList=""
			Faction="/team"
			Health="100"
			Team=""
			ThingTemplate="ASTdead03"
			id="ASTdead03">
			<Position
				x="1838.61"
				y="1795.53"
				z="0"/>
		</Prop>
		<Prop
			Angle="2.45227"
			EventList=""
			Faction="/team"
			Health="100"
			Team=""
			ThingTemplate="ASTdead02"
			id="ASTDEAD02">
			<Position
				x="1744.09"
				y="1869.68"
				z="0"/>
		</Prop>
		<Prop
			Angle="-1.19378"
			EventList=""
			Faction="/team"
			Health="100"
			Team=""
			ThingTemplate="ASTdead06"
			id="ASTDEAD06">
			<Position
				x="1786.69"
				y="1761.98"
				z="0"/>
		</Prop>
		<Prop
			Angle="-1.52262"
			EventList=""
			Faction="/team"
			Health="100"
			Team=""
			ThingTemplate="ASTdead03"
			id="ASTdead03">
			<Position
				x="1480.32"
				y="1827.98"
				z="0"/>
		</Prop>
		<Prop
			Angle="-0.401994"
			EventList=""
			Faction="/team"
			Health="100"
			Team=""
			ThingTemplate="ASTdead06"
			id="ASTDEAD06">
			<Position
				x="1529.53"
				y="1881.02"
				z="0"/>
		</Prop>
		<Prop
			Angle="-1.62293"
			EventList=""
			Faction="/team"
			Health="100"
			Team=""
			ThingTemplate="ASTdead06"
			id="ASTDEAD06">
			<Position
				x="1509.05"
				y="1796.89"
				z="0"/>
		</Prop>
		<Prop
			Angle="-1.40173"
			EventList=""
			Faction="/team"
			Health="100"
			Team=""
			ThingTemplate="ASTdead02"
			id="ASTDEAD02">
			<Position
				x="1496.62"
				y="1833.01"
				z="0"/>
		</Prop>
		<Prop
			Angle="2.26845"
			EventList=""
			Faction="/team"
			Health="100"
			Team=""
			ThingTemplate="ASTdead01"
			id="ASTdead01">
			<Position
				x="1451.95"
				y="1882.9"
				z="0"/>
		</Prop>
		<Prop
			Angle="0.266166"
			EventList=""
			Faction="/team"
			Health="100"
			Team=""
			ThingTemplate="ASTdead01"
			id="ASTdead01">
			<Position
				x="1546.48"
				y="1903.16"
				z="0"/>
		</Prop>
		<Prop
			Angle="0.6892"
			EventList=""
			Faction="/team"
			Health="100"
			Team=""
			ThingTemplate="ASTdead03"
			id="ASTdead03">
			<Position
				x="1442.77"
				y="1850.85"
				z="0"/>
		</Prop>
		<Prop
			Angle="0.65354"
			EventList=""
			Faction="/team"
			Health="100"
			Team=""
			ThingTemplate="ASTdead02"
			id="ASTDEAD02">
			<Position
				x="1543.36"
				y="1865.6"
				z="0"/>
		</Prop>
		<Prop
			Angle="2.07459"
			EventList=""
			Faction="/team"
			Health="100"
			Team=""
			ThingTemplate="ASTdead02"
			id="ASTDEAD02">
			<Position
				x="1482.39"
				y="1839.9"
				z="0"/>
		</Prop>
		<Prop
			Angle="2.3157"
			EventList=""
			Faction="/team"
			Health="100"
			Team=""
			ThingTemplate="ASTdead06"
			id="ASTDEAD06">
			<Position
				x="1505.76"
				y="1845.94"
				z="0"/>
		</Prop>
		<Prop
			Angle="-2.597"
			EventList=""
			Faction="/team"
			Health="100"
			Team=""
			ThingTemplate="ASTdead01"
			id="ASTdead01">
			<Position
				x="1168.87"
				y="1779.23"
				z="0"/>
		</Prop>
		<Prop
			Angle="-2.19332"
			EventList=""
			Faction="/team"
			Health="100"
			Team=""
			ThingTemplate="ASTdead02"
			id="ASTDEAD02">
			<Position
				x="1215.73"
				y="1847.68"
				z="0"/>
		</Prop>
		<Prop
			Angle="0.239974"
			EventList=""
			Faction="/team"
			Health="100"
			Team=""
			ThingTemplate="ASTdead03"
			id="ASTdead03">
			<Position
				x="1149.48"
				y="1782.76"
				z="0"/>
		</Prop>
		<Prop
			Angle="-2.84281"
			EventList=""
			Faction="/team"
			Health="100"
			Team=""
			ThingTemplate="ASTdead02"
			id="ASTDEAD02">
			<Position
				x="1245.88"
				y="1829.99"
				z="0"/>
		</Prop>
		<Prop
			Angle="-1.18181"
			EventList=""
			Faction="/team"
			Health="100"
			Team=""
			ThingTemplate="ASTdead01"
			id="ASTdead01">
			<Position
				x="1139.42"
				y="1807.32"
				z="0"/>
		</Prop>
		<Prop
			Angle="-1.19578"
			EventList=""
			Faction="/team"
			Health="100"
			Team=""
			ThingTemplate="ASTdead01"
			id="ASTdead01">
			<Position
				x="1266.38"
				y="1783.28"
				z="0"/>
		</Prop>
		<Prop
			Angle="2.36549"
			EventList=""
			Faction="/team"
			Health="100"
			Team=""
			ThingTemplate="ASTdead06"
			id="ASTDEAD06">
			<Position
				x="1256.19"
				y="1814.93"
				z="0"/>
		</Prop>
		<Prop
			Angle="-1.77976"
			EventList=""
			Faction="/team"
			Health="100"
			Team=""
			ThingTemplate="ASTdead06"
			id="ASTDEAD06">
			<Position
				x="1204.95"
				y="1789.19"
				z="0"/>
		</Prop>
		<Prop
			Angle="-0.531266"
			EventList=""
			Faction="/team"
			Health="100"
			Team=""
			ThingTemplate="ASTdead03"
			id="ASTdead03">
			<Position
				x="1253.59"
				y="1787.87"
				z="0"/>
		</Prop>
		<Prop
			Angle="2.8259"
			EventList=""
			Faction="/team"
			Health="100"
			Team=""
			ThingTemplate="ASTdead02"
			id="ASTDEAD02">
			<Position
				x="1165.94"
				y="1825.2"
				z="0"/>
		</Prop>
		<Prop
			Angle="-1.88055"
			EventList=""
			Faction="/team"
			Health="100"
			Team=""
			ThingTemplate="ASTdead03"
			id="ASTdead03">
			<Position
				x="1274.31"
				y="1458.8"
				z="0"/>
		</Prop>
		<Prop
			Angle="2.92078"
			EventList=""
			Faction="/team"
			Health="100"
			Team=""
			ThingTemplate="ASTdead06"
			id="ASTDEAD06">
			<Position
				x="1119.01"
				y="1494.38"
				z="0"/>
		</Prop>
		<Prop
			Angle="2.92802"
			EventList=""
			Faction="/team"
			Health="100"
			Team=""
			ThingTemplate="ASTdead03"
			id="ASTdead03">
			<Position
				x="1155.02"
				y="1506.28"
				z="0"/>
		</Prop>
		<Prop
			Angle="-0.83668"
			EventList=""
			Faction="/team"
			Health="100"
			Team=""
			ThingTemplate="ASTdead01"
			id="ASTdead01">
			<Position
				x="1098.38"
				y="1436.02"
				z="0"/>
		</Prop>
		<Prop
			Angle="-1.37858"
			EventList=""
			Faction="/team"
			Health="100"
			Team=""
			ThingTemplate="ASTdead06"
			id="ASTDEAD06">
			<Position
				x="1230.55"
				y="1510"
				z="0"/>
		</Prop>
		<Prop
			Angle="-1.36492"
			EventList=""
			Faction="/team"
			Health="100"
			Team=""
			ThingTemplate="ASTdead01"
			id="ASTdead01">
			<Position
				x="1069.02"
				y="1473.4"
				z="0"/>
		</Prop>
		<Prop
			Angle="2.65639"
			EventList=""
			Faction="/team"
			Health="100"
			Team=""
			ThingTemplate="ASTdead02"
			id="ASTDEAD02">
			<Position
				x="1186.78"
				y="1455.85"
				z="0"/>
		</Prop>
		<Prop
			Angle="-1.66094"
			EventList=""
			Faction="/team"
			Health="100"
			Team=""
			ThingTemplate="ASTdead06"
			id="ASTDEAD06">
			<Position
				x="1156.34"
				y="1511.56"
				z="0"/>
		</Prop>
		<Prop
			Angle="-1.54754"
			EventList=""
			Faction="/team"
			Health="100"
			Team=""
			ThingTemplate="ASTdead06"
			id="ASTDEAD06">
			<Position
				x="1126.92"
				y="1464.7"
				z="0"/>
		</Prop>
		<Prop
			Angle="0.11436"
			EventList=""
			Faction="/team"
			Health="100"
			Team=""
			ThingTemplate="ASTdead02"
			id="ASTDEAD02">
			<Position
				x="1221.74"
				y="1469.55"
				z="0"/>
		</Prop>
		<Prop
			Angle="0.572263"
			EventList=""
			Faction="/team"
			Health="100"
			Team=""
			ThingTemplate="ASTdead06"
			id="ASTDEAD06">
			<Position
				x="1173.33"
				y="1479.92"
				z="0"/>
		</Prop>
		<Prop
			Angle="0.41843"
			EventList=""
			Faction="/team"
			Health="100"
			Team=""
			ThingTemplate="ASTdead01"
			id="ASTdead01">
			<Position
				x="1182.66"
				y="1476.79"
				z="0"/>
		</Prop>
		<Prop
			Angle="0.521694"
			EventList=""
			Faction="/team"
			Health="100"
			Team=""
			ThingTemplate="ASTdead03"
			id="ASTdead03">
			<Position
				x="1129.85"
				y="1531.07"
				z="0"/>
		</Prop>
		<Prop
			Angle="-1.04071"
			EventList=""
			Faction="/team"
			Health="100"
			Team=""
			ThingTemplate="ASTdead01"
			id="ASTdead01">
			<Position
				x="1167.44"
				y="1530.2"
				z="0"/>
		</Prop>
		<Prop
			Angle="0.515067"
			EventList=""
			Faction="/team"
			Health="100"
			Team=""
			ThingTemplate="ASTdead02"
			id="ASTDEAD02">
			<Position
				x="1123.04"
				y="1476.41"
				z="0"/>
		</Prop>
		<Prop
			Angle="1.04495"
			EventList=""
			Faction="/team"
			Health="100"
			Team=""
			ThingTemplate="ASTdead03"
			id="ASTdead03">
			<Position
				x="1201.96"
				y="1569.46"
				z="0"/>
		</Prop>
		<Prop
			Angle="-3.02484"
			EventList=""
			Faction="/team"
			Health="100"
			Team=""
			ThingTemplate="ASTdead01"
			id="ASTdead01">
			<Position
				x="1160.09"
				y="1441.66"
				z="0"/>
		</Prop>
		<Prop
			Angle="1.08362"
			EventList=""
			Faction="/team"
			Health="100"
			Team=""
			ThingTemplate="ASTdead06"
			id="ASTDEAD06">
			<Position
				x="1134"
				y="1427.58"
				z="0"/>
		</Prop>
		<Prop
			Angle="1.73274"
			EventList=""
			Faction="/team"
			Health="100"
			Team=""
			ThingTemplate="ASTdead02"
			id="ASTDEAD02">
			<Position
				x="1196.26"
				y="1459.96"
				z="0"/>
		</Prop>
		<Prop
			Angle="-2.49968"
			EventList=""
			Faction="/team"
			Health="100"
			Team=""
			ThingTemplate="ASTdead03"
			id="ASTdead03">
			<Position
				x="1165.69"
				y="1491.58"
				z="0"/>
		</Prop>
		<Prop
			Angle="0.394667"
			EventList=""
			Faction="/team"
			Health="100"
			Team=""
			ThingTemplate="ASTdead02"
			id="ASTDEAD02">
			<Position
				x="1379.64"
				y="1819.62"
				z="0"/>
		</Prop>
		<Prop
			Angle="1.37054"
			EventList=""
			Faction="/team"
			Health="100"
			Team=""
			ThingTemplate="ASTdead02"
			id="ASTDEAD02">
			<Position
				x="1269.59"
				y="1700.24"
				z="0"/>
		</Prop>
		<Prop
			Angle="-1.32307"
			EventList=""
			Faction="/team"
			Health="100"
			Team=""
			ThingTemplate="ASTdead02"
			id="ASTDEAD02">
			<Position
				x="1215.02"
				y="1701.85"
				z="0"/>
		</Prop>
		<Prop
			Angle="1.07215"
			EventList=""
			Faction="/team"
			Health="100"
			Team=""
			ThingTemplate="ASTdead01"
			id="ASTdead01">
			<Position
				x="1438.7"
				y="1676.3"
				z="0"/>
		</Prop>
		<Prop
			Angle="-0.376981"
			EventList=""
			Faction="/team"
			Health="100"
			Team=""
			ThingTemplate="ASTdead01"
			id="ASTdead01">
			<Position
				x="1425.52"
				y="1726.06"
				z="0"/>
		</Prop>
		<Prop
			Angle="2.33582"
			EventList=""
			Faction="/team"
			Health="100"
			Team=""
			ThingTemplate="ASTdead03"
			id="ASTdead03">
			<Position
				x="1291.42"
				y="1800.65"
				z="0"/>
		</Prop>
		<Prop
			Angle="-0.32769"
			EventList=""
			Faction="/team"
			Health="100"
			Team=""
			ThingTemplate="ASTdead02"
			id="ASTDEAD02">
			<Position
				x="1331.73"
				y="1775.14"
				z="0"/>
		</Prop>
		<Prop
			Angle="-0.819238"
			EventList=""
			Faction="/team"
			Health="100"
			Team=""
			ThingTemplate="ASTdead02"
			id="ASTDEAD02">
			<Position
				x="1266.35"
				y="1689.22"
				z="0"/>
		</Prop>
		<Prop
			Angle="-2.70489"
			EventList=""
			Faction="/team"
			Health="100"
			Team=""
			ThingTemplate="ASTdead06"
			id="ASTDEAD06">
			<Position
				x="1305.09"
				y="1825.64"
				z="0"/>
		</Prop>
		<Prop
			Angle="1.39964"
			EventList=""
			Faction="/team"
			Health="100"
			Team=""
			ThingTemplate="ASTdead01"
			id="ASTdead01">
			<Position
				x="1392.78"
				y="1824.81"
				z="0"/>
		</Prop>
		<Prop
			Angle="1.62816"
			EventList=""
			Faction="/team"
			Health="100"
			Team=""
			ThingTemplate="ASTdead03"
			id="ASTdead03">
			<Position
				x="1301.03"
				y="1657.49"
				z="0"/>
		</Prop>
		<Prop
			Angle="-0.788125"
			EventList=""
			Faction="/team"
			Health="100"
			Team=""
			ThingTemplate="ASTdead01"
			id="ASTdead01">
			<Position
				x="1207.54"
				y="1333.91"
				z="0"/>
		</Prop>
		<Prop
			Angle="-2.87184"
			EventList=""
			Faction="/team"
			Health="100"
			Team=""
			ThingTemplate="ASTdead06"
			id="ASTDEAD06">
			<Position
				x="1249.96"
				y="1716.39"
				z="0"/>
		</Prop>
		<Prop
			Angle="-2.96753"
			EventList=""
			Faction="/team"
			Health="100"
			Team=""
			ThingTemplate="ASTdead06"
			id="ASTDEAD06">
			<Position
				x="1365.7"
				y="1601.87"
				z="0"/>
		</Prop>
		<Prop
			Angle="2.47354"
			EventList=""
			Faction="/team"
			Health="100"
			Team=""
			ThingTemplate="ASTdead06"
			id="ASTDEAD06">
			<Position
				x="1286.19"
				y="1663.62"
				z="0"/>
		</Prop>
		<Prop
			Angle="-3.0243"
			EventList=""
			Faction="/team"
			Health="100"
			Team=""
			ThingTemplate="ASTdead06"
			id="ASTDEAD06">
			<Position
				x="1286.42"
				y="1739.83"
				z="0"/>
		</Prop>
		<Prop
			Angle="-2.48038"
			EventList=""
			Faction="/team"
			Health="100"
			Team=""
			ThingTemplate="ASTdead02"
			id="ASTDEAD02">
			<Position
				x="1373.03"
				y="1738.22"
				z="0"/>
		</Prop>
		<Prop
			Angle="1.20871"
			EventList=""
			Faction="/team"
			Health="100"
			Team=""
			ThingTemplate="ASTdead06"
			id="ASTDEAD06">
			<Position
				x="1182.82"
				y="1716.94"
				z="0"/>
		</Prop>
		<Prop
			Angle="1.05071"
			EventList=""
			Faction="/team"
			Health="100"
			Team=""
			ThingTemplate="ASTdead01"
			id="ASTdead01">
			<Position
				x="1335.85"
				y="1634.06"
				z="0"/>
		</Prop>
		<Prop
			Angle="1.7392"
			EventList=""
			Faction="/team"
			Health="100"
			Team=""
			ThingTemplate="ASTdead01"
			id="ASTdead01">
			<Position
				x="1256.07"
				y="1759.9"
				z="0"/>
		</Prop>
		<Prop
			Angle="-2.26396"
			EventList=""
			Faction="/team"
			Health="100"
			Team=""
			ThingTemplate="ASTdead06"
			id="ASTDEAD06">
			<Position
				x="1360.43"
				y="1665.39"
				z="0"/>
		</Prop>
		<Prop
			Angle="1.61933"
			EventList=""
			Faction="/team"
			Health="100"
			Team=""
			ThingTemplate="ASTdead01"
			id="ASTdead01">
			<Position
				x="1271.91"
				y="1464.97"
				z="0"/>
		</Prop>
		<Prop
			Angle="-2.96693"
			EventList=""
			Faction="/team"
			Health="100"
			Team=""
			ThingTemplate="ASTdead01"
			id="ASTdead01">
			<Position
				x="1214.1"
				y="1580.94"
				z="0"/>
		</Prop>
		<Prop
			Angle="-1.54899"
			EventList=""
			Faction="/team"
			Health="100"
			Team=""
			ThingTemplate="ASTdead03"
			id="ASTdead03">
			<Position
				x="1256.22"
				y="1553.68"
				z="0"/>
		</Prop>
		<Prop
			Angle="-2.15673"
			EventList=""
			Faction="/team"
			Health="100"
			Team=""
			ThingTemplate="ASTdead06"
			id="ASTDEAD06">
			<Position
				x="1207.93"
				y="1472.07"
				z="0"/>
		</Prop>
		<Prop
			Angle="-0.692624"
			EventList=""
			Faction="/team"
			Health="100"
			Team=""
			ThingTemplate="ASTdead01"
			id="ASTdead01">
			<Position
				x="1380.32"
				y="1617"
				z="0"/>
		</Prop>
		<Prop
			Angle="-2.84923"
			EventList=""
			Faction="/team"
			Health="100"
			Team=""
			ThingTemplate="ASTdead01"
			id="ASTdead01">
			<Position
				x="1396.58"
				y="1633.06"
				z="0"/>
		</Prop>
		<Prop
			Angle="-2.04439"
			EventList=""
			Faction="/team"
			Health="100"
			Team=""
			ThingTemplate="ASTdead02"
			id="ASTDEAD02">
			<Position
				x="1386.43"
				y="1587.18"
				z="0"/>
		</Prop>
		<Prop
			Angle="-1.33881"
			EventList=""
			Faction="/team"
			Health="100"
			Team=""
			ThingTemplate="ASTdead01"
			id="ASTdead01">
			<Position
				x="1230.17"
				y="1612.05"
				z="0"/>
		</Prop>
		<Prop
			Angle="2.59144"
			EventList=""
			Faction="/team"
			Health="100"
			Team=""
			ThingTemplate="ASTdead02"
			id="ASTDEAD02">
			<Position
				x="1390.04"
				y="1369.39"
				z="0"/>
		</Prop>
		<Prop
			Angle="0.523261"
			EventList=""
			Faction="/team"
			Health="100"
			Team=""
			ThingTemplate="ASTdead01"
			id="ASTdead01">
			<Position
				x="1418.81"
				y="1509.04"
				z="0"/>
		</Prop>
		<Prop
			Angle="1.74302"
			EventList=""
			Faction="/team"
			Health="100"
			Team=""
			ThingTemplate="ASTdead06"
			id="ASTDEAD06">
			<Position
				x="1405.82"
				y="1395.19"
				z="0"/>
		</Prop>
		<Prop
			Angle="0.689286"
			EventList=""
			Faction="/team"
			Health="100"
			Team=""
			ThingTemplate="ASTdead06"
			id="ASTDEAD06">
			<Position
				x="1184.53"
				y="1390.37"
				z="0"/>
		</Prop>
		<Prop
			Angle="2.70848"
			EventList=""
			Faction="/team"
			Health="100"
			Team=""
			ThingTemplate="ASTdead01"
			id="ASTdead01">
			<Position
				x="1358.81"
				y="1350.11"
				z="0"/>
		</Prop>
		<Prop
			Angle="2.13417"
			EventList=""
			Faction="/team"
			Health="100"
			Team=""
			ThingTemplate="ASTdead02"
			id="ASTDEAD02">
			<Position
				x="1326.87"
				y="1327.12"
				z="0"/>
		</Prop>
		<Prop
			Angle="3.09595"
			EventList=""
			Faction="/team"
			Health="100"
			Team=""
			ThingTemplate="ASTdead02"
			id="ASTDEAD02">
			<Position
				x="1263.5"
				y="1426.48"
				z="0"/>
		</Prop>
		<Prop
			Angle="-2.39808"
			EventList=""
			Faction="/team"
			Health="100"
			Team=""
			ThingTemplate="ASTdead03"
			id="ASTdead03">
			<Position
				x="1199.57"
				y="1377.82"
				z="0"/>
		</Prop>
		<Prop
			Angle="0.777499"
			EventList=""
			Faction="/team"
			Health="100"
			Team=""
			ThingTemplate="ASTdead02"
			id="ASTDEAD02">
			<Position
				x="1284.11"
				y="1253.83"
				z="0"/>
		</Prop>
		<Prop
			Angle="-0.507276"
			EventList=""
			Faction="/team"
			Health="100"
			Team=""
			ThingTemplate="ASTdead03"
			id="ASTdead03">
			<Position
				x="1241.63"
				y="1263.73"
				z="0"/>
		</Prop>
		<Prop
			Angle="-2.87645"
			EventList=""
			Faction="/team"
			Health="100"
			Team=""
			ThingTemplate="ASTdead02"
			id="ASTDEAD02">
			<Position
				x="1226.45"
				y="1197.04"
				z="0"/>
		</Prop>
		<Prop
			Angle="-1.56708"
			EventList=""
			Faction="/team"
			Health="100"
			Team=""
			ThingTemplate="ASTdead06"
			id="ASTDEAD06">
			<Position
				x="1271.81"
				y="1102.21"
				z="0"/>
		</Prop>
		<Prop
			Angle="2.78772"
			EventList=""
			Faction="/team"
			Health="100"
			Team=""
			ThingTemplate="ASTdead01"
			id="ASTdead01">
			<Position
				x="1298.44"
				y="1320.37"
				z="0"/>
		</Prop>
		<Prop
			Angle="1.09094"
			EventList=""
			Faction="/team"
			Health="100"
			Team=""
			ThingTemplate="ASTdead02"
			id="ASTDEAD02">
			<Position
				x="1234.21"
				y="1196.25"
				z="0"/>
		</Prop>
		<Prop
			Angle="-2.15344"
			EventList=""
			Faction="/team"
			Health="100"
			Team=""
			ThingTemplate="ASTdead06"
			id="ASTDEAD06">
			<Position
				x="1307.02"
				y="1241.96"
				z="0"/>
		</Prop>
		<Prop
			Angle="1.80849"
			EventList=""
			Faction="/team"
			Health="100"
			Team=""
			ThingTemplate="ASTdead02"
			id="ASTDEAD02">
			<Position
				x="1368.89"
				y="1222.13"
				z="0"/>
		</Prop>
		<Prop
			Angle="-2.22"
			EventList=""
			Faction="/team"
			Health="100"
			Team=""
			ThingTemplate="ASTdead02"
			id="ASTDEAD02">
			<Position
				x="1382.68"
				y="1298.04"
				z="0"/>
		</Prop>
		<Prop
			Angle="0.0945472"
			EventList=""
			Faction="/team"
			Health="100"
			Team=""
			ThingTemplate="ASTdead02"
			id="ASTDEAD02">
			<Position
				x="1327.46"
				y="1132.41"
				z="0"/>
		</Prop>
		<Prop
			Angle="-0.717561"
			EventList=""
			Faction="/team"
			Health="100"
			Team=""
			ThingTemplate="ASTdead02"
			id="ASTDEAD02">
			<Position
				x="1297.66"
				y="1288.47"
				z="0"/>
		</Prop>
		<Prop
			Angle="2.98532"
			EventList=""
			Faction="/team"
			Health="100"
			Team=""
			ThingTemplate="ASTdead03"
			id="ASTdead03">
			<Position
				x="1363.3"
				y="1210.77"
				z="0"/>
		</Prop>
		<Prop
			Angle="1.47242"
			EventList=""
			Faction="/team"
			Health="100"
			Team=""
			ThingTemplate="ASTdead06"
			id="ASTDEAD06">
			<Position
				x="1427.17"
				y="1104.08"
				z="0"/>
		</Prop>
		<Prop
			Angle="2.27183"
			EventList=""
			Faction="/team"
			Health="100"
			Team=""
			ThingTemplate="ASTdead03"
			id="ASTdead03">
			<Position
				x="1401.51"
				y="1152.85"
				z="0"/>
		</Prop>
		<Prop
			Angle="1.96999"
			EventList=""
			Faction="/team"
			Health="100"
			Team=""
			ThingTemplate="ASTdead01"
			id="ASTdead01">
			<Position
				x="1409.55"
				y="1232.14"
				z="0"/>
		</Prop>
		<Prop
			Angle="1.9934"
			EventList=""
			Faction="/team"
			Health="100"
			Team=""
			ThingTemplate="ASTdead01"
			id="ASTdead01">
			<Position
				x="1468.87"
				y="1212.8"
				z="0"/>
		</Prop>
		<Prop
			Angle="-0.742343"
			EventList=""
			Faction="/team"
			Health="100"
			Team=""
			ThingTemplate="ASTdead03"
			id="ASTdead03">
			<Position
				x="1430.35"
				y="1200.51"
				z="0"/>
		</Prop>
		<Prop
			Angle="1.9492"
			EventList=""
			Faction="/team"
			Health="100"
			Team=""
			ThingTemplate="ASTdead03"
			id="ASTdead03">
			<Position
				x="1416.94"
				y="1132.35"
				z="0"/>
		</Prop>
		<Prop
			Angle="1.3248"
			EventList=""
			Faction="/team"
			Health="100"
			Team=""
			ThingTemplate="ASTdead03"
			id="ASTdead03">
			<Position
				x="1387.86"
				y="1176.47"
				z="0"/>
		</Prop>
		<Prop
			Angle="0.0597093"
			EventList=""
			Faction="/team"
			Health="100"
			Team=""
			ThingTemplate="ASTdead02"
			id="ASTDEAD02">
			<Position
				x="1452.35"
				y="1168.01"
				z="0"/>
		</Prop>
		<Prop
			Angle="2.89668"
			EventList=""
			Faction="/team"
			Health="100"
			Team=""
			ThingTemplate="ASTdead06"
			id="ASTDEAD06">
			<Position
				x="1433.96"
				y="1169.41"
				z="0"/>
		</Prop>
		<Prop
			Angle="1.01183"
			EventList=""
			Faction="/team"
			Health="100"
			Team=""
			ThingTemplate="ASTdead03"
			id="ASTdead03">
			<Position
				x="1643.86"
				y="1398.64"
				z="0"/>
		</Prop>
		<Prop
			Angle="0.362826"
			EventList=""
			Faction="/team"
			Health="100"
			Team=""
			ThingTemplate="ASTdead02"
			id="ASTDEAD02">
			<Position
				x="1583.12"
				y="1177.32"
				z="0"/>
		</Prop>
		<Prop
			Angle="-0.228453"
			EventList=""
			Faction="/team"
			Health="100"
			Team=""
			ThingTemplate="ASTdead02"
			id="ASTDEAD02">
			<Position
				x="1621.8"
				y="1177.24"
				z="0"/>
		</Prop>
		<Prop
			Angle="0.422715"
			EventList=""
			Faction="/team"
			Health="100"
			Team=""
			ThingTemplate="ASTdead03"
			id="ASTdead03">
			<Position
				x="1551.84"
				y="1418.81"
				z="0"/>
		</Prop>
		<Prop
			Angle="2.79615"
			EventList=""
			Faction="/team"
			Health="100"
			Team=""
			ThingTemplate="ASTdead02"
			id="ASTDEAD02">
			<Position
				x="1694.76"
				y="1318.54"
				z="0"/>
		</Prop>
		<Prop
			Angle="-2.68417"
			EventList=""
			Faction="/team"
			Health="100"
			Team=""
			ThingTemplate="ASTdead03"
			id="ASTdead03">
			<Position
				x="1616.16"
				y="1062.09"
				z="0"/>
		</Prop>
		<Prop
			Angle="-1.01869"
			EventList=""
			Faction="/team"
			Health="100"
			Team=""
			ThingTemplate="ASTdead01"
			id="ASTdead01">
			<Position
				x="1498.62"
				y="1373.49"
				z="0"/>
		</Prop>
		<Prop
			Angle="0.317639"
			EventList=""
			Faction="/team"
			Health="100"
			Team=""
			ThingTemplate="ASTdead03"
			id="ASTdead03">
			<Position
				x="1640.6"
				y="1116.01"
				z="0"/>
		</Prop>
		<Prop
			Angle="-0.276378"
			EventList=""
			Faction="/team"
			Health="100"
			Team=""
			ThingTemplate="ASTdead01"
			id="ASTdead01">
			<Position
				x="1692.41"
				y="1198.59"
				z="0"/>
		</Prop>
		<Prop
			Angle="-1.59593"
			EventList=""
			Faction="/team"
			Health="100"
			Team=""
			ThingTemplate="ASTdead06"
			id="ASTDEAD06">
			<Position
				x="1543.66"
				y="1351.98"
				z="0"/>
		</Prop>
		<Prop
			Angle="-2.69791"
			EventList=""
			Faction="/team"
			Health="100"
			Team=""
			ThingTemplate="ASTdead01"
			id="ASTdead01">
			<Position
				x="1688.5"
				y="1381.7"
				z="0"/>
		</Prop>
		<Prop
			Angle="0.314611"
			EventList=""
			Faction="/team"
			Health="100"
			Team=""
			ThingTemplate="ASTdead03"
			id="ASTdead03">
			<Position
				x="1525.38"
				y="1324.73"
				z="0"/>
		</Prop>
		<Prop
			Angle="-1.34176"
			EventList=""
			Faction="/team"
			Health="100"
			Team=""
			ThingTemplate="ASTdead03"
			id="ASTdead03">
			<Position
				x="1717"
				y="1450.66"
				z="0"/>
		</Prop>
		<Prop
			Angle="-0.782422"
			EventList=""
			Faction="/team"
			Health="100"
			Team=""
			ThingTemplate="ASTdead03"
			id="ASTdead03">
			<Position
				x="1619.3"
				y="1227.55"
				z="0"/>
		</Prop>
		<Prop
			Angle="2.62792"
			EventList=""
			Faction="/team"
			Health="100"
			Team=""
			ThingTemplate="ASTdead03"
			id="ASTdead03">
			<Position
				x="1637.7"
				y="1455.38"
				z="0"/>
		</Prop>
		<Prop
			Angle="0.207593"
			EventList=""
			Faction="/team"
			Health="100"
			Team=""
			ThingTemplate="ASTdead01"
			id="ASTdead01">
			<Position
				x="1703.01"
				y="1456.25"
				z="0"/>
		</Prop>
		<Prop
			Angle="2.30624"
			EventList=""
			Faction="/team"
			Health="100"
			Team=""
			ThingTemplate="ASTdead03"
			id="ASTdead03">
			<Position
				x="1646.49"
				y="1268.8"
				z="0"/>
		</Prop>
		<Prop
			Angle="-2.46202"
			EventList=""
			Faction="/team"
			Health="100"
			Team=""
			ThingTemplate="ASTdead02"
			id="ASTDEAD02">
			<Position
				x="1625.7"
				y="1249.27"
				z="0"/>
		</Prop>
		<Prop
			Angle="-0.0207038"
			EventList=""
			Faction="/team"
			Health="100"
			Team=""
			ThingTemplate="ASTdead01"
			id="ASTdead01">
			<Position
				x="1702.6"
				y="1408.61"
				z="0"/>
		</Prop>
		<Prop
			Angle="2.11903"
			EventList=""
			Faction="/team"
			Health="100"
			Team=""
			ThingTemplate="ASTdead06"
			id="ASTDEAD06">
			<Position
				x="1760.82"
				y="1277.44"
				z="0"/>
		</Prop>
		<Prop
			Angle="-3.0765"
			EventList=""
			Faction="/team"
			Health="100"
			Team=""
			ThingTemplate="ASTdead02"
			id="ASTDEAD02">
			<Position
				x="1943.15"
				y="1491.76"
				z="0"/>
		</Prop>
		<Prop
			Angle="-0.0983987"
			EventList=""
			Faction="/team"
			Health="100"
			Team=""
			ThingTemplate="ASTdead06"
			id="ASTDEAD06">
			<Position
				x="1809.62"
				y="1540.89"
				z="0"/>
		</Prop>
		<Prop
			Angle="2.05485"
			EventList=""
			Faction="/team"
			Health="100"
			Team=""
			ThingTemplate="ASTdead06"
			id="ASTDEAD06">
			<Position
				x="1821.33"
				y="1405.36"
				z="0"/>
		</Prop>
		<Prop
			Angle="-1.7743"
			EventList=""
			Faction="/team"
			Health="100"
			Team=""
			ThingTemplate="ASTdead02"
			id="ASTDEAD02">
			<Position
				x="1801.1"
				y="1405.3"
				z="0"/>
		</Prop>
		<Prop
			Angle="2.87947"
			EventList=""
			Faction="/team"
			Health="100"
			Team=""
			ThingTemplate="ASTdead03"
			id="ASTdead03">
			<Position
				x="1796.6"
				y="1340.23"
				z="0"/>
		</Prop>
		<Prop
			Angle="3.05442"
			EventList=""
			Faction="/team"
			Health="100"
			Team=""
			ThingTemplate="ASTdead02"
			id="ASTDEAD02">
			<Position
				x="1879.35"
				y="1378.62"
				z="0"/>
		</Prop>
		<Prop
			Angle="-0.723572"
			EventList=""
			Faction="/team"
			Health="100"
			Team=""
			ThingTemplate="ASTdead03"
			id="ASTdead03">
			<Position
				x="1756.17"
				y="1626"
				z="0"/>
		</Prop>
		<Prop
			Angle="2.49141"
			EventList=""
			Faction="/team"
			Health="100"
			Team=""
			ThingTemplate="ASTdead02"
			id="ASTDEAD02">
			<Position
				x="1847.65"
				y="1381.17"
				z="0"/>
		</Prop>
		<Prop
			Angle="-0.418234"
			EventList=""
			Faction="/team"
			Health="100"
			Team=""
			ThingTemplate="ASTdead06"
			id="ASTDEAD06">
			<Position
				x="1897.26"
				y="1348.22"
				z="0"/>
		</Prop>
		<Prop
			Angle="0.564278"
			EventList=""
			Faction="/team"
			Health="100"
			Team=""
			ThingTemplate="ASTdead02"
			id="ASTDEAD02">
			<Position
				x="1891.65"
				y="1477.71"
				z="0"/>
		</Prop>
		<Prop
			Angle="-2.17659"
			EventList=""
			Faction="/team"
			Health="100"
			Team=""
			ThingTemplate="ASTdead06"
			id="ASTDEAD06">
			<Position
				x="1543.94"
				y="1699.79"
				z="0"/>
		</Prop>
		<Prop
			Angle="0.742818"
			EventList=""
			Faction="/team"
			Health="100"
			Team=""
			ThingTemplate="ASTdead03"
			id="ASTdead03">
			<Position
				x="1576.33"
				y="1597.1"
				z="0"/>
		</Prop>
		<Prop
			Angle="1.22189"
			EventList=""
			Faction="/team"
			Health="100"
			Team=""
			ThingTemplate="ASTdead03"
			id="ASTdead03">
			<Position
				x="1631.04"
				y="1748"
				z="0"/>
		</Prop>
		<Prop
			Angle="2.02404"
			EventList=""
			Faction="/team"
			Health="100"
			Team=""
			ThingTemplate="ASTdead03"
			id="ASTdead03">
			<Position
				x="1549.13"
				y="1760.55"
				z="0"/>
		</Prop>
		<Prop
			Angle="1.14285"
			EventList=""
			Faction="/team"
			Health="100"
			Team=""
			ThingTemplate="ASTdead01"
			id="ASTdead01">
			<Position
				x="1552.79"
				y="1734.29"
				z="0"/>
		</Prop>
		<Prop
			Angle="1.30078"
			EventList=""
			Faction="/team"
			Health="100"
			Team=""
			ThingTemplate="ASTdead02"
			id="ASTDEAD02">
			<Position
				x="1661.61"
				y="1767.09"
				z="0"/>
		</Prop>
		<Prop
			Angle="0.598525"
			EventList=""
			Faction="/team"
			Health="100"
			Team=""
			ThingTemplate="ASTdead03"
			id="ASTdead03">
			<Position
				x="1578.17"
				y="1658.32"
				z="0"/>
		</Prop>
		<Prop
			Angle="2.01379"
			EventList=""
			Faction="/team"
			Health="100"
			Team=""
			ThingTemplate="ASTdead06"
			id="ASTDEAD06">
			<Position
				x="1746.22"
				y="1593.73"
				z="0"/>
		</Prop>
		<Prop
			Angle="-2.23261"
			EventList=""
			Faction="/team"
			Health="100"
			Team=""
			ThingTemplate="ASTdead02"
			id="ASTDEAD02">
			<Position
				x="1594.32"
				y="1652.28"
				z="0"/>
		</Prop>
		<Prop
			Angle="-2.32838"
			EventList=""
			Faction="/team"
			Health="100"
			Team=""
			ThingTemplate="ASTdead06"
			id="ASTDEAD06">
			<Position
				x="1766.9"
				y="1705.68"
				z="0"/>
		</Prop>
		<Prop
			Angle="0.930026"
			EventList=""
			Faction="/team"
			Health="100"
			Team=""
			ThingTemplate="ASTdead03"
			id="ASTdead03">
			<Position
				x="1519.96"
				y="1729.78"
				z="0"/>
		</Prop>
		<Prop
			Angle="-0.646971"
			EventList=""
			Faction="/team"
			Health="100"
			Team=""
			ThingTemplate="ASTdead06"
			id="ASTDEAD06">
			<Position
				x="1528.66"
				y="1633.82"
				z="0"/>
		</Prop>
		<Prop
			Angle="-0.576833"
			EventList=""
			Faction="/team"
			Health="100"
			Team=""
			ThingTemplate="ASTdead02"
			id="ASTDEAD02">
			<Position
				x="1501.79"
				y="1640.92"
				z="0"/>
		</Prop>
		<Prop
			Angle="0.378025"
			EventList=""
			Faction="/team"
			Health="100"
			Team=""
			ThingTemplate="ASTdead06"
			id="ASTDEAD06">
			<Position
				x="1576.97"
				y="1752.18"
				z="0"/>
		</Prop>
		<Prop
			Angle="-2.57409"
			EventList=""
			Faction="/team"
			Health="100"
			Team=""
			ThingTemplate="ASTdead01"
			id="ASTdead01">
			<Position
				x="1603.27"
				y="1672.26"
				z="0"/>
		</Prop>
		<Prop
			Angle="-2.47208"
			EventList=""
			Faction="/team"
			Health="100"
			Team=""
			ThingTemplate="ASTdead02"
			id="ASTDEAD02">
			<Position
				x="1488.14"
				y="1633.4"
				z="0"/>
		</Prop>
		<Prop
			Angle="-2.51913"
			EventList=""
			Faction="/team"
			Health="100"
			Team=""
			ThingTemplate="ASTdead01"
			id="ASTdead01">
			<Position
				x="1544.29"
				y="1750.64"
				z="0"/>
		</Prop>
		<Prop
			Angle="-0.300609"
			EventList=""
			Faction="/team"
			Health="100"
			Team=""
			ThingTemplate="ASTdead06"
			id="ASTDEAD06">
			<Position
				x="1459.83"
				y="1744.33"
				z="0"/>
		</Prop>
		<Prop
			Angle="2.86524"
			EventList=""
			Faction="/team"
			Health="100"
			Team=""
			ThingTemplate="ASTdead01"
			id="ASTdead01">
			<Position
				x="1562.99"
				y="1764.09"
				z="0"/>
		</Prop>
		<Prop
			Angle="-1.14016"
			EventList=""
			Faction="/team"
			Health="100"
			Team=""
			ThingTemplate="ASTdead01"
			id="ASTdead01">
			<Position
				x="1562.81"
				y="1744.08"
				z="0"/>
		</Prop>
		<Prop
			Angle="1.11273"
			EventList=""
			Faction="/team"
			Health="100"
			Team=""
			ThingTemplate="ASTdead02"
			id="ASTDEAD02">
			<Position
				x="1461.33"
				y="1619.83"
				z="0"/>
		</Prop>
		<Prop
			Angle="-2.44821"
			EventList=""
			Faction="/team"
			Health="100"
			Team=""
			ThingTemplate="ASTdead01"
			id="ASTdead01">
			<Position
				x="1475.67"
				y="1644.52"
				z="0"/>
		</Prop>
		<Prop
			Angle="-2.1987"
			EventList=""
			Faction="/team"
			Health="100"
			Team=""
			ThingTemplate="ASTdead01"
			id="ASTdead01">
			<Position
				x="1411.64"
				y="1582.18"
				z="0"/>
		</Prop>
		<Prop
			Angle="-1.30147"
			EventList=""
			Faction="/team"
			Health="100"
			Team=""
			ThingTemplate="ASTdead01"
			id="ASTdead01">
			<Position
				x="1325.17"
				y="1422.96"
				z="0"/>
		</Prop>
		<Prop
			Angle="0.0758684"
			EventList=""
			Faction="/team"
			Health="100"
			Team=""
			ThingTemplate="ASTdead01"
			id="ASTdead01">
			<Position
				x="1308.55"
				y="1693.66"
				z="0"/>
		</Prop>
		<Prop
			Angle="1.69337"
			EventList=""
			Faction="/team"
			Health="100"
			Team=""
			ThingTemplate="ASTdead03"
			id="ASTdead03">
			<Position
				x="1318.79"
				y="1665.06"
				z="0"/>
		</Prop>
		<Prop
			Angle="0.171341"
			EventList=""
			Faction="/team"
			Health="100"
			Team=""
			ThingTemplate="ASTdead01"
			id="ASTdead01">
			<Position
				x="1354.95"
				y="1717.52"
				z="0"/>
		</Prop>
		<Prop
			Angle="-1.51074"
			EventList=""
			Faction="/team"
			Health="100"
			Team=""
			ThingTemplate="ASTdead01"
			id="ASTdead01">
			<Position
				x="1313.75"
				y="1625.38"
				z="0"/>
		</Prop>
		<Prop
			Angle="2.91837"
			EventList=""
			Faction="/team"
			Health="100"
			Team=""
			ThingTemplate="ASTdead06"
			id="ASTDEAD06">
			<Position
				x="1309.5"
				y="1590.41"
				z="0"/>
		</Prop>
		<Prop
			Angle="1.1047"
			EventList=""
			Faction="/team"
			Health="100"
			Team=""
			ThingTemplate="ASTdead02"
			id="ASTDEAD02">
			<Position
				x="1317.37"
				y="1565.7"
				z="0"/>
		</Prop>
		<Prop
			Angle="2.98398"
			EventList=""
			Faction="/team"
			Health="100"
			Team=""
			ThingTemplate="ASTdead01"
			id="ASTdead01">
			<Position
				x="1169.26"
				y="1758.39"
				z="0"/>
		</Prop>
		<Prop
			Angle="0.0150604"
			EventList=""
			Faction="/team"
			Health="100"
			Team=""
			ThingTemplate="ASTdead03"
			id="ASTdead03">
			<Position
				x="1214.45"
				y="1501.28"
				z="0"/>
		</Prop>
		<Prop
			Angle="-0.188297"
			EventList=""
			Faction="/team"
			Health="100"
			Team=""
			ThingTemplate="ASTdead06"
			id="ASTDEAD06">
			<Position
				x="1539.13"
				y="1488.87"
				z="0"/>
		</Prop>
		<Prop
			Angle="-2.0576"
			EventList=""
			Faction="/team"
			Health="100"
			Team=""
			ThingTemplate="ASTdead02"
			id="ASTDEAD02">
			<Position
				x="1170.11"
				y="1437.07"
				z="0"/>
		</Prop>
		<Prop
			Angle="-0.0042634"
			EventList=""
			Faction="/team"
			Health="100"
			Team=""
			ThingTemplate="ASTdead01"
			id="ASTdead01">
			<Position
				x="1351.69"
				y="1680.08"
				z="0"/>
		</Prop>
		<Prop
			Angle="-0.336524"
			EventList=""
			Faction="/team"
			Health="100"
			Team=""
			ThingTemplate="ASTdead03"
			id="ASTdead03">
			<Position
				x="1459.86"
				y="1281.13"
				z="0"/>
		</Prop>
		<Prop
			Angle="0.805904"
			EventList=""
			Faction="/team"
			Health="100"
			Team=""
			ThingTemplate="ASTdead02"
			id="ASTDEAD02">
			<Position
				x="1616.75"
				y="1523.09"
				z="0"/>
		</Prop>
		<Prop
			Angle="1.8181"
			EventList=""
			Faction="/team"
			Health="100"
			Team=""
			ThingTemplate="ASTdead02"
			id="ASTDEAD02">
			<Position
				x="1582.7"
				y="1329.1"
				z="0"/>
		</Prop>
		<Prop
			Angle="-1.15424"
			EventList=""
			Faction="/team"
			Health="100"
			Team=""
			ThingTemplate="ASTdead02"
			id="ASTDEAD02">
			<Position
				x="1137.3"
				y="1291.23"
				z="0"/>
		</Prop>
		<Prop
			Angle="1.5674"
			EventList=""
			Faction="/team"
			Health="100"
			Team=""
			ThingTemplate="ASTdead02"
			id="ASTDEAD02">
			<Position
				x="1204.92"
				y="1243.11"
				z="0"/>
		</Prop>
		<Prop
			Angle="-1.28893"
			EventList=""
			Faction="/team"
			Health="100"
			Team=""
			ThingTemplate="ASTdead06"
			id="ASTDEAD06">
			<Position
				x="1315.42"
				y="1388.06"
				z="0"/>
		</Prop>
		<Prop
			Angle="-1.03067"
			EventList=""
			Faction="/team"
			Health="100"
			Team=""
			ThingTemplate="ASTdead06"
			id="ASTDEAD06">
			<Position
				x="1302.35"
				y="1321.09"
				z="0"/>
		</Prop>
		<Prop
			Angle="2.79913"
			EventList=""
			Faction="/team"
			Health="100"
			Team=""
			ThingTemplate="ASTdead01"
			id="ASTdead01">
			<Position
				x="1422.76"
				y="1380.25"
				z="0"/>
		</Prop>
		<Prop
			Angle="-0.645472"
			EventList=""
			Faction="/team"
			Health="100"
			Team=""
			ThingTemplate="ASTdead01"
			id="ASTdead01">
			<Position
				x="1417.04"
				y="1283.47"
				z="0"/>
		</Prop>
		<Prop
			Angle="1.11844"
			EventList=""
			Faction="/team"
			Health="100"
			Team=""
			ThingTemplate="ASTdead02"
			id="ASTDEAD02">
			<Position
				x="1380.34"
				y="1285.99"
				z="0"/>
		</Prop>
		<Prop
			Angle="3.13623"
			EventList=""
			Faction="/team"
			Health="100"
			Team=""
			ThingTemplate="ASTdead02"
			id="ASTDEAD02">
			<Position
				x="1363.8"
				y="1251.39"
				z="0"/>
		</Prop>
		<Prop
			Angle="-1.20207"
			EventList=""
			Faction="/team"
			Health="100"
			Team=""
			ThingTemplate="ASTdead06"
			id="ASTDEAD06">
			<Position
				x="1420.99"
				y="1309.75"
				z="0"/>
		</Prop>
		<Prop
			Angle="1.90369"
			EventList=""
			Faction="/team"
			Health="100"
			Team=""
			ThingTemplate="ASTdead02"
			id="ASTDEAD02">
			<Position
				x="1357.45"
				y="1457.78"
				z="0"/>
		</Prop>
		<Prop
			Angle="-0.385818"
			EventList=""
			Faction="/team"
			Health="100"
			Team=""
			ThingTemplate="ASTdead02"
			id="ASTDEAD02">
			<Position
				x="1403.95"
				y="1423.4"
				z="0"/>
		</Prop>
		<Prop
			Angle="-0.351223"
			EventList=""
			Faction="/team"
			Health="100"
			Team=""
			ThingTemplate="ASTdead01"
			id="ASTdead01">
			<Position
				x="1319.1"
				y="1323.91"
				z="0"/>
		</Prop>
		<Prop
			Angle="1.09737"
			EventList=""
			Faction="PlyrCivilian/teamPlyrCivilian"
			Health="500"
			Team="PlyrCivilian"
			ThingTemplate="EGBMkt01_a"
			id="EGBMKT01_A">
			<Position
				x="1310.56"
				y="1063.55"
				z="0"/>
		</Prop>
		<Prop
			Angle="-1.3846"
			EventList=""
			Faction="PlyrCivilian/teamPlyrCivilian"
			Health="100"
			Team="PlyrCivilian"
			ThingTemplate="EGBMkt01_d"
			id="EGBMKT01_D">
			<Position
				x="1049.02"
				y="1622.79"
				z="0"/>
		</Prop>
		<Prop
			Angle="0"
			EventList=""
			Faction="SkirmishNeutral/teamSkirmishNeutral"
			Health="100"
			Team="SkirmishNeutral"
			ThingTemplate="VeterancyCrate"
			id="VeterancyCrate">
			<Position
				x="818.582"
				y="1731.68"
				z="0"/>
		</Prop>
		<Prop
			Angle="0"
			EventList=""
			Faction="SkirmishNeutral/teamSkirmishNeutral"
			Health="100"
			Team="SkirmishNeutral"
			ThingTemplate="VeterancyCrate"
			id="VeterancyCrate">
			<Position
				x="807.93"
				y="1719.84"
				z="0"/>
		</Prop>
		<Prop
			Angle="0"
			EventList=""
			Faction="SkirmishNeutral/teamSkirmishNeutral"
			Health="100"
			Team="SkirmishNeutral"
			ThingTemplate="SalvageCrate"
			id="SalvageCrate">
			<Position
				x="2158.24"
				y="1787.23"
				z="0"/>
		</Prop>
		<Prop
			Angle="0"
			EventList=""
			Faction="SkirmishNeutral/teamSkirmishNeutral"
			Health="100"
			Team="SkirmishNeutral"
			ThingTemplate="SalvageCrate"
			id="SalvageCrate">
			<Position
				x="2148.76"
				y="1771.57"
				z="0"/>
		</Prop>
		<Prop
			Angle="0"
			EventList=""
			Faction="SkirmishNeutral/teamSkirmishNeutral"
			Health="100"
			Team="SkirmishNeutral"
			ThingTemplate="MoneyCrate"
			id="MoneyCrate">
			<Position
				x="2014.12"
				y="484.808"
				z="0"/>
		</Prop>
		<Prop
			Angle="0"
			EventList=""
			Faction="SkirmishNeutral/teamSkirmishNeutral"
			Health="100"
			Team="SkirmishNeutral"
			ThingTemplate="MoneyCrate"
			id="MoneyCrate">
			<Position
				x="2006.08"
				y="460.614"
				z="0"/>
		</Prop>
		<Prop
			Angle="0"
			EventList=""
			Faction="SkirmishNeutral/teamSkirmishNeutral"
			Health="100"
			Team="SkirmishNeutral"
			ThingTemplate="VeterancyCrate"
			id="VeterancyCrate">
			<Position
				x="1990.52"
				y="2394.8"
				z="0"/>
		</Prop>
		<Prop
			Angle="0"
			EventList=""
			Faction="SkirmishNeutral/teamSkirmishNeutral"
			Health="100"
			Team="SkirmishNeutral"
			ThingTemplate="VeterancyCrate"
			id="VeterancyCrate">
			<Position
				x="1979.94"
				y="2371.88"
				z="0"/>
		</Prop>
		<Prop
			Angle="0"
			EventList=""
			Faction="SkirmishNeutral/teamSkirmishNeutral"
			Health="100"
			Team="SkirmishNeutral"
			ThingTemplate="MoneyCrate"
			id="MoneyCrate">
			<Position
				x="945.194"
				y="508.253"
				z="0"/>
		</Prop>
		<Prop
			Angle="0"
			EventList=""
			Faction="SkirmishNeutral/teamSkirmishNeutral"
			Health="100"
			Team="SkirmishNeutral"
			ThingTemplate="MoneyCrate"
			id="MoneyCrate">
			<Position
				x="955.395"
				y="488.846"
				z="0"/>
		</Prop>
		<Prop
			Angle="0"
			EventList=""
			Faction="PlyrCivilian/teamPlyrCivilian"
			Health="100"
			Team="PlyrCivilian"
			ThingTemplate="ITRocks13"
			id="ITROCKS13">
			<Position
				x="1678.82"
				y="2784.93"
				z="0"/>
		</Prop>
		<Prop
			Angle="0"
			EventList=""
			Faction="PlyrCivilian/teamPlyrCivilian"
			Health="100"
			Team="PlyrCivilian"
			ThingTemplate="ITRocks12"
			id="ITROCKS12">
			<Position
				x="94.9789"
				y="2674.16"
				z="0"/>
		</Prop>
		<Prop
			Angle="0"
			EventList=""
			Faction="PlyrCivilian/teamPlyrCivilian"
			Health="100"
			Team="PlyrCivilian"
			ThingTemplate="ITRocks11"
			id="ITROCKS11">
			<Position
				x="410.271"
				y="1995.03"
				z="50"/>
		</Prop>
		<Prop
			Angle="0"
			EventList=""
			Faction="PlyrCivilian/teamPlyrCivilian"
			Health="100"
			Team="PlyrCivilian"
			ThingTemplate="ITRocks09"
			id="ITROCKS09">
			<Position
				x="263.545"
				y="1748.35"
				z="0"/>
		</Prop>
		<Prop
			Angle="0"
			EventList=""
			Faction="PlyrCivilian/teamPlyrCivilian"
			Health="100"
			Team="PlyrCivilian"
			ThingTemplate="ITRocks14"
			id="ITROCKS14">
			<Position
				x="401.775"
				y="84.1798"
				z="0"/>
		</Prop>
		<Prop
			Angle="-1.19418"
			EventList=""
			Faction="PlyrCivilian/teamPlyrCivilian"
			Health="100"
			Team="PlyrCivilian"
			ThingTemplate="ITRocks12"
			id="ITROCKS12">
			<Position
				x="1221.4"
				y="305.231"
				z="0"/>
		</Prop>
		<Prop
			Angle="0.358147"
			EventList=""
			Faction="PlyrCivilian/teamPlyrCivilian"
			Health="100"
			Team="PlyrCivilian"
			ThingTemplate="ITRocks10"
			id="ITROCKS10">
			<Position
				x="2930.57"
				y="409.608"
				z="0"/>
		</Prop>
		<Prop
			Angle="0"
			EventList=""
			Faction="PlyrCivilian/teamPlyrCivilian"
			Health="100"
			Team="PlyrCivilian"
			ThingTemplate="ITRocks07"
			id="ITROCKS07">
			<Position
				x="2501.36"
				y="109.648"
				z="0"/>
		</Prop>
		<Prop
			Angle="0"
			EventList=""
			Faction="PlyrCivilian/teamPlyrCivilian"
			Health="100"
			Team="PlyrCivilian"
			ThingTemplate="ITRocks08"
			id="ITROCKS08">
			<Position
				x="2509.25"
				y="1219.82"
				z="0"/>
		</Prop>
		<Prop
			Angle="0"
			EventList=""
			Faction="PlyrCivilian/teamPlyrCivilian"
			Health="100"
			Team="PlyrCivilian"
			ThingTemplate="ITRocks09"
			id="ITROCKS09">
			<Position
				x="2503.77"
				y="1797.66"
				z="0"/>
		</Prop>
		<Prop
			Angle="0"
			EventList=""
			Faction="PlyrCivilian/teamPlyrCivilian"
			Health="100"
			Team="PlyrCivilian"
			ThingTemplate="ITRocks10"
			id="ITROCKS10">
			<Position
				x="2859.58"
				y="1119.56"
				z="45"/>
		</Prop>
		<Prop
			Angle="0"
			EventList=""
			Faction="PlyrCivilian/teamPlyrCivilian"
			Health="100"
			Team="PlyrCivilian"
			ThingTemplate="ITRocks12"
			id="ITROCKS12">
			<Position
				x="2504.26"
				y="2921.89"
				z="0"/>
		</Prop>
		<Prop
			Angle="0"
			EventList=""
			Faction="PlyrCivilian/teamPlyrCivilian"
			Health="100"
			Team="PlyrCivilian"
			ThingTemplate="ITRocks14"
			id="ITROCKS14">
			<Position
				x="2867.9"
				y="2518.8"
				z="0"/>
		</Prop>
		<Prop
			Angle="-3.13908"
			EventList=""
			Faction="SkirmishNeutral/teamSkirmishNeutral"
			Health="100"
			Team="SkirmishNeutral"
			ThingTemplate="TiberiumFieldBlue"
			id="TiberiumFieldBlue">
			<Position
				x="1479.97"
				y="82.5511"
				z="0"/>
		</Prop>
		<Prop
			Angle="-2.411"
			EventList=""
			Faction="SkirmishNeutral/teamSkirmishNeutral"
			Health="100"
			Team="SkirmishNeutral"
			ThingTemplate="TiberiumFieldBlue"
			id="TiberiumFieldBlue">
			<Position
				x="2758.41"
				y="172.122"
				z="0"/>
		</Prop>
		<Prop
			Angle="1.76116"
			EventList=""
			Faction="SkirmishNeutral/teamSkirmishNeutral"
			Health="100"
			Team="SkirmishNeutral"
			ThingTemplate="TiberiumFieldBlue"
			id="TiberiumFieldBlue">
			<Position
				x="2893.67"
				y="1517.05"
				z="0"/>
		</Prop>
		<Prop
			Angle="2.67282"
			EventList=""
			Faction="SkirmishNeutral/teamSkirmishNeutral"
			Health="100"
			Team="SkirmishNeutral"
			ThingTemplate="TiberiumFieldBlue"
			id="TiberiumFieldBlue">
			<Position
				x="2774.01"
				y="2848.62"
				z="0"/>
		</Prop>
		<Prop
			Angle="-2.77319"
			EventList=""
			Faction="SkirmishNeutral/teamSkirmishNeutral"
			Health="100"
			Team="SkirmishNeutral"
			ThingTemplate="TiberiumFieldBlue"
			id="TiberiumFieldBlue">
			<Position
				x="1434.5"
				y="2879.32"
				z="0"/>
		</Prop>
		<Prop
			Angle="-2.21459"
			EventList=""
			Faction="SkirmishNeutral/teamSkirmishNeutral"
			Health="100"
			Team="SkirmishNeutral"
			ThingTemplate="TiberiumFieldBlue"
			id="TiberiumFieldBlue">
			<Position
				x="161.203"
				y="2787.57"
				z="0"/>
		</Prop>
		<Prop
			Angle="-1.35317"
			EventList=""
			Faction="SkirmishNeutral/teamSkirmishNeutral"
			Health="100"
			Team="SkirmishNeutral"
			ThingTemplate="TiberiumFieldBlue"
			id="TiberiumFieldBlue">
			<Position
				x="84.5468"
				y="1474.45"
				z="0"/>
		</Prop>
		<Prop
			Angle="-0.653224"
			EventList=""
			Faction="SkirmishNeutral/teamSkirmishNeutral"
			Health="100"
			Team="SkirmishNeutral"
			ThingTemplate="TiberiumFieldBlue"
			id="TiberiumFieldBlue">
			<Position
				x="153.566"
				y="176.142"
				z="0"/>
		</Prop>
		<Audio
			ThingTemplate="Amb_BirdsSeagull2"
			id="Amb_BirdsSeagull2">
			<Position
				x="298.057"
				y="646.25"
				z="0"/>
		</Audio>
		<Audio
			ThingTemplate="Amb_BirdsSeagull"
			id="Amb_BirdsSeagull">
			<Position
				x="1264.66"
				y="604.314"
				z="0"/>
		</Audio>
		<Audio
			ThingTemplate="Amb_BirdsSeagull2"
			id="Amb_BirdsSeagull2">
			<Position
				x="2269.04"
				y="427.432"
				z="0"/>
		</Audio>
		<Audio
			ThingTemplate="Amb_BirdsSeagull"
			id="Amb_BirdsSeagull">
			<Position
				x="2340.82"
				y="1321.76"
				z="0"/>
		</Audio>
		<Audio
			ThingTemplate="Amb_BirdsSeagull2"
			id="Amb_BirdsSeagull2">
			<Position
				x="2584.65"
				y="2296.97"
				z="0"/>
		</Audio>
		<Audio
			ThingTemplate="Amb_BirdsSeagull"
			id="Amb_BirdsSeagull">
			<Position
				x="1733.37"
				y="2425.29"
				z="0"/>
		</Audio>
		<Audio
			ThingTemplate="Amb_BirdsSeagull2"
			id="Amb_BirdsSeagull2">
			<Position
				x="640.036"
				y="2480.38"
				z="0"/>
		</Audio>
		<Audio
			ThingTemplate="Amb_BirdsSeagull"
			id="Amb_BirdsSeagull">
			<Position
				x="678.981"
				y="1368.66"
				z="0"/>
		</Audio>
		<Audio
			ThingTemplate="AmbStream_Rain1"
			id="AmbStream_Rain1">
			<Position
				x="1487.12"
				y="1412.44"
				z="0"/>
		</Audio>
		<Audio
			ThingTemplate="AmbStream_YellowZone01_Temperate_5point1"
			id="AmbStream_YellowZone01_Temperate_5point1">
			<Position
				x="1465.41"
				y="1423.77"
				z="0"/>
		</Audio>
		<Audio
			ThingTemplate="Amb_OceanWaves1"
			id="Amb_OceanWaves1">
			<Position
				x="667.912"
				y="1589.15"
				z="0"/>
		</Audio>
		<Audio
			ThingTemplate="Amb_OceanWaves1"
			id="Amb_OceanWaves1">
			<Position
				x="483.774"
				y="2333.07"
				z="0"/>
		</Audio>
		<Audio
			ThingTemplate="Amb_OceanWaves1"
			id="Amb_OceanWaves1">
			<Position
				x="1408.37"
				y="2315.84"
				z="0"/>
		</Audio>
		<Audio
			ThingTemplate="Amb_OceanWaves1"
			id="Amb_OceanWaves1">
			<Position
				x="2298.58"
				y="2531.5"
				z="0"/>
		</Audio>
		<Audio
			ThingTemplate="Amb_OceanWaves1"
			id="Amb_OceanWaves1">
			<Position
				x="2302.44"
				y="1591.15"
				z="0"/>
		</Audio>
		<Audio
			ThingTemplate="Amb_OceanWaves1"
			id="Amb_OceanWaves1">
			<Position
				x="2441.25"
				y="657.355"
				z="0"/>
		</Audio>
		<Audio
			ThingTemplate="Amb_OceanWaves1"
			id="Amb_OceanWaves1">
			<Position
				x="1519.33"
				y="684.588"
				z="0"/>
		</Audio>
		<Audio
			ThingTemplate="Amb_OceanWaves1"
			id="Amb_OceanWaves1">
			<Position
				x="497.553"
				y="628.612"
				z="0"/>
		</Audio>
		<MapMetaData
			BorderSize="0"
			CRC="0"
			Description="Map:erl115-into-the-sea/Desc"
			DisplayName="erl115 - Into the Sea"
			FileName="Data"
			Height="300"
			IsMultiplayer="true"
			IsOfficial="false"
			NumPlayers="8"
			Width="300">
			<StartPosition
				Name="InitialCameraPosition">
				<Position
					x="0"
					y="0"
					z="0"/>
			</StartPosition>
			<StartPosition
				Name="Player_1_Start">
				<Position
					x="493.723"
					y="347.047"
					z="0"/>
			</StartPosition>
			<StartPosition
				Name="Player_2_Start">
				<Position
					x="461.263"
					y="1595.5"
					z="0"/>
			</StartPosition>
			<StartPosition
				Name="Player_3_Start">
				<Position
					x="528.423"
					y="2707.02"
					z="0"/>
			</StartPosition>
			<StartPosition
				Name="Player_4_Start">
				<Position
					x="1270.89"
					y="2545.14"
					z="0"/>
			</StartPosition>
			<StartPosition
				Name="Player_5_Start">
				<Position
					x="2404.71"
					y="2732.54"
					z="0"/>
			</StartPosition>
			<StartPosition
				Name="Player_6_Start">
				<Position
					x="2551.83"
					y="1659.92"
					z="0"/>
			</StartPosition>
			<StartPosition
				Name="Player_7_Start">
				<Position
					x="2523.59"
					y="514.173"
					z="0"/>
			</StartPosition>
			<StartPosition
				Name="Player_8_Start">
				<Position
					x="1638.99"
					y="433.658"
					z="0"/>
			</StartPosition>
		</MapMetaData>
		<EnvironmentData
			Cloud="TSCloudMed"
			Environment="EVDefault"
			Macro="TSNoiseUrb"/>
		<WorldDict>
			<RealProperty
				Key="cameraMinHeight"
				Value="250"/>
			<RealProperty
				Key="cameraMaxHeight"
				Value="450"/>
			<RealProperty
				Key="cameraPitchAngle"
				Value="40"/>
			<BoolProperty
				Key="isLivingWorldScriptHolder"
				Value="false"/>
			<AssetIdProperty
				Key="musicZone"
				Value="MusicPalette_BlueZone"/>
			<StringProperty
				Key="mapName"
				Value="erl115 - Into the Sea"/>
			<StringProperty
				Key="mapDescription"
				Value="Made by erl115."/>
			<IntProperty
				Key="compression"
				Value="1"/>
			<RealProperty
				Key="cameraGroundMinHeight"
				Value="0"/>
			<RealProperty
				Key="cameraGroundMaxHeight"
				Value="2560"/>
			<BoolProperty
				Key="isScenarioMultiplayer"
				Value="false"/>
			<IntProperty
				Key="weather"
				Value="1"/>
		</WorldDict>
	</GameMap>
	<TerrainTextureAtlas
		AllowLossyCompression="true"
		AtlasSize="2048"
		id="erl115intothesea">
		<Tile
			BaseTexture="ART:Terrain/TDirt_Aus03.tga"
			NormalTexture="ART:Terrain/TDirt_Aus03_nrm.tga"
			TextureID="64423149"/>
		<Tile
			BaseTexture="ART:Terrain/TDirt_Aus01.tga"
			NormalTexture="ART:Terrain/TDirt_Aus01_nrm.tga"
			TextureID="1030918754"/>
		<Tile
			BaseTexture="ART:Terrain/TDirt_Aus02b.tga"
			NormalTexture="ART:Terrain/TDirt_Aus02b_nrm.tga"
			TextureID="2151771990"/>
		<Tile
			BaseTexture="ART:Terrain/TDirt_Aus03b.tga"
			NormalTexture="ART:Terrain/TDirt_Aus03b_nrm.tga"
			TextureID="2466179484"/>
		<Tile
			BaseTexture="ART:Terrain/TDirt_Sar09.tga"
			NormalTexture="ART:Terrain/TDirt_Sar09_nrm.tga"
			TextureID="2650333996"/>
		<Tile
			BaseTexture="ART:Terrain/CnC3Default.tga"
			NormalTexture="ART:Terrain/CnC3Default_nrm.tga"
			TextureID="2793349879"/>
		<Tile
			BaseTexture="ART:Terrain/TDirt_Aus01b.tga"
			NormalTexture="ART:Terrain/TDirt_Aus01b_nrm.tga"
			TextureID="2821642813"/>
		<Tile
			BaseTexture="ART:Terrain/TDirt_RedZone01.tga"
			NormalTexture="ART:Terrain/TDirt_RedZone01_nrm.tga"
			TextureID="3001150286"/>
	</TerrainTextureAtlas>
	<GameScriptList
		id="_neutral_">
		<ScriptSet>
			<Script
				id="Fog">
				<Action
					Type="MAP_SHROUD_ALL">
					<ParameterList/>
				</Action>
			</Script>
			<Script
				id="Timer">
				<Action
					Type="SET_MILLISECOND_TIMER">
					<ParameterList/>
				</Action>
			</Script>
		</ScriptSet>
	</GameScriptList>
	<GameScriptList
		id="PlyrCivilian">
		<ScriptSet/>
	</GameScriptList>
	<GameScriptList
		id="PlyrCreeps">
		<ScriptSet/>
	</GameScriptList>
	<GameScriptList
		id="Skirmish">
		<ScriptSet/>
	</GameScriptList>
	<GameScriptList
		id="SkirmishNull">
		<ScriptSet/>
	</GameScriptList>
	<GameScriptList
		id="SkirmishObserver">
		<ScriptSet/>
	</GameScriptList>
	<GameScriptList
		id="SkirmishCommentator">
		<ScriptSet/>
	</GameScriptList>
	<GameScriptList
		id="SkirmishCivilian">
		<ScriptSet/>
	</GameScriptList>
	<GameScriptList
		id="SkirmishNeutral">
		<ScriptSet/>
	</GameScriptList>
	<GameScriptList
		id="SkirmishGDI">
		<ScriptSet/>
	</GameScriptList>
	<GameScriptList
		id="SkirmishSteelTalons">
		<ScriptSet/>
	</GameScriptList>
	<GameScriptList
		id="SkirmishZOCOM">
		<ScriptSet/>
	</GameScriptList>
	<GameScriptList
		id="SkirmishNod">
		<ScriptSet/>
	</GameScriptList>
	<GameScriptList
		id="SkirmishBlackHand">
		<ScriptSet/>
	</GameScriptList>
	<GameScriptList
		id="SkirmishMarkedOfKane">
		<ScriptSet/>
	</GameScriptList>
	<GameScriptList
		id="SkirmishAlien">
		<ScriptSet/>
	</GameScriptList>
	<GameScriptList
		id="SkirmishReaper17">
		<ScriptSet/>
	</GameScriptList>
	<GameScriptList
		id="SkirmishTraveler59">
		<ScriptSet/>
	</GameScriptList>
	<GameScriptList
		id="Player_1">
		<ScriptSet>
			<ScriptGroup
				id="KillsScript">
				<Script
					id="Getmoney">
					<Action
						Type="INCREMENT_COUNTER">
						<ParameterList/>
					</Action>
					<Action
						Type="PLAYER_GIVE_MONEY">
						<ParameterList/>
					</Action>
				</Script>
				<Script
					id="Total">
					<Action
						Type="SET_COUNTER">
						<ParameterList/>
					</Action>
					<Action
						Type="COUNTER_MATH_COUNTER">
						<ParameterList/>
					</Action>
					<Action
						Type="COUNTER_MATH_COUNTER">
						<ParameterList/>
					</Action>
					<Action
						Type="COUNTER_MATH_COUNTER">
						<ParameterList/>
					</Action>
				</Script>
				<Script
					id="Count">
					<Action
						Type="SET_PLAYER_KILLS_OF_KINDOF_TO_COUNTER">
						<ParameterList/>
					</Action>
					<Action
						Type="SET_PLAYER_KILLS_OF_KINDOF_TO_COUNTER">
						<ParameterList/>
					</Action>
					<Action
						Type="SET_PLAYER_KILLS_OF_KINDOF_TO_COUNTER">
						<ParameterList/>
					</Action>
				</Script>
			</ScriptGroup>
		</ScriptSet>
	</GameScriptList>
	<GameScriptList
		id="Player_2">
		<ScriptSet>
			<ScriptGroup
				id="KillsScript__1">
				<Script
					id="Getmoney__1">
					<Action
						Type="INCREMENT_COUNTER">
						<ParameterList/>
					</Action>
					<Action
						Type="PLAYER_GIVE_MONEY">
						<ParameterList/>
					</Action>
				</Script>
				<Script
					id="Total__1">
					<Action
						Type="SET_COUNTER">
						<ParameterList/>
					</Action>
					<Action
						Type="COUNTER_MATH_COUNTER">
						<ParameterList/>
					</Action>
					<Action
						Type="COUNTER_MATH_COUNTER">
						<ParameterList/>
					</Action>
					<Action
						Type="COUNTER_MATH_COUNTER">
						<ParameterList/>
					</Action>
				</Script>
				<Script
					id="Count__1">
					<Action
						Type="SET_PLAYER_KILLS_OF_KINDOF_TO_COUNTER">
						<ParameterList/>
					</Action>
					<Action
						Type="SET_PLAYER_KILLS_OF_KINDOF_TO_COUNTER">
						<ParameterList/>
					</Action>
					<Action
						Type="SET_PLAYER_KILLS_OF_KINDOF_TO_COUNTER">
						<ParameterList/>
					</Action>
				</Script>
			</ScriptGroup>
		</ScriptSet>
	</GameScriptList>
	<GameScriptList
		id="Player_3">
		<ScriptSet>
			<ScriptGroup
				id="KillsScript__2">
				<Script
					id="Getmoney__2">
					<Action
						Type="INCREMENT_COUNTER">
						<ParameterList/>
					</Action>
					<Action
						Type="PLAYER_GIVE_MONEY">
						<ParameterList/>
					</Action>
				</Script>
				<Script
					id="Total__2">
					<Action
						Type="SET_COUNTER">
						<ParameterList/>
					</Action>
					<Action
						Type="COUNTER_MATH_COUNTER">
						<ParameterList/>
					</Action>
					<Action
						Type="COUNTER_MATH_COUNTER">
						<ParameterList/>
					</Action>
					<Action
						Type="COUNTER_MATH_COUNTER">
						<ParameterList/>
					</Action>
				</Script>
				<Script
					id="Count__2">
					<Action
						Type="SET_PLAYER_KILLS_OF_KINDOF_TO_COUNTER">
						<ParameterList/>
					</Action>
					<Action
						Type="SET_PLAYER_KILLS_OF_KINDOF_TO_COUNTER">
						<ParameterList/>
					</Action>
					<Action
						Type="SET_PLAYER_KILLS_OF_KINDOF_TO_COUNTER">
						<ParameterList/>
					</Action>
				</Script>
			</ScriptGroup>
		</ScriptSet>
	</GameScriptList>
	<GameScriptList
		id="Player_4">
		<ScriptSet>
			<ScriptGroup
				id="KillsScript__3">
				<Script
					id="Getmoney__3">
					<Action
						Type="INCREMENT_COUNTER">
						<ParameterList/>
					</Action>
					<Action
						Type="PLAYER_GIVE_MONEY">
						<ParameterList/>
					</Action>
				</Script>
				<Script
					id="Total__3">
					<Action
						Type="SET_COUNTER">
						<ParameterList/>
					</Action>
					<Action
						Type="COUNTER_MATH_COUNTER">
						<ParameterList/>
					</Action>
					<Action
						Type="COUNTER_MATH_COUNTER">
						<ParameterList/>
					</Action>
					<Action
						Type="COUNTER_MATH_COUNTER">
						<ParameterList/>
					</Action>
				</Script>
				<Script
					id="Count__3">
					<Action
						Type="SET_PLAYER_KILLS_OF_KINDOF_TO_COUNTER">
						<ParameterList/>
					</Action>
					<Action
						Type="SET_PLAYER_KILLS_OF_KINDOF_TO_COUNTER">
						<ParameterList/>
					</Action>
					<Action
						Type="SET_PLAYER_KILLS_OF_KINDOF_TO_COUNTER">
						<ParameterList/>
					</Action>
				</Script>
			</ScriptGroup>
		</ScriptSet>
	</GameScriptList>
	<GameScriptList
		id="Player_5">
		<ScriptSet>
			<ScriptGroup
				id="KillsScript__4">
				<Script
					id="Getmoney__4">
					<Action
						Type="INCREMENT_COUNTER">
						<ParameterList/>
					</Action>
					<Action
						Type="PLAYER_GIVE_MONEY">
						<ParameterList/>
					</Action>
				</Script>
				<Script
					id="Total__4">
					<Action
						Type="SET_COUNTER">
						<ParameterList/>
					</Action>
					<Action
						Type="COUNTER_MATH_COUNTER">
						<ParameterList/>
					</Action>
					<Action
						Type="COUNTER_MATH_COUNTER">
						<ParameterList/>
					</Action>
					<Action
						Type="COUNTER_MATH_COUNTER">
						<ParameterList/>
					</Action>
				</Script>
				<Script
					id="Count__4">
					<Action
						Type="SET_PLAYER_KILLS_OF_KINDOF_TO_COUNTER">
						<ParameterList/>
					</Action>
					<Action
						Type="SET_PLAYER_KILLS_OF_KINDOF_TO_COUNTER">
						<ParameterList/>
					</Action>
					<Action
						Type="SET_PLAYER_KILLS_OF_KINDOF_TO_COUNTER">
						<ParameterList/>
					</Action>
				</Script>
			</ScriptGroup>
		</ScriptSet>
	</GameScriptList>
	<GameScriptList
		id="Player_6">
		<ScriptSet>
			<ScriptGroup
				id="KillsScript__5">
				<Script
					id="Getmoney__5">
					<Action
						Type="INCREMENT_COUNTER">
						<ParameterList/>
					</Action>
					<Action
						Type="PLAYER_GIVE_MONEY">
						<ParameterList/>
					</Action>
				</Script>
				<Script
					id="Total__5">
					<Action
						Type="SET_COUNTER">
						<ParameterList/>
					</Action>
					<Action
						Type="COUNTER_MATH_COUNTER">
						<ParameterList/>
					</Action>
					<Action
						Type="COUNTER_MATH_COUNTER">
						<ParameterList/>
					</Action>
					<Action
						Type="COUNTER_MATH_COUNTER">
						<ParameterList/>
					</Action>
				</Script>
				<Script
					id="Count__5">
					<Action
						Type="SET_PLAYER_KILLS_OF_KINDOF_TO_COUNTER">
						<ParameterList/>
					</Action>
					<Action
						Type="SET_PLAYER_KILLS_OF_KINDOF_TO_COUNTER">
						<ParameterList/>
					</Action>
					<Action
						Type="SET_PLAYER_KILLS_OF_KINDOF_TO_COUNTER">
						<ParameterList/>
					</Action>
				</Script>
			</ScriptGroup>
		</ScriptSet>
	</GameScriptList>
	<GameScriptList
		id="Player_7">
		<ScriptSet>
			<ScriptGroup
				id="KillsScript__6">
				<Script
					id="Getmoney__6">
					<Action
						Type="INCREMENT_COUNTER">
						<ParameterList/>
					</Action>
					<Action
						Type="PLAYER_GIVE_MONEY">
						<ParameterList/>
					</Action>
				</Script>
				<Script
					id="Total__6">
					<Action
						Type="SET_COUNTER">
						<ParameterList/>
					</Action>
					<Action
						Type="COUNTER_MATH_COUNTER">
						<ParameterList/>
					</Action>
					<Action
						Type="COUNTER_MATH_COUNTER">
						<ParameterList/>
					</Action>
					<Action
						Type="COUNTER_MATH_COUNTER">
						<ParameterList/>
					</Action>
				</Script>
				<Script
					id="Count__6">
					<Action
						Type="SET_PLAYER_KILLS_OF_KINDOF_TO_COUNTER">
						<ParameterList/>
					</Action>
					<Action
						Type="SET_PLAYER_KILLS_OF_KINDOF_TO_COUNTER">
						<ParameterList/>
					</Action>
					<Action
						Type="SET_PLAYER_KILLS_OF_KINDOF_TO_COUNTER">
						<ParameterList/>
					</Action>
				</Script>
			</ScriptGroup>
		</ScriptSet>
	</GameScriptList>
	<GameScriptList
		id="Player_8">
		<ScriptSet>
			<ScriptGroup
				id="KillsScript__7">
				<Script
					id="Getmoney__7">
					<Action
						Type="INCREMENT_COUNTER">
						<ParameterList/>
					</Action>
					<Action
						Type="PLAYER_GIVE_MONEY">
						<ParameterList/>
					</Action>
				</Script>
				<Script
					id="Total__7">
					<Action
						Type="SET_COUNTER">
						<ParameterList/>
					</Action>
					<Action
						Type="COUNTER_MATH_COUNTER">
						<ParameterList/>
					</Action>
					<Action
						Type="COUNTER_MATH_COUNTER">
						<ParameterList/>
					</Action>
					<Action
						Type="COUNTER_MATH_COUNTER">
						<ParameterList/>
					</Action>
				</Script>
				<Script
					id="Count__7">
					<Action
						Type="SET_PLAYER_KILLS_OF_KINDOF_TO_COUNTER">
						<ParameterList/>
					</Action>
					<Action
						Type="SET_PLAYER_KILLS_OF_KINDOF_TO_COUNTER">
						<ParameterList/>
					</Action>
					<Action
						Type="SET_PLAYER_KILLS_OF_KINDOF_TO_COUNTER">
						<ParameterList/>
					</Action>
				</Script>
			</ScriptGroup>
		</ScriptSet>
	</GameScriptList>
</AssetDeclaration>