<?xml version="1.0" encoding="UTF-8"?>
<AssetDeclaration
	xmlns="uri:ea.com:eala:asset"
	xmlns:xsi="http://www.w3.org/2001/XMLSchema-instance">
	<Tags/>
	<Includes>
		<Include
			source="DATA:static.xml"
			type="reference"/>
		<Include
			source="DATA:global.xml"
			type="reference"/>
		<Include
			source="ART:EVDefault.xml"
			type="instance"/>
		<Include
			source="ART:TSCloudMed.xml"
			type="instance"/>
		<Include
			source="ART:TSNoiseUrb.xml"
			type="instance"/>
		<Include
			source="DATA:GlobalData/roads.xml"
			type="instance"/>
		<Include
			source="DATA:civilian/eeurope_ee/props/eepauto01.xml"
			type="instance"/>
		<Include
			source="DATA:civilian/eeurope_ee/props/eepauto02.xml"
			type="instance"/>
		<Include
			source="DATA:civilian/eeurope_ee/props/eepauto03.xml"
			type="instance"/>
		<Include
			source="DATA:civilian/eeurope_ee/props/eepauto04.xml"
			type="instance"/>
		<Include
			source="DATA:civilian/eeurope_ee/props/eepauto05.xml"
			type="instance"/>
		<Include
			source="DATA:civilian/eeurope_ee/props/eepauto06.xml"
			type="instance"/>
		<Include
			source="DATA:civilian/eeurope_ee/props/eepauto07.xml"
			type="instance"/>
		<Include
			source="DATA:civilian/eeurope_ee/props/eepauto09.xml"
			type="instance"/>
		<Include
			source="DATA:civilian/washington_dc_dc/buildings/dcbsen01.xml"
			type="instance"/>
		<Include
			source="DATA:civilian/washington_dc_dc/props/dcpfence01.xml"
			type="instance"/>
		<Include
			source="DATA:civilian/washington_dc_dc/props/dcpfence02.xml"
			type="instance"/>
		<Include
			source="DATA:civilian/washington_dc_dc/props/dcpfence03.xml"
			type="instance"/>
		<Include
			source="DATA:civilian/washington_dc_dc/props/dcpstrli07.xml"
			type="instance"/>
		<Include
			source="DATA:neutral/structures/civbunker.xml"
			type="instance"/>
		<Include
			source="DATA:sounds/musicscript_unknownzone.xml"
			type="instance"/>
		<Include
			source="overrides.xml"
			type="all"/>
	</Includes>
	<GameMap
		id="erl115zombiemadnessremakev2.0">
		<Waypoint
			id="Waypoint 43">
			<Position
				x="1124.78"
				y="1457.68"
				z="0"/>
		</Waypoint>
		<Waypoint
			id="Waypoint 41">
			<Position
				x="1205.27"
				y="1454.51"
				z="0"/>
		</Waypoint>
		<Waypoint
			id="Waypoint 39">
			<Position
				x="1304.18"
				y="1456.64"
				z="0"/>
		</Waypoint>
		<Waypoint
			id="Waypoint 37">
			<Position
				x="1409.96"
				y="1461"
				z="0"/>
		</Waypoint>
		<Waypoint
			id="Waypoint 35">
			<Position
				x="1454.67"
				y="1420.22"
				z="0"/>
		</Waypoint>
		<Waypoint
			id="Waypoint 33">
			<Position
				x="1455.97"
				y="1319.43"
				z="0"/>
		</Waypoint>
		<Waypoint
			id="Waypoint 31">
			<Position
				x="1455.55"
				y="1198.35"
				z="0"/>
		</Waypoint>
		<Waypoint
			id="Waypoint 29">
			<Position
				x="1450.63"
				y="1102.52"
				z="0"/>
		</Waypoint>
		<Waypoint
			id="Waypoint 27">
			<Position
				x="1388.66"
				y="1060.55"
				z="0"/>
		</Waypoint>
		<Waypoint
			id="Waypoint 25">
			<Position
				x="1299.64"
				y="1060.6"
				z="0"/>
		</Waypoint>
		<Waypoint
			id="Waypoint 23">
			<Position
				x="1197.24"
				y="1060.07"
				z="0"/>
		</Waypoint>
		<Waypoint
			id="Waypoint 21">
			<Position
				x="1088.85"
				y="1066.92"
				z="0"/>
		</Waypoint>
		<Waypoint
			id="Waypoint 19">
			<Position
				x="1064.27"
				y="1153.32"
				z="0"/>
		</Waypoint>
		<Waypoint
			id="Waypoint 17">
			<Position
				x="1063.13"
				y="1285.08"
				z="0"/>
		</Waypoint>
		<Waypoint
			id="Waypoint 15">
			<Position
				x="1061.21"
				y="1422.37"
				z="0"/>
		</Waypoint>
		<Waypoint
			id="move1">
			<Position
				x="1250.95"
				y="1244.94"
				z="0"/>
		</Waypoint>
		<Waypoint
			id="Spawn8">
			<Position
				x="-476.906"
				y="1237.84"
				z="0"/>
		</Waypoint>
		<Waypoint
			id="Spawn7">
			<Position
				x="-462.245"
				y="-214.275"
				z="0"/>
		</Waypoint>
		<Waypoint
			id="Spawn6">
			<Position
				x="1260.98"
				y="-245.579"
				z="0"/>
		</Waypoint>
		<Waypoint
			id="Spawn5">
			<Position
				x="2683.16"
				y="-228.626"
				z="0"/>
		</Waypoint>
		<Waypoint
			id="Spawn4">
			<Position
				x="2706.82"
				y="1241.15"
				z="0"/>
		</Waypoint>
		<Waypoint
			id="Spawn3">
			<Position
				x="2635.54"
				y="2732.83"
				z="0"/>
		</Waypoint>
		<Waypoint
			id="Spawn2">
			<Position
				x="1204.43"
				y="2742.54"
				z="0"/>
		</Waypoint>
		<Waypoint
			id="Spawn1">
			<Position
				x="-162.721"
				y="2732.27"
				z="0"/>
		</Waypoint>
		<Waypoint
			id="Player_5_Start">
			<Position
				x="1231.46"
				y="238.294"
				z="0"/>
		</Waypoint>
		<Waypoint
			id="Player_4_Start">
			<Position
				x="1493.07"
				y="1005.7"
				z="0"/>
		</Waypoint>
		<Waypoint
			id="Player_3_Start">
			<Position
				x="1499.72"
				y="1503.24"
				z="0"/>
		</Waypoint>
		<Waypoint
			id="Player_2_Start">
			<Position
				x="1005.67"
				y="1493.01"
				z="0"/>
		</Waypoint>
		<Waypoint
			id="Player_1_Start">
			<Position
				x="1012.39"
				y="1015.73"
				z="0"/>
		</Waypoint>
		<Structure
			Angle="0"
			EventList=""
			Faction="PlyrCivilian/teamPlyrCivilian"
			Health="100"
			Team="PlyrCivilian"
			ThingTemplate="DCBSen01"
			id="DCBSEN01">
			<Position
				x="473.392"
				y="2293.99"
				z="0"/>
		</Structure>
		<Structure
			Angle="0"
			EventList=""
			Faction="PlyrCivilian/teamPlyrCivilian"
			Health="100"
			Team="PlyrCivilian"
			ThingTemplate="DCBSen01"
			id="DCBSEN01">
			<Position
				x="931.17"
				y="2386.28"
				z="0"/>
		</Structure>
		<Structure
			Angle="0"
			EventList=""
			Faction="PlyrCivilian/teamPlyrCivilian"
			Health="100"
			Team="PlyrCivilian"
			ThingTemplate="DCBSen01"
			id="DCBSEN01">
			<Position
				x="1549.21"
				y="2360.05"
				z="0"/>
		</Structure>
		<Structure
			Angle="0"
			EventList=""
			Faction="PlyrCivilian/teamPlyrCivilian"
			Health="100"
			Team="PlyrCivilian"
			ThingTemplate="DCBSen01"
			id="DCBSEN01">
			<Position
				x="2070.16"
				y="2304.86"
				z="0"/>
		</Structure>
		<Structure
			Angle="0"
			EventList=""
			Faction="PlyrCivilian/teamPlyrCivilian"
			Health="100"
			Team="PlyrCivilian"
			ThingTemplate="DCBSen01"
			id="DCBSEN01">
			<Position
				x="2061.15"
				y="1649.42"
				z="0"/>
		</Structure>
		<Structure
			Angle="0"
			EventList=""
			Faction="PlyrCivilian/teamPlyrCivilian"
			Health="100"
			Team="PlyrCivilian"
			ThingTemplate="DCBSen01"
			id="DCBSEN01">
			<Position
				x="2012.45"
				y="1186.3"
				z="0"/>
		</Structure>
		<Structure
			Angle="0"
			EventList=""
			Faction="PlyrCivilian/teamPlyrCivilian"
			Health="100"
			Team="PlyrCivilian"
			ThingTemplate="DCBSen01"
			id="DCBSEN01">
			<Position
				x="1850.23"
				y="708.264"
				z="0"/>
		</Structure>
		<Structure
			Angle="0"
			EventList=""
			Faction="PlyrCivilian/teamPlyrCivilian"
			Health="100"
			Team="PlyrCivilian"
			ThingTemplate="DCBSen01"
			id="DCBSEN01">
			<Position
				x="1561.36"
				y="279.672"
				z="0"/>
		</Structure>
		<Structure
			Angle="0"
			EventList=""
			Faction="PlyrCivilian/teamPlyrCivilian"
			Health="100"
			Team="PlyrCivilian"
			ThingTemplate="DCBSen01"
			id="DCBSEN01">
			<Position
				x="1025.35"
				y="240.729"
				z="0"/>
		</Structure>
		<Structure
			Angle="0"
			EventList=""
			Faction="PlyrCivilian/teamPlyrCivilian"
			Health="100"
			Team="PlyrCivilian"
			ThingTemplate="DCBSen01"
			id="DCBSEN01">
			<Position
				x="617.966"
				y="540.309"
				z="0"/>
		</Structure>
		<Structure
			Angle="0"
			EventList=""
			Faction="PlyrCivilian/teamPlyrCivilian"
			Health="100"
			Team="PlyrCivilian"
			ThingTemplate="DCBSen01"
			id="DCBSEN01">
			<Position
				x="414.277"
				y="1054.88"
				z="0"/>
		</Structure>
		<Structure
			Angle="0"
			EventList=""
			Faction="PlyrCivilian/teamPlyrCivilian"
			Health="100"
			Team="PlyrCivilian"
			ThingTemplate="DCBSen01"
			id="DCBSEN01">
			<Position
				x="364.63"
				y="1646.08"
				z="0"/>
		</Structure>
		<Structure
			Angle="0"
			EventList=""
			Faction="PlyrCivilian/teamPlyrCivilian"
			Health="100"
			Team="PlyrCivilian"
			ThingTemplate="DCPStrLi07"
			id="DCPSTRLI07">
			<Position
				x="841.715"
				y="875.619"
				z="0"/>
		</Structure>
		<Structure
			Angle="0"
			EventList=""
			Faction="PlyrCivilian/teamPlyrCivilian"
			Health="100"
			Team="PlyrCivilian"
			ThingTemplate="DCPStrLi07"
			id="DCPSTRLI07">
			<Position
				x="1283.2"
				y="817.86"
				z="0"/>
		</Structure>
		<Structure
			Angle="0"
			EventList=""
			Faction="PlyrCivilian/teamPlyrCivilian"
			Health="100"
			Team="PlyrCivilian"
			ThingTemplate="DCPStrLi07"
			id="DCPSTRLI07">
			<Position
				x="1661.68"
				y="907.097"
				z="0"/>
		</Structure>
		<Structure
			Angle="0"
			EventList=""
			Faction="PlyrCivilian/teamPlyrCivilian"
			Health="100"
			Team="PlyrCivilian"
			ThingTemplate="DCPStrLi07"
			id="DCPSTRLI07">
			<Position
				x="1688.74"
				y="1321.76"
				z="0"/>
		</Structure>
		<Structure
			Angle="0"
			EventList=""
			Faction="PlyrCivilian/teamPlyrCivilian"
			Health="100"
			Team="PlyrCivilian"
			ThingTemplate="DCPStrLi07"
			id="DCPSTRLI07">
			<Position
				x="1655.11"
				y="1764.96"
				z="0"/>
		</Structure>
		<Structure
			Angle="0"
			EventList=""
			Faction="PlyrCivilian/teamPlyrCivilian"
			Health="100"
			Team="PlyrCivilian"
			ThingTemplate="DCPStrLi07"
			id="DCPSTRLI07">
			<Position
				x="1226.7"
				y="1804.77"
				z="0"/>
		</Structure>
		<Structure
			Angle="0"
			EventList=""
			Faction="PlyrCivilian/teamPlyrCivilian"
			Health="100"
			Team="PlyrCivilian"
			ThingTemplate="DCPStrLi07"
			id="DCPSTRLI07">
			<Position
				x="873.009"
				y="1782.72"
				z="0"/>
		</Structure>
		<Structure
			Angle="0"
			EventList=""
			Faction="PlyrCivilian/teamPlyrCivilian"
			Health="100"
			Team="PlyrCivilian"
			ThingTemplate="DCPStrLi07"
			id="DCPSTRLI07">
			<Position
				x="792.164"
				y="1247.09"
				z="0"/>
		</Structure>
		<Structure
			Angle="-1.53384"
			EventList=""
			Faction="PlyrCivilian/teamPlyrCivilian"
			Health="500"
			Team="PlyrCivilian"
			ThingTemplate="ZOCOMWatchTower"
			id="ZOCOMWatchTower">
			<Position
				x="1246.41"
				y="1239.04"
				z="0"/>
		</Structure>
		<Structure
			Angle="0"
			EventList=""
			Faction="PlyrCivilian/teamPlyrCivilian"
			Health="300"
			Team="PlyrCivilian"
			ThingTemplate="CivBunker"
			id="CivBunker">
			<Position
				x="1243.96"
				y="881.395"
				z="0"/>
		</Structure>
		<Structure
			Angle="0"
			EventList=""
			Faction="PlyrCivilian/teamPlyrCivilian"
			Health="300"
			Team="PlyrCivilian"
			ThingTemplate="CivBunker"
			id="CivBunker">
			<Position
				x="1556.58"
				y="925.502"
				z="0"/>
		</Structure>
		<Structure
			Angle="0"
			EventList=""
			Faction="PlyrCivilian/teamPlyrCivilian"
			Health="300"
			Team="PlyrCivilian"
			ThingTemplate="CivBunker"
			id="CivBunker">
			<Position
				x="1614.56"
				y="1243.33"
				z="0"/>
		</Structure>
		<Structure
			Angle="0"
			EventList=""
			Faction="PlyrCivilian/teamPlyrCivilian"
			Health="300"
			Team="PlyrCivilian"
			ThingTemplate="CivBunker"
			id="CivBunker">
			<Position
				x="1563.67"
				y="1570.16"
				z="0"/>
		</Structure>
		<Structure
			Angle="0"
			EventList=""
			Faction="PlyrCivilian/teamPlyrCivilian"
			Health="300"
			Team="PlyrCivilian"
			ThingTemplate="CivBunker"
			id="CivBunker">
			<Position
				x="1234.69"
				y="1612.56"
				z="0"/>
		</Structure>
		<Structure
			Angle="0"
			EventList=""
			Faction="PlyrCivilian/teamPlyrCivilian"
			Health="300"
			Team="PlyrCivilian"
			ThingTemplate="CivBunker"
			id="CivBunker">
			<Position
				x="931.294"
				y="1558.3"
				z="0"/>
		</Structure>
		<Structure
			Angle="0"
			EventList=""
			Faction="PlyrCivilian/teamPlyrCivilian"
			Health="300"
			Team="PlyrCivilian"
			ThingTemplate="CivBunker"
			id="CivBunker">
			<Position
				x="877.055"
				y="1239.24"
				z="0"/>
		</Structure>
		<Structure
			Angle="0"
			EventList=""
			Faction="PlyrCivilian/teamPlyrCivilian"
			Health="300"
			Team="PlyrCivilian"
			ThingTemplate="CivBunker"
			id="CivBunker">
			<Position
				x="929.895"
				y="913.725"
				z="0"/>
		</Structure>
		<Structure
			Angle="0"
			EventList=""
			Faction="PlyrCivilian/teamPlyrCivilian"
			Health="300"
			Team="PlyrCivilian"
			ThingTemplate="CivBunker"
			id="CivBunker">
			<Position
				x="1170.55"
				y="1565.6"
				z="0"/>
		</Structure>
		<Structure
			Angle="0"
			EventList=""
			Faction="PlyrCivilian/teamPlyrCivilian"
			Health="300"
			Team="PlyrCivilian"
			ThingTemplate="CivBunker"
			id="CivBunker">
			<Position
				x="1298.19"
				y="1563.29"
				z="0"/>
		</Structure>
		<Structure
			Angle="0"
			EventList=""
			Faction="PlyrCivilian/teamPlyrCivilian"
			Health="300"
			Team="PlyrCivilian"
			ThingTemplate="CivBunker"
			id="CivBunker">
			<Position
				x="924.096"
				y="1460.63"
				z="0"/>
		</Structure>
		<Structure
			Angle="0"
			EventList=""
			Faction="PlyrCivilian/teamPlyrCivilian"
			Health="300"
			Team="PlyrCivilian"
			ThingTemplate="CivBunker"
			id="CivBunker">
			<Position
				x="1014.07"
				y="1568.06"
				z="0"/>
		</Structure>
		<Structure
			Angle="0"
			EventList=""
			Faction="PlyrCivilian/teamPlyrCivilian"
			Health="300"
			Team="PlyrCivilian"
			ThingTemplate="CivBunker"
			id="CivBunker">
			<Position
				x="927.801"
				y="1165.58"
				z="0"/>
		</Structure>
		<Structure
			Angle="0"
			EventList=""
			Faction="PlyrCivilian/teamPlyrCivilian"
			Health="300"
			Team="PlyrCivilian"
			ThingTemplate="CivBunker"
			id="CivBunker">
			<Position
				x="926.406"
				y="1302.92"
				z="0"/>
		</Structure>
		<Structure
			Angle="-0.785398"
			EventList=""
			Faction="Player_5/teamPlayer_5"
			Health="100"
			Team="Player_5"
			ThingTemplate="GDIConstructionYard"
			id="GDIConstructionYard">
			<Position
				x="193.879"
				y="-680.029"
				z="0"/>
		</Structure>
		<Structure
			Angle="-0.785398"
			EventList=""
			Faction="Player_4/teamPlayer_4"
			Health="100"
			Team="Player_4"
			ThingTemplate="GDIConstructionYard"
			id="GDIConstructionYard">
			<Position
				x="179.254"
				y="-683.42"
				z="0"/>
		</Structure>
		<Structure
			Angle="-0.785398"
			EventList=""
			Faction="Player_3/teamPlayer_3"
			Health="100"
			Team="Player_3"
			ThingTemplate="GDIConstructionYard"
			id="GDIConstructionYard">
			<Position
				x="207.859"
				y="-692.027"
				z="0"/>
		</Structure>
		<Structure
			Angle="-0.785398"
			EventList=""
			Faction="Player_2/teamPlayer_2"
			Health="100"
			Team="Player_2"
			ThingTemplate="GDIConstructionYard"
			id="GDIConstructionYard">
			<Position
				x="166.738"
				y="-685.188"
				z="0"/>
		</Structure>
		<Structure
			Angle="-0.785398"
			EventList=""
			Faction="Player_1/teamPlayer_1"
			Health="100"
			Team="Player_1"
			ThingTemplate="GDIConstructionYard"
			id="GDIConstructionYard">
			<Position
				x="157.554"
				y="-707.333"
				z="0"/>
		</Structure>
		<Structure
			Angle="0"
			EventList=""
			Faction="Player_1/teamPlayer_1"
			Health="100"
			Team="Player_1"
			ThingTemplate="GDIMedicalBay"
			id="GDIMedicalBay">
			<Position
				x="801.538"
				y="996.314"
				z="0"/>
		</Structure>
		<Structure
			Angle="0"
			EventList=""
			Faction="Player_2/teamPlayer_2"
			Health="100"
			Team="Player_2"
			ThingTemplate="GDIMedicalBay"
			id="GDIMedicalBay">
			<Position
				x="789.49"
				y="1502.98"
				z="0"/>
		</Structure>
		<Structure
			Angle="0"
			EventList=""
			Faction="Player_3/teamPlayer_3"
			Health="100"
			Team="Player_3"
			ThingTemplate="GDIMedicalBay"
			id="GDIMedicalBay">
			<Position
				x="1707.47"
				y="1489.2"
				z="0"/>
		</Structure>
		<Structure
			Angle="0"
			EventList=""
			Faction="Player_4/teamPlayer_4"
			Health="100"
			Team="Player_4"
			ThingTemplate="GDIMedicalBay"
			id="GDIMedicalBay">
			<Position
				x="1697.03"
				y="1003.22"
				z="0"/>
		</Structure>
		<Structure
			Angle="0"
			EventList=""
			Faction="PlyrCivilian/teamPlyrCivilian"
			Health="300"
			Team="PlyrCivilian"
			ThingTemplate="CivBunker"
			id="CivBunker">
			<Position
				x="1568.01"
				y="1484.17"
				z="0"/>
		</Structure>
		<Structure
			Angle="0"
			EventList=""
			Faction="PlyrCivilian/teamPlyrCivilian"
			Health="300"
			Team="PlyrCivilian"
			ThingTemplate="CivBunker"
			id="CivBunker">
			<Position
				x="1177.54"
				y="929.774"
				z="0"/>
		</Structure>
		<Structure
			Angle="0"
			EventList=""
			Faction="PlyrCivilian/teamPlyrCivilian"
			Health="300"
			Team="PlyrCivilian"
			ThingTemplate="CivBunker"
			id="CivBunker">
			<Position
				x="1484.79"
				y="923.84"
				z="0"/>
		</Structure>
		<Structure
			Angle="0"
			EventList=""
			Faction="PlyrCivilian/teamPlyrCivilian"
			Health="300"
			Team="PlyrCivilian"
			ThingTemplate="CivBunker"
			id="CivBunker">
			<Position
				x="1576.51"
				y="1172.73"
				z="0"/>
		</Structure>
		<Structure
			Angle="0"
			EventList=""
			Faction="PlyrCivilian/teamPlyrCivilian"
			Health="300"
			Team="PlyrCivilian"
			ThingTemplate="CivBunker"
			id="CivBunker">
			<Position
				x="1491.64"
				y="1570.64"
				z="0"/>
		</Structure>
		<Structure
			Angle="-0.762522"
			EventList=""
			Faction="Player_4/teamPlayer_4"
			Health="100"
			Team="Player_4"
			ThingTemplate="GDIArmory"
			id="GDIArmory">
			<Position
				x="378.42"
				y="-706.717"
				z="0"/>
		</Structure>
		<Structure
			Angle="-0.785398"
			EventList=""
			Faction="Player_3/teamPlayer_3"
			Health="100"
			Team="Player_3"
			ThingTemplate="GDIArmory"
			id="GDIArmory">
			<Position
				x="372.747"
				y="-715.312"
				z="0"/>
		</Structure>
		<Structure
			Angle="-0.785398"
			EventList=""
			Faction="Player_2/teamPlayer_2"
			Health="100"
			Team="Player_2"
			ThingTemplate="GDIArmory"
			id="GDIArmory">
			<Position
				x="339.06"
				y="-723.476"
				z="0"/>
		</Structure>
		<Structure
			Angle="-0.785398"
			EventList=""
			Faction="Player_1/teamPlayer_1"
			Health="100"
			Team="Player_1"
			ThingTemplate="GDIArmory"
			id="GDIArmory">
			<Position
				x="349.587"
				y="-720.27"
				z="0"/>
		</Structure>
		<Structure
			Angle="1.5708"
			EventList=""
			Faction="Player_4/teamPlayer_4"
			Health="100"
			Team="Player_4"
			ThingTemplate="GDICommandPost"
			id="GDICommandPost">
			<Position
				x="1500.62"
				y="772.572"
				z="0"/>
		</Structure>
		<Structure
			Angle="-1.5708"
			EventList=""
			Faction="Player_3/teamPlayer_3"
			Health="100"
			Team="Player_3"
			ThingTemplate="GDICommandPost"
			id="GDICommandPost">
			<Position
				x="1493.42"
				y="1704.05"
				z="0"/>
		</Structure>
		<Structure
			Angle="-1.5708"
			EventList=""
			Faction="Player_2/teamPlayer_2"
			Health="100"
			Team="Player_2"
			ThingTemplate="GDICommandPost"
			id="GDICommandPost">
			<Position
				x="1001.47"
				y="1714.33"
				z="0"/>
		</Structure>
		<Structure
			Angle="1.5708"
			EventList=""
			Faction="Player_1/teamPlayer_1"
			Health="100"
			Team="Player_1"
			ThingTemplate="GDICommandPost"
			id="GDICommandPost">
			<Position
				x="994.516"
				y="780.423"
				z="0"/>
		</Structure>
		<Structure
			Angle="0"
			EventList=""
			Faction="PlyrCivilian/teamPlyrCivilian"
			Health="300"
			Team="PlyrCivilian"
			ThingTemplate="CivBunker"
			id="CivBunker">
			<Position
				x="1305.15"
				y="927.188"
				z="0"/>
		</Structure>
		<Structure
			Angle="0"
			EventList=""
			Faction="PlyrCivilian/teamPlyrCivilian"
			Health="300"
			Team="PlyrCivilian"
			ThingTemplate="CivBunker"
			id="CivBunker">
			<Position
				x="1572.24"
				y="1002.66"
				z="0"/>
		</Structure>
		<Structure
			Angle="0"
			EventList=""
			Faction="PlyrCivilian/teamPlyrCivilian"
			Health="300"
			Team="PlyrCivilian"
			ThingTemplate="CivBunker"
			id="CivBunker">
			<Position
				x="1570.36"
				y="1303.35"
				z="0"/>
		</Structure>
		<Structure
			Angle="0"
			EventList=""
			Faction="PlyrCivilian/teamPlyrCivilian"
			Health="300"
			Team="PlyrCivilian"
			ThingTemplate="CivBunker"
			id="CivBunker">
			<Position
				x="929.237"
				y="1007.59"
				z="0"/>
		</Structure>
		<Structure
			Angle="0"
			EventList=""
			Faction="PlyrCivilian/teamPlyrCivilian"
			Health="300"
			Team="PlyrCivilian"
			ThingTemplate="CivBunker"
			id="CivBunker">
			<Position
				x="1005.31"
				y="909.064"
				z="0"/>
		</Structure>
		<Structure
			Angle="-1.5752"
			EventList=""
			Faction="Player_4/teamPlayer_4"
			Health="100"
			Team="Player_4"
			ThingTemplate="GDIBarracks"
			id="GDIBarracks">
			<Position
				x="1360.23"
				y="1169.41"
				z="0"/>
		</Structure>
		<Structure
			Angle="1.56142"
			EventList=""
			Faction="Player_2/teamPlayer_2"
			Health="100"
			Team="Player_2"
			ThingTemplate="GDIBarracks"
			id="GDIBarracks">
			<Position
				x="1141.03"
				y="1326.07"
				z="0"/>
		</Structure>
		<Structure
			Angle="1.57177"
			EventList=""
			Faction="Player_3/teamPlayer_3"
			Health="100"
			Team="Player_3"
			ThingTemplate="GDIBarracks"
			id="GDIBarracks">
			<Position
				x="1359.89"
				y="1328.49"
				z="0"/>
		</Structure>
		<Structure
			Angle="-1.55021"
			EventList=""
			Faction="Player_1/teamPlayer_1"
			Health="100"
			Team="Player_1"
			ThingTemplate="GDIBarracks"
			id="GDIBarracks">
			<Position
				x="1140.59"
				y="1162.09"
				z="0"/>
		</Structure>
		<Unit
			Angle="0"
			EventList=""
			Faction="Player_4/teamPlayer_4"
			Health="100"
			Team="Player_4"
			ThingTemplate="MarkedOfKaneTibTrooper"
			id="MarkedOfKaneTibTrooper">
			<Position
				x="1626.45"
				y="884.929"
				z="0"/>
		</Unit>
		<Unit
			Angle="0"
			EventList=""
			Faction="Player_4/teamPlayer_4"
			Health="100"
			Team="Player_4"
			ThingTemplate="ZOCOMCommando"
			id="ZOCOMCommando">
			<Position
				x="1603.16"
				y="887.102"
				z="0"/>
		</Unit>
		<Unit
			Angle="0"
			EventList=""
			Faction="Player_4/teamPlayer_4"
			Health="100"
			Team="Player_4"
			ThingTemplate="MarkedOfKaneBunkerTruck"
			id="MarkedOfKaneBunkerTruck">
			<Position
				x="1607.61"
				y="847.467"
				z="0"/>
		</Unit>
		<Unit
			Angle="0"
			EventList=""
			Faction="Player_4/teamPlayer_4"
			Health="100"
			Team="Player_4"
			ThingTemplate="MarkedOfKaneCommando"
			id="MarkedOfKaneCommando">
			<Position
				x="1590.33"
				y="881.688"
				z="0"/>
		</Unit>
		<Unit
			Angle="0"
			EventList=""
			Faction="Player_3/teamPlayer_3"
			Health="100"
			Team="Player_3"
			ThingTemplate="MarkedOfKaneTibTrooper"
			id="MarkedOfKaneTibTrooper">
			<Position
				x="1630.2"
				y="1652.66"
				z="0"/>
		</Unit>
		<Unit
			Angle="0"
			EventList=""
			Faction="Player_3/teamPlayer_3"
			Health="100"
			Team="Player_3"
			ThingTemplate="ZOCOMCommando"
			id="ZOCOMCommando">
			<Position
				x="1606.9"
				y="1654.83"
				z="0"/>
		</Unit>
		<Unit
			Angle="0"
			EventList=""
			Faction="Player_3/teamPlayer_3"
			Health="100"
			Team="Player_3"
			ThingTemplate="MarkedOfKaneBunkerTruck"
			id="MarkedOfKaneBunkerTruck">
			<Position
				x="1611.35"
				y="1615.19"
				z="0"/>
		</Unit>
		<Unit
			Angle="0"
			EventList=""
			Faction="Player_3/teamPlayer_3"
			Health="100"
			Team="Player_3"
			ThingTemplate="MarkedOfKaneCommando"
			id="MarkedOfKaneCommando">
			<Position
				x="1594.08"
				y="1649.41"
				z="0"/>
		</Unit>
		<Unit
			Angle="0"
			EventList=""
			Faction="Player_2/teamPlayer_2"
			Health="100"
			Team="Player_2"
			ThingTemplate="MarkedOfKaneTibTrooper"
			id="MarkedOfKaneTibTrooper">
			<Position
				x="911.918"
				y="1669.95"
				z="0"/>
		</Unit>
		<Unit
			Angle="0"
			EventList=""
			Faction="Player_2/teamPlayer_2"
			Health="100"
			Team="Player_2"
			ThingTemplate="ZOCOMCommando"
			id="ZOCOMCommando">
			<Position
				x="888.622"
				y="1672.12"
				z="0"/>
		</Unit>
		<Unit
			Angle="0"
			EventList=""
			Faction="Player_2/teamPlayer_2"
			Health="100"
			Team="Player_2"
			ThingTemplate="MarkedOfKaneBunkerTruck"
			id="MarkedOfKaneBunkerTruck">
			<Position
				x="893.071"
				y="1632.48"
				z="0"/>
		</Unit>
		<Unit
			Angle="0"
			EventList=""
			Faction="Player_2/teamPlayer_2"
			Health="100"
			Team="Player_2"
			ThingTemplate="MarkedOfKaneCommando"
			id="MarkedOfKaneCommando">
			<Position
				x="875.797"
				y="1666.71"
				z="0"/>
		</Unit>
		<Unit
			Angle="0"
			EventList=""
			Faction="Player_1/teamPlayer_1"
			Health="100"
			Team="Player_1"
			ThingTemplate="MarkedOfKaneTibTrooper"
			id="MarkedOfKaneTibTrooper">
			<Position
				x="930.601"
				y="856.172"
				z="0"/>
		</Unit>
		<Unit
			Angle="0"
			EventList=""
			Faction="Player_1/teamPlayer_1"
			Health="100"
			Team="Player_1"
			ThingTemplate="ZOCOMCommando"
			id="ZOCOMCommando">
			<Position
				x="907.306"
				y="858.345"
				z="0"/>
		</Unit>
		<Unit
			Angle="0"
			EventList=""
			Faction="Player_1/teamPlayer_1"
			Health="100"
			Team="Player_1"
			ThingTemplate="MarkedOfKaneBunkerTruck"
			id="MarkedOfKaneBunkerTruck">
			<Position
				x="911.754"
				y="818.71"
				z="0"/>
		</Unit>
		<Unit
			Angle="0"
			EventList=""
			Faction="Player_1/teamPlayer_1"
			Health="100"
			Team="Player_1"
			ThingTemplate="MarkedOfKaneCommando"
			id="MarkedOfKaneCommando">
			<Position
				x="894.481"
				y="852.931"
				z="0"/>
		</Unit>
		<Prop
			Angle="-0.0438905"
			EventList=""
			Faction="PlyrCivilian/teamPlyrCivilian"
			Health="100"
			Team="PlyrCivilian"
			ThingTemplate="EEPAuto02"
			id="EEPAUTO02">
			<Position
				x="837.394"
				y="1876.31"
				z="0"/>
		</Prop>
		<Prop
			Angle="-2.10052"
			EventList=""
			Faction="PlyrCivilian/teamPlyrCivilian"
			Health="100"
			Team="PlyrCivilian"
			ThingTemplate="EEPAuto03"
			id="EEPAUTO03">
			<Position
				x="607.786"
				y="835.167"
				z="0"/>
		</Prop>
		<Prop
			Angle="-1.84834"
			EventList=""
			Faction="PlyrCivilian/teamPlyrCivilian"
			Health="100"
			Team="PlyrCivilian"
			ThingTemplate="EEPAuto06"
			id="EEPAUTO06">
			<Position
				x="769.231"
				y="715.678"
				z="0"/>
		</Prop>
		<Prop
			Angle="0"
			EventList=""
			Faction="PlyrCivilian/teamPlyrCivilian"
			Health="100"
			Team="PlyrCivilian"
			ThingTemplate="EEPAuto01"
			id="EEPAuto01">
			<Position
				x="850.17"
				y="1714.27"
				z="0"/>
		</Prop>
		<Prop
			Angle="-0.0438905"
			EventList=""
			Faction="PlyrCivilian/teamPlyrCivilian"
			Health="100"
			Team="PlyrCivilian"
			ThingTemplate="EEPAuto02"
			id="EEPAUTO02">
			<Position
				x="1895.48"
				y="1732.27"
				z="0"/>
		</Prop>
		<Prop
			Angle="-2.10052"
			EventList=""
			Faction="PlyrCivilian/teamPlyrCivilian"
			Health="100"
			Team="PlyrCivilian"
			ThingTemplate="EEPAuto03"
			id="EEPAUTO03">
			<Position
				x="1883.27"
				y="1070.23"
				z="0"/>
		</Prop>
		<Prop
			Angle="0"
			EventList=""
			Faction="PlyrCivilian/teamPlyrCivilian"
			Health="100"
			Team="PlyrCivilian"
			ThingTemplate="EEPAuto04"
			id="EEPAUTO04">
			<Position
				x="1214.31"
				y="1600.13"
				z="0"/>
		</Prop>
		<Prop
			Angle="1.20021"
			EventList=""
			Faction="PlyrCivilian/teamPlyrCivilian"
			Health="100"
			Team="PlyrCivilian"
			ThingTemplate="EEPAuto05"
			id="EEPAUTO05">
			<Position
				x="947.272"
				y="1109.73"
				z="0"/>
		</Prop>
		<Prop
			Angle="-1.84834"
			EventList=""
			Faction="PlyrCivilian/teamPlyrCivilian"
			Health="100"
			Team="PlyrCivilian"
			ThingTemplate="EEPAuto06"
			id="EEPAUTO06">
			<Position
				x="1003.41"
				y="944.788"
				z="0"/>
		</Prop>
		<Prop
			Angle="-1.05699"
			EventList=""
			Faction="PlyrCivilian/teamPlyrCivilian"
			Health="100"
			Team="PlyrCivilian"
			ThingTemplate="EEPAuto09"
			id="EEPAUTO09">
			<Position
				x="1463.6"
				y="965.393"
				z="0"/>
		</Prop>
		<Prop
			Angle="1.21515"
			EventList=""
			Faction="PlyrCreeps/teamPlyrCreeps"
			Health="100"
			Team="PlyrCreeps"
			ThingTemplate="EEPAuto07"
			id="EEPAUTO07">
			<Position
				x="1205.73"
				y="912.906"
				z="0"/>
		</Prop>
		<Prop
			Angle="1.65806"
			EventList=""
			Faction="PlyrCivilian/teamPlyrCivilian"
			Health="100"
			Team="PlyrCivilian"
			ThingTemplate="DCPFence01"
			id="DCPFENCE01">
			<Position
				x="1513.06"
				y="1385.17"
				z="0"/>
		</Prop>
		<Prop
			Angle="1.39515"
			EventList=""
			Faction="PlyrCivilian/teamPlyrCivilian"
			Health="100"
			Team="PlyrCivilian"
			ThingTemplate="DCPFence01"
			id="DCPFENCE01">
			<Position
				x="1513.25"
				y="1335.39"
				z="0"/>
		</Prop>
		<Prop
			Angle="1.65806"
			EventList=""
			Faction="PlyrCivilian/teamPlyrCivilian"
			Health="100"
			Team="PlyrCivilian"
			ThingTemplate="DCPFence01"
			id="DCPFENCE01">
			<Position
				x="1513.41"
				y="1318.42"
				z="0"/>
		</Prop>
		<Prop
			Angle="1.65806"
			EventList=""
			Faction="PlyrCivilian/teamPlyrCivilian"
			Health="100"
			Team="PlyrCivilian"
			ThingTemplate="DCPFence01"
			id="DCPFENCE01">
			<Position
				x="1515.99"
				y="1352.3"
				z="0"/>
		</Prop>
		<Prop
			Angle="1.65806"
			EventList=""
			Faction="PlyrCivilian/teamPlyrCivilian"
			Health="100"
			Team="PlyrCivilian"
			ThingTemplate="DCPFence01"
			id="DCPFENCE01">
			<Position
				x="1514.94"
				y="1368.93"
				z="0"/>
		</Prop>
		<Prop
			Angle="1.81867"
			EventList=""
			Faction="PlyrCivilian/teamPlyrCivilian"
			Health="100"
			Team="PlyrCivilian"
			ThingTemplate="DCPFence01"
			id="DCPFENCE01">
			<Position
				x="1511.74"
				y="1402.08"
				z="0"/>
		</Prop>
		<Prop
			Angle="0.515323"
			EventList=""
			Faction="PlyrCivilian/teamPlyrCivilian"
			Health="100"
			Team="PlyrCivilian"
			ThingTemplate="DCPFence01"
			id="DCPFENCE01">
			<Position
				x="1181.05"
				y="1512.28"
				z="0"/>
		</Prop>
		<Prop
			Angle="0"
			EventList=""
			Faction="PlyrCivilian/teamPlyrCivilian"
			Health="100"
			Team="PlyrCivilian"
			ThingTemplate="DCPFence01"
			id="DCPFENCE01">
			<Position
				x="1151.39"
				y="1504.69"
				z="0"/>
		</Prop>
		<Prop
			Angle="0"
			EventList=""
			Faction="PlyrCivilian/teamPlyrCivilian"
			Health="100"
			Team="PlyrCivilian"
			ThingTemplate="DCPFence01"
			id="DCPFENCE01">
			<Position
				x="1101.67"
				y="1507.18"
				z="0"/>
		</Prop>
		<Prop
			Angle="-0.223646"
			EventList=""
			Faction="PlyrCivilian/teamPlyrCivilian"
			Health="100"
			Team="PlyrCivilian"
			ThingTemplate="DCPFence01"
			id="DCPFENCE01">
			<Position
				x="1084.56"
				y="1511.19"
				z="0"/>
		</Prop>
		<Prop
			Angle="0.205669"
			EventList=""
			Faction="PlyrCivilian/teamPlyrCivilian"
			Health="100"
			Team="PlyrCivilian"
			ThingTemplate="DCPFence01"
			id="DCPFENCE01">
			<Position
				x="1118.43"
				y="1506.67"
				z="0"/>
		</Prop>
		<Prop
			Angle="-0.253911"
			EventList=""
			Faction="PlyrCivilian/teamPlyrCivilian"
			Health="100"
			Team="PlyrCivilian"
			ThingTemplate="DCPFence01"
			id="DCPFENCE01">
			<Position
				x="1135.59"
				y="1509.68"
				z="0"/>
		</Prop>
		<Prop
			Angle="0.515323"
			EventList=""
			Faction="PlyrCivilian/teamPlyrCivilian"
			Health="100"
			Team="PlyrCivilian"
			ThingTemplate="DCPFence01"
			id="DCPFENCE01">
			<Position
				x="1166.97"
				y="1504.59"
				z="0"/>
		</Prop>
		<Prop
			Angle="1.65806"
			EventList=""
			Faction="PlyrCivilian/teamPlyrCivilian"
			Health="100"
			Team="PlyrCivilian"
			ThingTemplate="DCPFence01"
			id="DCPFENCE01">
			<Position
				x="1004.88"
				y="1388.37"
				z="0"/>
		</Prop>
		<Prop
			Angle="1.39515"
			EventList=""
			Faction="PlyrCivilian/teamPlyrCivilian"
			Health="100"
			Team="PlyrCivilian"
			ThingTemplate="DCPFence01"
			id="DCPFENCE01">
			<Position
				x="1005.07"
				y="1338.58"
				z="0"/>
		</Prop>
		<Prop
			Angle="1.65806"
			EventList=""
			Faction="PlyrCivilian/teamPlyrCivilian"
			Health="100"
			Team="PlyrCivilian"
			ThingTemplate="DCPFence01"
			id="DCPFENCE01">
			<Position
				x="1005.23"
				y="1321.62"
				z="0"/>
		</Prop>
		<Prop
			Angle="1.65806"
			EventList=""
			Faction="PlyrCivilian/teamPlyrCivilian"
			Health="100"
			Team="PlyrCivilian"
			ThingTemplate="DCPFence01"
			id="DCPFENCE01">
			<Position
				x="1007.81"
				y="1355.5"
				z="0"/>
		</Prop>
		<Prop
			Angle="1.65806"
			EventList=""
			Faction="PlyrCivilian/teamPlyrCivilian"
			Health="100"
			Team="PlyrCivilian"
			ThingTemplate="DCPFence01"
			id="DCPFENCE01">
			<Position
				x="1006.76"
				y="1372.13"
				z="0"/>
		</Prop>
		<Prop
			Angle="1.81867"
			EventList=""
			Faction="PlyrCivilian/teamPlyrCivilian"
			Health="100"
			Team="PlyrCivilian"
			ThingTemplate="DCPFence01"
			id="DCPFENCE01">
			<Position
				x="1003.56"
				y="1405.28"
				z="0"/>
		</Prop>
		<Prop
			Angle="-0"
			EventList=""
			Faction="PlyrCivilian/teamPlyrCivilian"
			Health="100"
			Team="PlyrCivilian"
			ThingTemplate="DCPFence01"
			id="DCPFENCE01">
			<Position
				x="1383.65"
				y="1511.28"
				z="0"/>
		</Prop>
		<Prop
			Angle="0.154636"
			EventList=""
			Faction="PlyrCivilian/teamPlyrCivilian"
			Health="100"
			Team="PlyrCivilian"
			ThingTemplate="DCPFence01"
			id="DCPFENCE01">
			<Position
				x="1303.15"
				y="1510.07"
				z="0"/>
		</Prop>
		<Prop
			Angle="0.164726"
			EventList=""
			Faction="PlyrCivilian/teamPlyrCivilian"
			Health="100"
			Team="PlyrCivilian"
			ThingTemplate="DCPFence01"
			id="DCPFENCE01">
			<Position
				x="1351.22"
				y="1508.28"
				z="0"/>
		</Prop>
		<Prop
			Angle="-0.208736"
			EventList=""
			Faction="PlyrCivilian/teamPlyrCivilian"
			Health="100"
			Team="PlyrCivilian"
			ThingTemplate="DCPFence01"
			id="DCPFENCE01">
			<Position
				x="1320.06"
				y="1511.42"
				z="0"/>
		</Prop>
		<Prop
			Angle="-0"
			EventList=""
			Faction="PlyrCivilian/teamPlyrCivilian"
			Health="100"
			Team="PlyrCivilian"
			ThingTemplate="DCPFence01"
			id="DCPFENCE01">
			<Position
				x="1335.63"
				y="1508"
				z="0"/>
		</Prop>
		<Prop
			Angle="0.176213"
			EventList=""
			Faction="PlyrCivilian/teamPlyrCivilian"
			Health="100"
			Team="PlyrCivilian"
			ThingTemplate="DCPFence01"
			id="DCPFENCE01">
			<Position
				x="1399.69"
				y="1509.92"
				z="0"/>
		</Prop>
		<Prop
			Angle="-0"
			EventList=""
			Faction="PlyrCivilian/teamPlyrCivilian"
			Health="100"
			Team="PlyrCivilian"
			ThingTemplate="DCPFence01"
			id="DCPFENCE01">
			<Position
				x="1367.27"
				y="1511.27"
				z="0"/>
		</Prop>
		<Prop
			Angle="-1.39006"
			EventList=""
			Faction="PlyrCivilian/teamPlyrCivilian"
			Health="100"
			Team="PlyrCivilian"
			ThingTemplate="DCPFence01"
			id="DCPFENCE01">
			<Position
				x="1009.2"
				y="1096.8"
				z="0"/>
		</Prop>
		<Prop
			Angle="-0"
			EventList=""
			Faction="PlyrCivilian/teamPlyrCivilian"
			Health="100"
			Team="PlyrCivilian"
			ThingTemplate="DCPFence01"
			id="DCPFENCE01">
			<Position
				x="1165.08"
				y="999.784"
				z="0"/>
		</Prop>
		<Prop
			Angle="0.154636"
			EventList=""
			Faction="PlyrCivilian/teamPlyrCivilian"
			Health="100"
			Team="PlyrCivilian"
			ThingTemplate="DCPFence01"
			id="DCPFENCE01">
			<Position
				x="1084.57"
				y="998.572"
				z="0"/>
		</Prop>
		<Prop
			Angle="-0"
			EventList=""
			Faction="PlyrCivilian/teamPlyrCivilian"
			Health="100"
			Team="PlyrCivilian"
			ThingTemplate="DCPFence01"
			id="DCPFENCE01">
			<Position
				x="1309.79"
				y="993.124"
				z="0"/>
		</Prop>
		<Prop
			Angle="-0.128549"
			EventList=""
			Faction="PlyrCivilian/teamPlyrCivilian"
			Health="100"
			Team="PlyrCivilian"
			ThingTemplate="DCPFence01"
			id="DCPFENCE01">
			<Position
				x="1341.37"
				y="1000.62"
				z="0"/>
		</Prop>
		<Prop
			Angle="-0"
			EventList=""
			Faction="PlyrCivilian/teamPlyrCivilian"
			Health="100"
			Team="PlyrCivilian"
			ThingTemplate="DCPFence01"
			id="DCPFENCE01">
			<Position
				x="1374"
				y="999.98"
				z="0"/>
		</Prop>
		<Prop
			Angle="0.164726"
			EventList=""
			Faction="PlyrCivilian/teamPlyrCivilian"
			Health="100"
			Team="PlyrCivilian"
			ThingTemplate="DCPFence01"
			id="DCPFENCE01">
			<Position
				x="1132.64"
				y="996.782"
				z="0"/>
		</Prop>
		<Prop
			Angle="-0.208736"
			EventList=""
			Faction="PlyrCivilian/teamPlyrCivilian"
			Health="100"
			Team="PlyrCivilian"
			ThingTemplate="DCPFence01"
			id="DCPFENCE01">
			<Position
				x="1101.48"
				y="999.922"
				z="0"/>
		</Prop>
		<Prop
			Angle="-0"
			EventList=""
			Faction="PlyrCivilian/teamPlyrCivilian"
			Health="100"
			Team="PlyrCivilian"
			ThingTemplate="DCPFence01"
			id="DCPFENCE01">
			<Position
				x="1117.05"
				y="996.51"
				z="0"/>
		</Prop>
		<Prop
			Angle="-0.267682"
			EventList=""
			Faction="PlyrCivilian/teamPlyrCivilian"
			Health="100"
			Team="PlyrCivilian"
			ThingTemplate="DCPFence01"
			id="DCPFENCE01">
			<Position
				x="1181.11"
				y="998.422"
				z="0"/>
		</Prop>
		<Prop
			Angle="-0"
			EventList=""
			Faction="PlyrCivilian/teamPlyrCivilian"
			Health="100"
			Team="PlyrCivilian"
			ThingTemplate="DCPFence01"
			id="DCPFENCE01">
			<Position
				x="1148.69"
				y="999.772"
				z="0"/>
		</Prop>
		<Prop
			Angle="-1.45958"
			EventList=""
			Faction="PlyrCivilian/teamPlyrCivilian"
			Health="100"
			Team="PlyrCivilian"
			ThingTemplate="DCPFence01"
			id="DCPFENCE01">
			<Position
				x="1012.27"
				y="1080.21"
				z="0"/>
		</Prop>
		<Prop
			Angle="1.65806"
			EventList=""
			Faction="PlyrCivilian/teamPlyrCivilian"
			Health="100"
			Team="PlyrCivilian"
			ThingTemplate="DCPFence01"
			id="DCPFENCE01">
			<Position
				x="1510.62"
				y="1160.75"
				z="0"/>
		</Prop>
		<Prop
			Angle="1.39515"
			EventList=""
			Faction="PlyrCivilian/teamPlyrCivilian"
			Health="100"
			Team="PlyrCivilian"
			ThingTemplate="DCPFence01"
			id="DCPFENCE01">
			<Position
				x="1510.81"
				y="1110.96"
				z="0"/>
		</Prop>
		<Prop
			Angle="1.65806"
			EventList=""
			Faction="PlyrCivilian/teamPlyrCivilian"
			Health="100"
			Team="PlyrCivilian"
			ThingTemplate="DCPFence01"
			id="DCPFENCE01">
			<Position
				x="1510.97"
				y="1094"
				z="0"/>
		</Prop>
		<Prop
			Angle="1.65806"
			EventList=""
			Faction="PlyrCivilian/teamPlyrCivilian"
			Health="100"
			Team="PlyrCivilian"
			ThingTemplate="DCPFence01"
			id="DCPFENCE01">
			<Position
				x="1513.55"
				y="1127.88"
				z="0"/>
		</Prop>
		<Prop
			Angle="-0.0740169"
			EventList=""
			Faction="PlyrCivilian/teamPlyrCivilian"
			Health="100"
			Team="PlyrCivilian"
			ThingTemplate="DCPFence01"
			id="DCPFENCE01">
			<Position
				x="1391.05"
				y="1000.29"
				z="0"/>
		</Prop>
		<Prop
			Angle="0.127334"
			EventList=""
			Faction="PlyrCivilian/teamPlyrCivilian"
			Health="100"
			Team="PlyrCivilian"
			ThingTemplate="DCPFence01"
			id="DCPFENCE01">
			<Position
				x="1357.69"
				y="998.258"
				z="0"/>
		</Prop>
		<Prop
			Angle="-0.410453"
			EventList=""
			Faction="PlyrCivilian/teamPlyrCivilian"
			Health="100"
			Team="PlyrCivilian"
			ThingTemplate="DCPFence01"
			id="DCPFENCE01">
			<Position
				x="1407.9"
				y="998.92"
				z="0"/>
		</Prop>
		<Prop
			Angle="1.65806"
			EventList=""
			Faction="PlyrCivilian/teamPlyrCivilian"
			Health="100"
			Team="PlyrCivilian"
			ThingTemplate="DCPFence01"
			id="DCPFENCE01">
			<Position
				x="1512.5"
				y="1144.51"
				z="0"/>
		</Prop>
		<Prop
			Angle="1.54838"
			EventList=""
			Faction="PlyrCivilian/teamPlyrCivilian"
			Health="100"
			Team="PlyrCivilian"
			ThingTemplate="DCPFence01"
			id="DCPFENCE01">
			<Position
				x="1509.3"
				y="1177.66"
				z="0"/>
		</Prop>
		<Prop
			Angle="-1.79029"
			EventList=""
			Faction="PlyrCivilian/teamPlyrCivilian"
			Health="100"
			Team="PlyrCivilian"
			ThingTemplate="DCPFence01"
			id="DCPFENCE01">
			<Position
				x="1012.05"
				y="1112.73"
				z="0"/>
		</Prop>
		<Prop
			Angle="-1.39006"
			EventList=""
			Faction="PlyrCivilian/teamPlyrCivilian"
			Health="100"
			Team="PlyrCivilian"
			ThingTemplate="DCPFence01"
			id="DCPFENCE01">
			<Position
				x="1009.5"
				y="1129.7"
				z="0"/>
		</Prop>
		<Prop
			Angle="-0.387821"
			EventList=""
			Faction="PlyrCivilian/teamPlyrCivilian"
			Health="100"
			Team="PlyrCivilian"
			ThingTemplate="DCPFence02"
			id="DCPFENCE02">
			<Position
				x="1009.86"
				y="1148.37"
				z="0"/>
		</Prop>
		<Prop
			Angle="0.424486"
			EventList=""
			Faction="PlyrCivilian/teamPlyrCivilian"
			Health="100"
			Team="PlyrCivilian"
			ThingTemplate="DCPFence03"
			id="DCPFENCE03">
			<Position
				x="1326.02"
				y="993.226"
				z="0"/>
		</Prop>
		<Prop
			Angle="-1.39006"
			EventList=""
			Faction="PlyrCivilian/teamPlyrCivilian"
			Health="100"
			Team="PlyrCivilian"
			ThingTemplate="DCPFence01"
			id="DCPFENCE01">
			<Position
				x="1007.76"
				y="1164.5"
				z="0"/>
		</Prop>
		<Prop
			Angle="-1.67172"
			EventList=""
			Faction="PlyrCivilian/teamPlyrCivilian"
			Health="100"
			Team="PlyrCivilian"
			ThingTemplate="DCPFence01"
			id="DCPFENCE01">
			<Position
				x="1008.98"
				y="1180.06"
				z="0"/>
		</Prop>
		<MapMetaData
			BorderSize="80"
			CRC="0"
			Description="Map:erl115-zombiemadness-remake-v2/Desc"
			DisplayName="erl115 - Zombiemadness remake2 v2.0 normal"
			FileName="Data"
			Height="410"
			IsMultiplayer="true"
			IsOfficial="false"
			NumPlayers="5"
			Width="410">
			<StartPosition
				Name="InitialCameraPosition">
				<Position
					x="0"
					y="0"
					z="0"/>
			</StartPosition>
			<StartPosition
				Name="Player_1_Start">
				<Position
					x="1012.39"
					y="1015.73"
					z="0"/>
			</StartPosition>
			<StartPosition
				Name="Player_2_Start">
				<Position
					x="1005.67"
					y="1493.01"
					z="0"/>
			</StartPosition>
			<StartPosition
				Name="Player_3_Start">
				<Position
					x="1499.72"
					y="1503.24"
					z="0"/>
			</StartPosition>
			<StartPosition
				Name="Player_4_Start">
				<Position
					x="1493.07"
					y="1005.7"
					z="0"/>
			</StartPosition>
			<StartPosition
				Name="Player_5_Start">
				<Position
					x="1231.46"
					y="238.294"
					z="0"/>
			</StartPosition>
		</MapMetaData>
		<EnvironmentData
			Cloud="TSCloudMed"
			Environment="EVDefault"
			Macro="TSNoiseUrb"/>
		<WorldDict>
			<RealProperty
				Key="cameraMaxHeight"
				Value="400"/>
			<BoolProperty
				Key="isLivingWorldScriptHolder"
				Value="false"/>
			<AssetIdProperty
				Key="musicZone"
				Value="MusicPalette_NotSet"/>
			<IntProperty
				Key="weather"
				Value="0"/>
			<IntProperty
				Key="compression"
				Value="1"/>
			<StringProperty
				Key="mapName"
				Value="erl115 - Zombiemadness remake2 v2.0 normal"/>
			<StringProperty
				Key="mapDescription"
				Value=""/>
			<RealProperty
				Key="cameraGroundMinHeight"
				Value="0"/>
			<RealProperty
				Key="cameraGroundMaxHeight"
				Value="2560"/>
			<BoolProperty
				Key="isScenarioMultiplayer"
				Value="false"/>
		</WorldDict>
	</GameMap>
	<TerrainTextureAtlas
		AllowLossyCompression="true"
		AtlasSize="2048"
		id="erl115zombiemadnessremakev2.0">
		<Tile
			BaseTexture="ART:Terrain/TPave_Plaza05.tga"
			NormalTexture="ART:Terrain/TPave_Plaza05_nrm.tga"
			TextureID="1067003298"/>
		<Tile
			BaseTexture="ART:Terrain/TGrass_Aus02.tga"
			NormalTexture="ART:Terrain/TGrass_Aus02_nrm.tga"
			TextureID="2123701602"/>
		<Tile
			BaseTexture="ART:Terrain/CnC3DefaultBlack.tga"
			NormalTexture="ART:Terrain/CnC3DefaultBlack_nrm.tga"
			TextureID="2974579486"/>
		<Tile
			BaseTexture="ART:Terrain/TDirt_Mojave17.tga"
			NormalTexture="ART:Terrain/TDirt_Mojave17_nrm.tga"
			TextureID="3144225543"/>
		<Tile
			BaseTexture="ART:Terrain/TMisc_PavementEgypt03.tga"
			NormalTexture="ART:Terrain/TMisc_PavementEgypt03_nrm.tga"
			TextureID="3575571965"/>
		<Tile
			BaseTexture="ART:Terrain/CnC3Grid3.tga"
			NormalTexture="ART:Terrain/CnC3Grid3_nrm.tga"
			TextureID="3688474932"/>
		<Tile
			BaseTexture="ART:Terrain/TDirt_YellowZone03b.tga"
			NormalTexture="ART:Terrain/TDirt_YellowZone03b_nrm.tga"
			TextureID="3893590722"/>
		<Tile
			BaseTexture="ART:Terrain/TPave_Washington04.tga"
			NormalTexture="ART:Terrain/TPave_Washington04_nrm.tga"
			TextureID="3936714528"/>
	</TerrainTextureAtlas>
	<GameScriptList
		id="_neutral_">
		<ScriptSet>
			<Script
				id="Start fun">
				<Action
					Type="CREATE_UNNAMED_ON_TEAM_AT_WAYPOINT">
					<ParameterList>
						<ObjectType
							Object="EMPField"/>
					</ParameterList>
				</Action>
				<Action
					Type="CREATE_UNNAMED_ON_TEAM_AT_WAYPOINT">
					<ParameterList>
						<ObjectType
							Object="EMPField"/>
					</ParameterList>
				</Action>
				<Action
					Type="CREATE_UNNAMED_ON_TEAM_AT_WAYPOINT">
					<ParameterList>
						<ObjectType
							Object="EMPField"/>
					</ParameterList>
				</Action>
				<Action
					Type="CREATE_UNNAMED_ON_TEAM_AT_WAYPOINT">
					<ParameterList>
						<ObjectType
							Object="EMPField"/>
					</ParameterList>
				</Action>
				<Action
					Type="CREATE_UNNAMED_ON_TEAM_AT_WAYPOINT">
					<ParameterList>
						<ObjectType
							Object="EMPField"/>
					</ParameterList>
				</Action>
				<Action
					Type="CREATE_UNNAMED_ON_TEAM_AT_WAYPOINT">
					<ParameterList>
						<ObjectType
							Object="EMPField"/>
					</ParameterList>
				</Action>
				<Action
					Type="CREATE_UNNAMED_ON_TEAM_AT_WAYPOINT">
					<ParameterList>
						<ObjectType
							Object="EMPField"/>
					</ParameterList>
				</Action>
				<Action
					Type="CREATE_UNNAMED_ON_TEAM_AT_WAYPOINT">
					<ParameterList>
						<ObjectType
							Object="EMPField"/>
					</ParameterList>
				</Action>
				<Action
					Type="CREATE_UNNAMED_ON_TEAM_AT_WAYPOINT">
					<ParameterList>
						<ObjectType
							Object="EMPField"/>
					</ParameterList>
				</Action>
				<Action
					Type="CREATE_UNNAMED_ON_TEAM_AT_WAYPOINT">
					<ParameterList>
						<ObjectType
							Object="EMPField"/>
					</ParameterList>
				</Action>
				<Action
					Type="CREATE_UNNAMED_ON_TEAM_AT_WAYPOINT">
					<ParameterList>
						<ObjectType
							Object="EMPField"/>
					</ParameterList>
				</Action>
				<Action
					Type="CREATE_UNNAMED_ON_TEAM_AT_WAYPOINT">
					<ParameterList>
						<ObjectType
							Object="EMPField"/>
					</ParameterList>
				</Action>
				<Action
					Type="CREATE_UNNAMED_ON_TEAM_AT_WAYPOINT">
					<ParameterList>
						<ObjectType
							Object="EMPField"/>
					</ParameterList>
				</Action>
				<Action
					Type="CREATE_UNNAMED_ON_TEAM_AT_WAYPOINT">
					<ParameterList>
						<ObjectType
							Object="EMPField"/>
					</ParameterList>
				</Action>
				<Action
					Type="CREATE_UNNAMED_ON_TEAM_AT_WAYPOINT">
					<ParameterList>
						<ObjectType
							Object="EMPField"/>
					</ParameterList>
				</Action>
			</Script>
			<Script
				id="Start fun__1">
				<Action
					Type="CREATE_UNNAMED_ON_TEAM_AT_WAYPOINT">
					<ParameterList>
						<ObjectType
							Object="CivilianMale1"/>
					</ParameterList>
				</Action>
				<Action
					Type="CREATE_UNNAMED_ON_TEAM_AT_WAYPOINT">
					<ParameterList>
						<ObjectType
							Object="CivilianMale1"/>
					</ParameterList>
				</Action>
				<Action
					Type="CREATE_UNNAMED_ON_TEAM_AT_WAYPOINT">
					<ParameterList>
						<ObjectType
							Object="CivilianMale1"/>
					</ParameterList>
				</Action>
				<Action
					Type="CREATE_UNNAMED_ON_TEAM_AT_WAYPOINT">
					<ParameterList>
						<ObjectType
							Object="CivilianMale1"/>
					</ParameterList>
				</Action>
				<Action
					Type="CREATE_UNNAMED_ON_TEAM_AT_WAYPOINT">
					<ParameterList>
						<ObjectType
							Object="CivilianMale1"/>
					</ParameterList>
				</Action>
				<Action
					Type="CREATE_UNNAMED_ON_TEAM_AT_WAYPOINT">
					<ParameterList>
						<ObjectType
							Object="CivilianMale1"/>
					</ParameterList>
				</Action>
				<Action
					Type="CREATE_UNNAMED_ON_TEAM_AT_WAYPOINT">
					<ParameterList>
						<ObjectType
							Object="CivilianMale1"/>
					</ParameterList>
				</Action>
				<Action
					Type="CREATE_UNNAMED_ON_TEAM_AT_WAYPOINT">
					<ParameterList>
						<ObjectType
							Object="CivilianMale1"/>
					</ParameterList>
				</Action>
				<Action
					Type="CREATE_UNNAMED_ON_TEAM_AT_WAYPOINT">
					<ParameterList>
						<ObjectType
							Object="CivilianMale1"/>
					</ParameterList>
				</Action>
				<Action
					Type="CREATE_UNNAMED_ON_TEAM_AT_WAYPOINT">
					<ParameterList>
						<ObjectType
							Object="CivilianMale1"/>
					</ParameterList>
				</Action>
				<Action
					Type="CREATE_UNNAMED_ON_TEAM_AT_WAYPOINT">
					<ParameterList>
						<ObjectType
							Object="CivilianMale1"/>
					</ParameterList>
				</Action>
				<Action
					Type="CREATE_UNNAMED_ON_TEAM_AT_WAYPOINT">
					<ParameterList>
						<ObjectType
							Object="CivilianMale1"/>
					</ParameterList>
				</Action>
				<Action
					Type="CREATE_UNNAMED_ON_TEAM_AT_WAYPOINT">
					<ParameterList>
						<ObjectType
							Object="CivilianMale1"/>
					</ParameterList>
				</Action>
				<Action
					Type="CREATE_UNNAMED_ON_TEAM_AT_WAYPOINT">
					<ParameterList>
						<ObjectType
							Object="CivilianMale1"/>
					</ParameterList>
				</Action>
				<Action
					Type="CREATE_UNNAMED_ON_TEAM_AT_WAYPOINT">
					<ParameterList>
						<ObjectType
							Object="CivilianMale1"/>
					</ParameterList>
				</Action>
				<Action
					Type="SHOW_MILITARY_CAPTION">
					<ParameterList/>
				</Action>
			</Script>
			<Script
				id="counter secs">
				<Action
					Type="INCREMENT_COUNTER">
					<ParameterList/>
				</Action>
			</Script>
			<Script
				id="Nobuild">
				<Action
					Type="ALLOW_DISALLOW_ONE_BUILDING">
					<ParameterList>
						<ObjectType
							Object="GDIEngineer"/>
					</ParameterList>
				</Action>
				<Action
					Type="GIVE_PLAYER_UPGRADE">
					<ParameterList/>
				</Action>
			</Script>
			<Script
				id="General">
				<Action
					Type="SET_COUNTER">
					<ParameterList/>
				</Action>
				<Action
					Type="MAP_SWITCH_BORDER">
					<ParameterList/>
				</Action>
				<Action
					Type="MAP_REVEAL_ALL_PERM">
					<ParameterList/>
				</Action>
				<Action
					Type="DISABLE_BORDER_SHROUD">
					<ParameterList/>
				</Action>
				<Action
					Type="PLAYER_SET_BASE_POWER">
					<ParameterList/>
				</Action>
				<Action
					Type="PLAYER_SPECIAL_POWER_AVAILABILITY">
					<ParameterList/>
				</Action>
				<Action
					Type="PLAYER_SPECIAL_POWER_AVAILABILITY">
					<ParameterList/>
				</Action>
				<Action
					Type="PLAYER_DISABLE_BASE_CONSTRUCTION">
					<ParameterList/>
				</Action>
				<Action
					Type="ALLOW_DISALLOW_ONE_BUILDING">
					<ParameterList>
						<ObjectType
							Object="GDISurveyor"/>
					</ParameterList>
				</Action>
				<Action
					Type="PLAYER_SET_MONEY">
					<ParameterList/>
				</Action>
				<Action
					Type="DISPLAY_COUNTER">
					<ParameterList/>
				</Action>
				<Action
					Type="DISPLAY_COUNTDOWN_TIMER">
					<ParameterList/>
				</Action>
				<Action
					Type="SET_MILLISECOND_TIMER">
					<ParameterList/>
				</Action>
				<Action
					Type="MUSIC_SET_TRACK">
					<ParameterList/>
				</Action>
				<Action
					Type="DISABLE_UI_FIXED_ELEMENT">
					<ParameterList/>
				</Action>
				<Action
					Type="DISABLE_UI_FIXED_ELEMENT">
					<ParameterList/>
				</Action>
				<Action
					Type="DISABLE_UI_FIXED_ELEMENT">
					<ParameterList/>
				</Action>
			</Script>
			<Script
				id="Lose">
				<Action
					Type="PLAYER_KILL">
					<ParameterList/>
				</Action>
				<Action
					Type="PLAYER_KILL">
					<ParameterList/>
				</Action>
				<Action
					Type="PLAYER_KILL">
					<ParameterList/>
				</Action>
				<Action
					Type="PLAYER_KILL">
					<ParameterList/>
				</Action>
			</Script>
			<Script
				id="Zombie counting">
				<Action
					Type="SET_COUNTER">
					<ParameterList/>
				</Action>
				<Action
					Type="COUNTER_MATH_COUNTER">
					<ParameterList/>
				</Action>
				<Action
					Type="COUNTER_MATH_COUNTER">
					<ParameterList/>
				</Action>
				<Action
					Type="COUNTER_MATH_COUNTER">
					<ParameterList/>
				</Action>
				<Action
					Type="COUNTER_MATH_COUNTER">
					<ParameterList/>
				</Action>
			</Script>
			<ScriptGroup
				id="Balanced">
				<Script
					id="P1x">
					<Action
						Type="NO_OP">
						<ParameterList/>
					</Action>
					<Action
						Type="UNIT_KILL_ALL_IN_AREA">
						<ParameterList/>
					</Action>
				</Script>
				<Script
					id="P1x__1">
					<Action
						Type="NO_OP">
						<ParameterList/>
					</Action>
					<Action
						Type="UNIT_KILL_ALL_IN_AREA">
						<ParameterList/>
					</Action>
				</Script>
				<Script
					id="P1x__2">
					<Action
						Type="NO_OP">
						<ParameterList/>
					</Action>
					<Action
						Type="UNIT_KILL_ALL_IN_AREA">
						<ParameterList/>
					</Action>
				</Script>
				<Script
					id="P1x__3">
					<Action
						Type="NO_OP">
						<ParameterList/>
					</Action>
					<Action
						Type="UNIT_KILL_ALL_IN_AREA">
						<ParameterList/>
					</Action>
				</Script>
			</ScriptGroup>
			<ScriptGroup
				id="death hus">
				<Script
					id="p1 hus">
					<Action
						Type="NAMED_TRANSFER_OWNERSHIP_PLAYER">
						<ParameterList/>
					</Action>
					<Action
						Type="UNIT_AFFECT_OBJECT_PANEL_FLAGS">
						<ParameterList/>
					</Action>
				</Script>
				<Script
					id="p1 hus__1">
					<Action
						Type="NAMED_TRANSFER_OWNERSHIP_PLAYER">
						<ParameterList/>
					</Action>
					<Action
						Type="UNIT_AFFECT_OBJECT_PANEL_FLAGS">
						<ParameterList/>
					</Action>
				</Script>
				<Script
					id="p1 hus__2">
					<Action
						Type="NAMED_TRANSFER_OWNERSHIP_PLAYER">
						<ParameterList/>
					</Action>
					<Action
						Type="UNIT_AFFECT_OBJECT_PANEL_FLAGS">
						<ParameterList/>
					</Action>
				</Script>
				<Script
					id="p1 hus__3">
					<Action
						Type="NAMED_TRANSFER_OWNERSHIP_PLAYER">
						<ParameterList/>
					</Action>
					<Action
						Type="UNIT_AFFECT_OBJECT_PANEL_FLAGS">
						<ParameterList/>
					</Action>
				</Script>
			</ScriptGroup>
		</ScriptSet>
	</GameScriptList>
	<GameScriptList
		id="PlyrCivilian">
		<ScriptSet/>
	</GameScriptList>
	<GameScriptList
		id="PlyrCreeps">
		<ScriptSet/>
	</GameScriptList>
	<GameScriptList
		id="Skirmish">
		<ScriptSet/>
	</GameScriptList>
	<GameScriptList
		id="SkirmishNull">
		<ScriptSet/>
	</GameScriptList>
	<GameScriptList
		id="SkirmishObserver">
		<ScriptSet/>
	</GameScriptList>
	<GameScriptList
		id="SkirmishCommentator">
		<ScriptSet/>
	</GameScriptList>
	<GameScriptList
		id="SkirmishCivilian">
		<ScriptSet/>
	</GameScriptList>
	<GameScriptList
		id="SkirmishNeutral">
		<ScriptSet/>
	</GameScriptList>
	<GameScriptList
		id="SkirmishGDI">
		<ScriptSet/>
	</GameScriptList>
	<GameScriptList
		id="SkirmishSteelTalons">
		<ScriptSet/>
	</GameScriptList>
	<GameScriptList
		id="SkirmishZOCOM">
		<ScriptSet/>
	</GameScriptList>
	<GameScriptList
		id="SkirmishNod">
		<ScriptSet/>
	</GameScriptList>
	<GameScriptList
		id="SkirmishBlackHand">
		<ScriptSet/>
	</GameScriptList>
	<GameScriptList
		id="SkirmishMarkedOfKane">
		<ScriptSet/>
	</GameScriptList>
	<GameScriptList
		id="SkirmishAlien">
		<ScriptSet/>
	</GameScriptList>
	<GameScriptList
		id="SkirmishReaper17">
		<ScriptSet/>
	</GameScriptList>
	<GameScriptList
		id="SkirmishTraveler59">
		<ScriptSet/>
	</GameScriptList>
	<GameScriptList
		id="Player_1">
		<ScriptSet>
			<Script
				id="Friends">
				<Action
					Type="PLAYER_SET_OVERRIDE_RELATION_TO_TEAM">
					<ParameterList/>
				</Action>
				<Action
					Type="PLAYER_SET_OVERRIDE_RELATION_TO_TEAM">
					<ParameterList/>
				</Action>
				<Action
					Type="PLAYER_SET_OVERRIDE_RELATION_TO_TEAM">
					<ParameterList/>
				</Action>
			</Script>
			<ScriptGroup
				id="Counter zombies__3">
				<Script
					id="Counter__3 1">
					<Action
						Type="SET_PLAYER_KILLS_OF_KINDOF_TO_COUNTER">
						<ParameterList/>
					</Action>
				</Script>
			</ScriptGroup>
		</ScriptSet>
	</GameScriptList>
	<GameScriptList
		id="Player_2">
		<ScriptSet>
			<Script
				id="Friends__1">
				<Action
					Type="PLAYER_SET_OVERRIDE_RELATION_TO_TEAM">
					<ParameterList/>
				</Action>
				<Action
					Type="PLAYER_SET_OVERRIDE_RELATION_TO_TEAM">
					<ParameterList/>
				</Action>
				<Action
					Type="PLAYER_SET_OVERRIDE_RELATION_TO_TEAM">
					<ParameterList/>
				</Action>
			</Script>
			<ScriptGroup
				id="Counter zombies__4">
				<Script
					id="Counter__4">
					<Action
						Type="SET_PLAYER_KILLS_OF_KINDOF_TO_COUNTER">
						<ParameterList/>
					</Action>
				</Script>
			</ScriptGroup>
		</ScriptSet>
	</GameScriptList>
	<GameScriptList
		id="Player_3">
		<ScriptSet>
			<Script
				id="Friends__2">
				<Action
					Type="PLAYER_SET_OVERRIDE_RELATION_TO_TEAM">
					<ParameterList/>
				</Action>
				<Action
					Type="PLAYER_SET_OVERRIDE_RELATION_TO_TEAM">
					<ParameterList/>
				</Action>
				<Action
					Type="PLAYER_SET_OVERRIDE_RELATION_TO_TEAM">
					<ParameterList/>
				</Action>
			</Script>
			<ScriptGroup
				id="Counter zombies__5">
				<Script
					id="Counter__5">
					<Action
						Type="SET_PLAYER_KILLS_OF_KINDOF_TO_COUNTER">
						<ParameterList/>
					</Action>
				</Script>
			</ScriptGroup>
		</ScriptSet>
	</GameScriptList>
	<GameScriptList
		id="Player_4">
		<ScriptSet>
			<Script
				id="Friends__3">
				<Action
					Type="PLAYER_SET_OVERRIDE_RELATION_TO_TEAM">
					<ParameterList/>
				</Action>
				<Action
					Type="PLAYER_SET_OVERRIDE_RELATION_TO_TEAM">
					<ParameterList/>
				</Action>
				<Action
					Type="PLAYER_SET_OVERRIDE_RELATION_TO_TEAM">
					<ParameterList/>
				</Action>
			</Script>
			<ScriptGroup
				id="Counter zombies__6">
				<Script
					id="Counter__6">
					<Action
						Type="SET_PLAYER_KILLS_OF_KINDOF_TO_COUNTER">
						<ParameterList/>
					</Action>
				</Script>
			</ScriptGroup>
		</ScriptSet>
	</GameScriptList>
	<GameScriptList
		id="Player_5">
		<ScriptSet>
			<ScriptGroup
				id="money">
				<Script
					id="Money p5">
					<Action
						Type="PLAYER_SET_MONEY">
						<ParameterList/>
					</Action>
				</Script>
			</ScriptGroup>
			<ScriptGroup
				id="waves">
				<Script
					id="Winner">
					<Action
						Type="PLAYER_KILL">
						<ParameterList/>
					</Action>
				</Script>
				<Script
					id="Wave1">
					<Action
						Type="SET_MILLISECOND_TIMER">
						<ParameterList/>
					</Action>
					<Action
						Type="CREATE_REINFORCEMENT_TEAM">
						<ParameterList/>
					</Action>
					<Action
						Type="MOVE_TEAM_TO">
						<ParameterList/>
					</Action>
					<Action
						Type="CREATE_REINFORCEMENT_TEAM">
						<ParameterList/>
					</Action>
					<Action
						Type="MOVE_TEAM_TO">
						<ParameterList/>
					</Action>
					<Action
						Type="CREATE_REINFORCEMENT_TEAM">
						<ParameterList/>
					</Action>
					<Action
						Type="MOVE_TEAM_TO">
						<ParameterList/>
					</Action>
					<Action
						Type="CREATE_REINFORCEMENT_TEAM">
						<ParameterList/>
					</Action>
					<Action
						Type="MOVE_TEAM_TO">
						<ParameterList/>
					</Action>
					<Action
						Type="CREATE_REINFORCEMENT_TEAM">
						<ParameterList/>
					</Action>
					<Action
						Type="MOVE_TEAM_TO">
						<ParameterList/>
					</Action>
					<Action
						Type="CREATE_REINFORCEMENT_TEAM">
						<ParameterList/>
					</Action>
					<Action
						Type="MOVE_TEAM_TO">
						<ParameterList/>
					</Action>
					<Action
						Type="CREATE_REINFORCEMENT_TEAM">
						<ParameterList/>
					</Action>
					<Action
						Type="MOVE_TEAM_TO">
						<ParameterList/>
					</Action>
					<Action
						Type="CREATE_REINFORCEMENT_TEAM">
						<ParameterList/>
					</Action>
					<Action
						Type="MOVE_TEAM_TO">
						<ParameterList/>
					</Action>
				</Script>
				<Script
					id="Death1">
					<Action
						Type="TEAM_ATTACK_NAMED">
						<ParameterList/>
					</Action>
				</Script>
				<Script
					id="Wave2">
					<Action
						Type="SET_MILLISECOND_TIMER">
						<ParameterList/>
					</Action>
					<Action
						Type="CREATE_REINFORCEMENT_TEAM">
						<ParameterList/>
					</Action>
					<Action
						Type="MOVE_TEAM_TO">
						<ParameterList/>
					</Action>
					<Action
						Type="CREATE_REINFORCEMENT_TEAM">
						<ParameterList/>
					</Action>
					<Action
						Type="MOVE_TEAM_TO">
						<ParameterList/>
					</Action>
					<Action
						Type="CREATE_REINFORCEMENT_TEAM">
						<ParameterList/>
					</Action>
					<Action
						Type="MOVE_TEAM_TO">
						<ParameterList/>
					</Action>
					<Action
						Type="CREATE_REINFORCEMENT_TEAM">
						<ParameterList/>
					</Action>
					<Action
						Type="MOVE_TEAM_TO">
						<ParameterList/>
					</Action>
					<Action
						Type="CREATE_REINFORCEMENT_TEAM">
						<ParameterList/>
					</Action>
					<Action
						Type="MOVE_TEAM_TO">
						<ParameterList/>
					</Action>
					<Action
						Type="CREATE_REINFORCEMENT_TEAM">
						<ParameterList/>
					</Action>
					<Action
						Type="MOVE_TEAM_TO">
						<ParameterList/>
					</Action>
					<Action
						Type="CREATE_REINFORCEMENT_TEAM">
						<ParameterList/>
					</Action>
					<Action
						Type="MOVE_TEAM_TO">
						<ParameterList/>
					</Action>
					<Action
						Type="CREATE_REINFORCEMENT_TEAM">
						<ParameterList/>
					</Action>
					<Action
						Type="MOVE_TEAM_TO">
						<ParameterList/>
					</Action>
				</Script>
				<Script
					id="Death2">
					<Action
						Type="TEAM_ATTACK_NAMED">
						<ParameterList/>
					</Action>
				</Script>
				<Script
					id="Wave3">
					<Action
						Type="SET_MILLISECOND_TIMER">
						<ParameterList/>
					</Action>
					<Action
						Type="CREATE_REINFORCEMENT_TEAM">
						<ParameterList/>
					</Action>
					<Action
						Type="MOVE_TEAM_TO">
						<ParameterList/>
					</Action>
					<Action
						Type="CREATE_REINFORCEMENT_TEAM">
						<ParameterList/>
					</Action>
					<Action
						Type="MOVE_TEAM_TO">
						<ParameterList/>
					</Action>
					<Action
						Type="CREATE_REINFORCEMENT_TEAM">
						<ParameterList/>
					</Action>
					<Action
						Type="MOVE_TEAM_TO">
						<ParameterList/>
					</Action>
					<Action
						Type="CREATE_REINFORCEMENT_TEAM">
						<ParameterList/>
					</Action>
					<Action
						Type="MOVE_TEAM_TO">
						<ParameterList/>
					</Action>
					<Action
						Type="CREATE_REINFORCEMENT_TEAM">
						<ParameterList/>
					</Action>
					<Action
						Type="MOVE_TEAM_TO">
						<ParameterList/>
					</Action>
					<Action
						Type="CREATE_REINFORCEMENT_TEAM">
						<ParameterList/>
					</Action>
					<Action
						Type="MOVE_TEAM_TO">
						<ParameterList/>
					</Action>
					<Action
						Type="CREATE_REINFORCEMENT_TEAM">
						<ParameterList/>
					</Action>
					<Action
						Type="MOVE_TEAM_TO">
						<ParameterList/>
					</Action>
					<Action
						Type="CREATE_REINFORCEMENT_TEAM">
						<ParameterList/>
					</Action>
					<Action
						Type="MOVE_TEAM_TO">
						<ParameterList/>
					</Action>
				</Script>
				<Script
					id="Death3">
					<Action
						Type="TEAM_ATTACK_NAMED">
						<ParameterList/>
					</Action>
				</Script>
				<Script
					id="Wave4">
					<Action
						Type="SET_MILLISECOND_TIMER">
						<ParameterList/>
					</Action>
					<Action
						Type="CREATE_REINFORCEMENT_TEAM">
						<ParameterList/>
					</Action>
					<Action
						Type="MOVE_TEAM_TO">
						<ParameterList/>
					</Action>
					<Action
						Type="CREATE_REINFORCEMENT_TEAM">
						<ParameterList/>
					</Action>
					<Action
						Type="MOVE_TEAM_TO">
						<ParameterList/>
					</Action>
					<Action
						Type="CREATE_REINFORCEMENT_TEAM">
						<ParameterList/>
					</Action>
					<Action
						Type="MOVE_TEAM_TO">
						<ParameterList/>
					</Action>
					<Action
						Type="CREATE_REINFORCEMENT_TEAM">
						<ParameterList/>
					</Action>
					<Action
						Type="MOVE_TEAM_TO">
						<ParameterList/>
					</Action>
					<Action
						Type="CREATE_REINFORCEMENT_TEAM">
						<ParameterList/>
					</Action>
					<Action
						Type="MOVE_TEAM_TO">
						<ParameterList/>
					</Action>
					<Action
						Type="CREATE_REINFORCEMENT_TEAM">
						<ParameterList/>
					</Action>
					<Action
						Type="MOVE_TEAM_TO">
						<ParameterList/>
					</Action>
					<Action
						Type="CREATE_REINFORCEMENT_TEAM">
						<ParameterList/>
					</Action>
					<Action
						Type="MOVE_TEAM_TO">
						<ParameterList/>
					</Action>
					<Action
						Type="CREATE_REINFORCEMENT_TEAM">
						<ParameterList/>
					</Action>
					<Action
						Type="MOVE_TEAM_TO">
						<ParameterList/>
					</Action>
				</Script>
				<Script
					id="Death4">
					<Action
						Type="TEAM_ATTACK_NAMED">
						<ParameterList/>
					</Action>
				</Script>
				<Script
					id="Wave5">
					<Action
						Type="SET_MILLISECOND_TIMER">
						<ParameterList/>
					</Action>
					<Action
						Type="CREATE_REINFORCEMENT_TEAM">
						<ParameterList/>
					</Action>
					<Action
						Type="MOVE_TEAM_TO">
						<ParameterList/>
					</Action>
					<Action
						Type="CREATE_REINFORCEMENT_TEAM">
						<ParameterList/>
					</Action>
					<Action
						Type="MOVE_TEAM_TO">
						<ParameterList/>
					</Action>
					<Action
						Type="CREATE_REINFORCEMENT_TEAM">
						<ParameterList/>
					</Action>
					<Action
						Type="MOVE_TEAM_TO">
						<ParameterList/>
					</Action>
					<Action
						Type="CREATE_REINFORCEMENT_TEAM">
						<ParameterList/>
					</Action>
					<Action
						Type="MOVE_TEAM_TO">
						<ParameterList/>
					</Action>
					<Action
						Type="CREATE_REINFORCEMENT_TEAM">
						<ParameterList/>
					</Action>
					<Action
						Type="MOVE_TEAM_TO">
						<ParameterList/>
					</Action>
					<Action
						Type="CREATE_REINFORCEMENT_TEAM">
						<ParameterList/>
					</Action>
					<Action
						Type="MOVE_TEAM_TO">
						<ParameterList/>
					</Action>
					<Action
						Type="CREATE_REINFORCEMENT_TEAM">
						<ParameterList/>
					</Action>
					<Action
						Type="MOVE_TEAM_TO">
						<ParameterList/>
					</Action>
					<Action
						Type="CREATE_REINFORCEMENT_TEAM">
						<ParameterList/>
					</Action>
					<Action
						Type="MOVE_TEAM_TO">
						<ParameterList/>
					</Action>
				</Script>
				<Script
					id="Death5">
					<Action
						Type="TEAM_ATTACK_NAMED">
						<ParameterList/>
					</Action>
				</Script>
				<Script
					id="Wave6">
					<Action
						Type="SET_MILLISECOND_TIMER">
						<ParameterList/>
					</Action>
					<Action
						Type="CREATE_REINFORCEMENT_TEAM">
						<ParameterList/>
					</Action>
					<Action
						Type="ATTACK_MOVE_TEAM_TO">
						<ParameterList/>
					</Action>
					<Action
						Type="CREATE_REINFORCEMENT_TEAM">
						<ParameterList/>
					</Action>
					<Action
						Type="MOVE_TEAM_TO">
						<ParameterList/>
					</Action>
					<Action
						Type="CREATE_REINFORCEMENT_TEAM">
						<ParameterList/>
					</Action>
					<Action
						Type="ATTACK_MOVE_TEAM_TO">
						<ParameterList/>
					</Action>
					<Action
						Type="CREATE_REINFORCEMENT_TEAM">
						<ParameterList/>
					</Action>
					<Action
						Type="MOVE_TEAM_TO">
						<ParameterList/>
					</Action>
					<Action
						Type="CREATE_REINFORCEMENT_TEAM">
						<ParameterList/>
					</Action>
					<Action
						Type="ATTACK_MOVE_TEAM_TO">
						<ParameterList/>
					</Action>
					<Action
						Type="CREATE_REINFORCEMENT_TEAM">
						<ParameterList/>
					</Action>
					<Action
						Type="MOVE_TEAM_TO">
						<ParameterList/>
					</Action>
					<Action
						Type="CREATE_REINFORCEMENT_TEAM">
						<ParameterList/>
					</Action>
					<Action
						Type="ATTACK_MOVE_TEAM_TO">
						<ParameterList/>
					</Action>
					<Action
						Type="CREATE_REINFORCEMENT_TEAM">
						<ParameterList/>
					</Action>
					<Action
						Type="MOVE_TEAM_TO">
						<ParameterList/>
					</Action>
				</Script>
				<Script
					id="Death6">
					<Action
						Type="TEAM_ATTACK_NAMED">
						<ParameterList/>
					</Action>
				</Script>
				<Script
					id="Wave7">
					<Action
						Type="SET_MILLISECOND_TIMER">
						<ParameterList/>
					</Action>
					<Action
						Type="CREATE_REINFORCEMENT_TEAM">
						<ParameterList/>
					</Action>
					<Action
						Type="ATTACK_MOVE_TEAM_TO">
						<ParameterList/>
					</Action>
					<Action
						Type="CREATE_REINFORCEMENT_TEAM">
						<ParameterList/>
					</Action>
					<Action
						Type="MOVE_TEAM_TO">
						<ParameterList/>
					</Action>
					<Action
						Type="CREATE_REINFORCEMENT_TEAM">
						<ParameterList/>
					</Action>
					<Action
						Type="ATTACK_MOVE_TEAM_TO">
						<ParameterList/>
					</Action>
					<Action
						Type="CREATE_REINFORCEMENT_TEAM">
						<ParameterList/>
					</Action>
					<Action
						Type="MOVE_TEAM_TO">
						<ParameterList/>
					</Action>
					<Action
						Type="CREATE_REINFORCEMENT_TEAM">
						<ParameterList/>
					</Action>
					<Action
						Type="ATTACK_MOVE_TEAM_TO">
						<ParameterList/>
					</Action>
					<Action
						Type="CREATE_REINFORCEMENT_TEAM">
						<ParameterList/>
					</Action>
					<Action
						Type="MOVE_TEAM_TO">
						<ParameterList/>
					</Action>
					<Action
						Type="CREATE_REINFORCEMENT_TEAM">
						<ParameterList/>
					</Action>
					<Action
						Type="ATTACK_MOVE_TEAM_TO">
						<ParameterList/>
					</Action>
					<Action
						Type="CREATE_REINFORCEMENT_TEAM">
						<ParameterList/>
					</Action>
					<Action
						Type="MOVE_TEAM_TO">
						<ParameterList/>
					</Action>
				</Script>
				<Script
					id="Death7">
					<Action
						Type="TEAM_ATTACK_NAMED">
						<ParameterList/>
					</Action>
				</Script>
				<Script
					id="Wave8">
					<Action
						Type="SET_MILLISECOND_TIMER">
						<ParameterList/>
					</Action>
					<Action
						Type="CREATE_REINFORCEMENT_TEAM">
						<ParameterList/>
					</Action>
					<Action
						Type="ATTACK_MOVE_TEAM_TO">
						<ParameterList/>
					</Action>
					<Action
						Type="CREATE_REINFORCEMENT_TEAM">
						<ParameterList/>
					</Action>
					<Action
						Type="MOVE_TEAM_TO">
						<ParameterList/>
					</Action>
					<Action
						Type="CREATE_REINFORCEMENT_TEAM">
						<ParameterList/>
					</Action>
					<Action
						Type="ATTACK_MOVE_TEAM_TO">
						<ParameterList/>
					</Action>
					<Action
						Type="CREATE_REINFORCEMENT_TEAM">
						<ParameterList/>
					</Action>
					<Action
						Type="MOVE_TEAM_TO">
						<ParameterList/>
					</Action>
					<Action
						Type="CREATE_REINFORCEMENT_TEAM">
						<ParameterList/>
					</Action>
					<Action
						Type="ATTACK_MOVE_TEAM_TO">
						<ParameterList/>
					</Action>
					<Action
						Type="CREATE_REINFORCEMENT_TEAM">
						<ParameterList/>
					</Action>
					<Action
						Type="MOVE_TEAM_TO">
						<ParameterList/>
					</Action>
					<Action
						Type="CREATE_REINFORCEMENT_TEAM">
						<ParameterList/>
					</Action>
					<Action
						Type="ATTACK_MOVE_TEAM_TO">
						<ParameterList/>
					</Action>
					<Action
						Type="CREATE_REINFORCEMENT_TEAM">
						<ParameterList/>
					</Action>
					<Action
						Type="MOVE_TEAM_TO">
						<ParameterList/>
					</Action>
				</Script>
				<Script
					id="Death8">
					<Action
						Type="TEAM_ATTACK_NAMED">
						<ParameterList/>
					</Action>
				</Script>
				<Script
					id="Wave9">
					<Action
						Type="SET_MILLISECOND_TIMER">
						<ParameterList/>
					</Action>
					<Action
						Type="CREATE_REINFORCEMENT_TEAM">
						<ParameterList/>
					</Action>
					<Action
						Type="ATTACK_MOVE_TEAM_TO">
						<ParameterList/>
					</Action>
					<Action
						Type="CREATE_REINFORCEMENT_TEAM">
						<ParameterList/>
					</Action>
					<Action
						Type="MOVE_TEAM_TO">
						<ParameterList/>
					</Action>
					<Action
						Type="CREATE_REINFORCEMENT_TEAM">
						<ParameterList/>
					</Action>
					<Action
						Type="ATTACK_MOVE_TEAM_TO">
						<ParameterList/>
					</Action>
					<Action
						Type="CREATE_REINFORCEMENT_TEAM">
						<ParameterList/>
					</Action>
					<Action
						Type="MOVE_TEAM_TO">
						<ParameterList/>
					</Action>
					<Action
						Type="CREATE_REINFORCEMENT_TEAM">
						<ParameterList/>
					</Action>
					<Action
						Type="ATTACK_MOVE_TEAM_TO">
						<ParameterList/>
					</Action>
					<Action
						Type="CREATE_REINFORCEMENT_TEAM">
						<ParameterList/>
					</Action>
					<Action
						Type="MOVE_TEAM_TO">
						<ParameterList/>
					</Action>
					<Action
						Type="CREATE_REINFORCEMENT_TEAM">
						<ParameterList/>
					</Action>
					<Action
						Type="ATTACK_MOVE_TEAM_TO">
						<ParameterList/>
					</Action>
					<Action
						Type="CREATE_REINFORCEMENT_TEAM">
						<ParameterList/>
					</Action>
					<Action
						Type="MOVE_TEAM_TO">
						<ParameterList/>
					</Action>
				</Script>
				<Script
					id="Death9">
					<Action
						Type="TEAM_ATTACK_NAMED">
						<ParameterList/>
					</Action>
				</Script>
				<Script
					id="Wave10">
					<Action
						Type="CREATE_REINFORCEMENT_TEAM">
						<ParameterList/>
					</Action>
					<Action
						Type="ATTACK_MOVE_TEAM_TO">
						<ParameterList/>
					</Action>
					<Action
						Type="CREATE_REINFORCEMENT_TEAM">
						<ParameterList/>
					</Action>
					<Action
						Type="ATTACK_MOVE_TEAM_TO">
						<ParameterList/>
					</Action>
					<Action
						Type="CREATE_REINFORCEMENT_TEAM">
						<ParameterList/>
					</Action>
					<Action
						Type="ATTACK_MOVE_TEAM_TO">
						<ParameterList/>
					</Action>
					<Action
						Type="CREATE_REINFORCEMENT_TEAM">
						<ParameterList/>
					</Action>
					<Action
						Type="ATTACK_MOVE_TEAM_TO">
						<ParameterList/>
					</Action>
					<Action
						Type="CREATE_REINFORCEMENT_TEAM">
						<ParameterList/>
					</Action>
					<Action
						Type="ATTACK_MOVE_TEAM_TO">
						<ParameterList/>
					</Action>
					<Action
						Type="CREATE_REINFORCEMENT_TEAM">
						<ParameterList/>
					</Action>
					<Action
						Type="ATTACK_MOVE_TEAM_TO">
						<ParameterList/>
					</Action>
					<Action
						Type="CREATE_REINFORCEMENT_TEAM">
						<ParameterList/>
					</Action>
					<Action
						Type="ATTACK_MOVE_TEAM_TO">
						<ParameterList/>
					</Action>
					<Action
						Type="CREATE_REINFORCEMENT_TEAM">
						<ParameterList/>
					</Action>
					<Action
						Type="ATTACK_MOVE_TEAM_TO">
						<ParameterList/>
					</Action>
				</Script>
				<Script
					id="Death10">
					<Action
						Type="TEAM_ATTACK_NAMED">
						<ParameterList/>
					</Action>
				</Script>
			</ScriptGroup>
		</ScriptSet>
	</GameScriptList>
	<GameScriptList
		id="Player_6">
		<ScriptSet/>
	</GameScriptList>
	<GameScriptList
		id="Player_7">
		<ScriptSet/>
	</GameScriptList>
	<GameScriptList
		id="PlyrBlackHand">
		<ScriptSet/>
	</GameScriptList>
</AssetDeclaration>